Workbook
Name DB_Annee: 'TABLEAU DE BORD'!$C$7
Name DB_Domaine: 'TABLEAU DE BORD'!$K$7
Name DB_Donateur: 'TABLEAU DE BORD'!$L$12
Name DB_Mois: 'TABLEAU DE BORD'!$G$7
Name DB_Projet: 'TABLEAU DE BORD'!$H$12
Name DB_Zone: 'TABLEAU DE BORD'!$P$12
Name Liste_ActivitesID: OFFSET(ACTIVITES!$A$56,0,0,MAX(1,COUNTIF(ACTIVITES!$G$56:$G$105,"<>")),1)
Name Liste_ActivitesIDProjets: OFFSET(PROJETS!$A$56,0,0,MAX(1,COUNTIF(PROJETS!$C$56:$C$95,"<>")),1)
Name Liste_Annees: tbl_Annees[Annee]
Name Liste_AnneesFiltre: PARAMETRES!$B$738:$B$749
Name Liste_BudgetLignesID: OFFSET(BUDGET!$A$28,0,0,MAX(1,COUNTIF(BUDGET!$U$28:$U$67,"<>")),1)
Name Liste_CategoriesBeneficiaires: tbl_CategoriesBeneficiaires[Libelle]
Name Liste_CategoriesDepenses: tbl_CategoriesDepenses[Libelle]
Name Liste_Departements: PARAMETRES!$D$536:$D$586
Name Liste_DepensesID: OFFSET(DEPENSES!$A$119,0,0,MAX(1,COUNTIF(DEPENSES!$V$119:$V$168,"<>")),1)
Name Liste_Domaines: tbl_Domaines[Libelle]
Name Liste_DonateursDemandesID: DONATEURS!$A$308:$A$367
Name Liste_DonateursID: OFFSET(DONATEURS!$A$56,0,0,MAX(1,COUNTIF(DONATEURS!$B$56:$B$205,"<>")),1)
Name Liste_DonateursOpportunitesID: DONATEURS!$A$244:$A$303
Name Liste_Fonctions: tbl_Fonctions[Libelle]
Name Liste_FrequencesPaiement: PARAMETRES!$B$714:$B$718
Name Liste_ModesPaiement: tbl_ModesPaiement[Libelle]
Name Liste_Mois: tbl_Mois[Mois]
Name Liste_MotifsDepart: PARAMETRES!$B$703:$B$709
Name Liste_NiveauxCompetence: PARAMETRES!$B$695:$B$698
Name Liste_NiveauxHierarchiques: PARAMETRES!$B$666:$B$671
Name Liste_NiveauxPriorite: tbl_NiveauxPriorite[Libelle]
Name Liste_NiveauxRisque: tbl_NiveauxRisque[Libelle]
Name Liste_PartenairesID: PARTENAIRES!$A$56:$A$115
Name Liste_RecettesID: RECETTES!$A$39:$A$88
Name Liste_RHID: OFFSET('RESSOURCES HUMAINES'!$A$27,0,0,MAX(1,COUNTIF('RESSOURCES HUMAINES'!$B$27:$B$76,"<>")),1)
Name Liste_ServicesRH: PARAMETRES!$B$651:$B$662
Name Liste_Sexe: tbl_Sexe[Libelle]
Name Liste_SourcesFinancement: tbl_SourcesFinancement[Libelle]
Name Liste_StatutsActivites: tbl_StatutsActivites[Libelle]
Name Liste_StatutsBudget: tbl_StatutsBudget[Libelle]
Name Liste_StatutsConge: PARAMETRES!$B$686:$B$691
Name Liste_StatutsDocuments: tbl_StatutsDocuments[Libelle]
Name Liste_StatutsGeneraux: tbl_StatutsGeneraux[Libelle]
Name Liste_StatutsProjets: tbl_StatutsProjets[Libelle]
Name Liste_StatutsRecettes: tbl_StatutsRecettes[Libelle]
Name Liste_StatutsRH: PARAMETRES!$B$640:$B$646
Name Liste_StatutsRisques: tbl_StatutsRisques[Libelle]
Name Liste_TranchesAge: tbl_TranchesAge[Libelle]
Name Liste_Trimestres: tbl_Trimestres[Code]
Name Liste_TypesActivites: tbl_TypesActivites[Libelle]
Name Liste_TypesBudget: tbl_TypesBudget[Libelle]
Name Liste_TypesConge: PARAMETRES!$B$676:$B$681
Name Liste_TypesContrats: tbl_TypesContrats[Libelle]
Name Liste_TypesDocuments: tbl_TypesDocuments[Libelle]
Name Liste_TypesDocumentsRH: PARAMETRES!$B$723:$B$734
Name Liste_TypesDonateurs: tbl_TypesDonateurs[Libelle]
Name Liste_TypesFinancement: tbl_TypesFinancement[Libelle]
Name Liste_TypesImmobilisations: tbl_TypesImmobilisations[Libelle]
Name Liste_TypesPartenaires: tbl_TypesPartenaires[Libelle]
Name Liste_TypesProjets: tbl_TypesProjets[Libelle]
Name Liste_TypesRecettes: tbl_TypesRecettes[Libelle]
Name Liste_UnitesMesure: tbl_UnitesMesure[Libelle]
Name Liste_ZonesGeo: PARAMETRES!$J$536:$J$586
Name Seuil_Depassement: PARAMETRES!$C$622

Sheet TABLEAU DE BORD
B1: O.N.G BK | TABLEAU DE BORD DE PILOTAGE | Y1: O.N.G BK | TABLEAU DE BORD DE PILOTAGE | AV1: O.N.G BK | TABLEAU DE BORD DE PILOTAGE
AA3: 2025 | AB3: Février | AC3: Formation professionnelle | AE3: Mars | AF3: =IF($C$7="Toutes les années",IF($K$7="Tous",SUMIFS(RECETTES!$AB$39:$AB$88,RECETTES!$X$39:$X$88,AE3),SUMIFS(RECETTES!$AB$39:$AB$88,RECETTES!$X$39:$X$88,AE3,RECETTES!$J$39:$J$88,$K$7)),IF($K$7="Tous",SUMIFS(RECETTES!$AB$39:$AB$88,RECETTES!$V$39:$V$88,$C$7,RECETTES!$X$39:$X$88,AE3),SUMIFS(RECETTES!$AB$39:$AB$88,RECETTES!$V$39:$V$88,$C$7,RECETTES!$X$39:$X$88,AE3,RECETTES!$J$39:$J$88,$K$7))) -> 0 | AG3: =IF($C$7="Toutes les années",IF($K$7="Tous",SUMIFS(DEPENSES!$AG$119:$AG$168,DEPENSES!$BO$119:$BO$168,AE3),SUMIFS(DEPENSES!$AG$119:$AG$168,DEPENSES!$BO$119:$BO$168,AE3,DEPENSES!$G$119:$G$168,$K$7)),IF($K$7="Tous",SUMIFS(DEPENSES!$AG$119:$AG$168,DEPENSES!$BM$119:$BM$168,$C$7,DEPENSES!$BO$119:$BO$168,AE3),SUMIFS(DEPENSES!$AG$119:$AG$168,DEPENSES!$BM$119:$BM$168,$C$7,DEPENSES!$BO$119:$BO$168,AE3,DEPENSES!$G$119:$G$168,$K$7))) -> 0 | AI3: Terminé | AJ3: =IF($C$7="Toutes les années",IF($K$7="Tous",COUNTIFS(PROJETS!$A$56:$A$95,"PROJ*",PROJETS!$AD$56:$AD$95,"Termine"),COUNTIFS(PROJETS!$A$56:$A$95,"PROJ*",PROJETS!$J$56:$J$95,$K$7,PROJETS!$AD$56:$AD$95,"Termine")),IF($K$7="Tous",COUNTIFS(PROJETS!$A$56:$A$95,"PROJ*",PROJETS!$AD$56:$AD$95,"Termine",PROJETS!$X$56:$X$95,">="&DATE($C$7,1,1),PROJETS!$X$56:$X$95,"<"&DATE($C$7+1,1,1)),COUNTIFS(PROJETS!$A$56:$A$95,"PROJ*",PROJETS!$J$56:$J$95,$K$7,PROJETS!$AD$56:$AD$95,"Termine",PROJETS!$X$56:$X$95,">="&DATE($C$7,1,1),PROJETS!$X$56:$X$95,"<"&DATE($C$7+1,1,1)))) -> 0 | AO3: Réalisée | AP3: =IF($C$7="Toutes les années",IF($K$7="Tous",COUNTIFS(ACTIVITES!$A$56:$A$105,"ACT*",ACTIVITES!$Z$56:$Z$105,"Realisee"),COUNTIFS(ACTIVITES!$A$56:$A$105,"ACT*",ACTIVITES!$K$56:$K$105,$K$7,ACTIVITES!$Z$56:$Z$105,"Realisee")),IF($K$7="Tous",COUNTIFS(ACTIVITES!$A$56:$A$105,"ACT*",ACTIVITES!$S$56:$S$105,$C$7,ACTIVITES!$Z$56:$Z$105,"Realisee"),COUNTIFS(ACTIVITES!$A$56:$A$105,"ACT*",ACTIVITES!$K$56:$K$105,$K$7,ACTIVITES!$S$56:$S$105,$C$7,ACTIVITES!$Z$56:$Z$105,"Realisee"))) -> 0 | AR3: 2025 | AS3: =COUNTIFS(PROJETS!$A$56:$A$95,"PROJ*",PROJETS!$X$56:$X$95,">="&DATE(AR3,1,1),PROJETS!$X$56:$X$95,"<"&DATE(AR3+1,1,1)) -> 0 | AT3: =COUNTIFS(BENEFICIAIRES!$A$56:$A$115,"BEN*",BENEFICIAIRES!$BB$56:$BB$115,">="&DATE(AR3,1,1),BENEFICIAIRES!$BB$56:$BB$115,"<"&DATE(AR3+1,1,1)) -> 0 | AU3: =SUMIFS(RECETTES!$AB$39:$AB$88,RECETTES!$V$39:$V$88,AR3) -> 0 | AV3: =SUMIFS(DEPENSES!$AG$119:$AG$168,DEPENSES!$BM$119:$BM$168,AR3) -> 0 | AW3: =COUNTIFS(ACTIVITES!$A$56:$A$105,"ACT*",ACTIVITES!$S$56:$S$105,AR3,ACTIVITES!$Z$56:$Z$105,"Realisee") -> 0 | AX3: =AR2 -> 0 | AY3: =AS2 -> 0 | AZ3: Février | BA3: =IF($C$7="Toutes les années",SUMIFS(RECETTES!$AB$39:$AB$88,RECETTES!$V$39:$V$88,2026,RECETTES!$W$39:$W$88,2),SUMIFS(RECETTES!$AB$39:$AB$88,RECETTES!$V$39:$V$88,$C$7,RECETTES!$W$39:$W$88,2)) -> 0 | BB3: =IF($C$7="Toutes les années",SUMIFS(DEPENSES!$AG$119:$AG$168,DEPENSES!$BM$119:$BM$168,2026,DEPENSES!$BN$119:$BN$168,2),SUMIFS(DEPENSES!$AG$119:$AG$168,DEPENSES!$BM$119:$BM$168,$C$7,DEPENSES!$BN$119:$BN$168,2)) -> 0 | BC3: =BA3-BB3 -> 0 | BE3: =AE2 -> 0 | BF3: =AF2 -> 0 | BG3: =AG2 -> 0 | BI3: =AI2 -> 0 | BJ3: =AJ2 -> 0 | BL3: =AL2 -> 0 | BM3: =AM2 -> 0 | BO3: =AO2 -> 0 | BP3: =AP2 -> 0
AA4: 2026 | AB4: Mars | AC4: Entrepreneuriat | AE4: Avril | AF4: =IF($C$7="Toutes les années",IF($K$7="Tous",SUMIFS(RECETTES!$AB$39:$AB$88,RECETTES!$X$39:$X$88,AE4),SUMIFS(RECETTES!$AB$39:$AB$88,RECETTES!$X$39:$X$88,AE4,RECETTES!$J$39:$J$88,$K$7)),IF($K$7="Tous",SUMIFS(RECETTES!$AB$39:$AB$88,RECETTES!$V$39:$V$88,$C$7,RECETTES!$X$39:$X$88,AE4),SUMIFS(RECETTES!$AB$39:$AB$88,RECETTES!$V$39:$V$88,$C$7,RECETTES!$X$39:$X$88,AE4,RECETTES!$J$39:$J$88,$K$7))) -> 0 | AG4: =IF($C$7="Toutes les années",IF($K$7="Tous",SUMIFS(DEPENSES!$AG$119:$AG$168,DEPENSES!$BO$119:$BO$168,AE4),SUMIFS(DEPENSES!$AG$119:$AG$168,DEPENSES!$BO$119:$BO$168,AE4,DEPENSES!$G$119:$G$168,$K$7)),IF($K$7="Tous",SUMIFS(DEPENSES!$AG$119:$AG$168,DEPENSES!$BM$119:$BM$168,$C$7,DEPENSES!$BO$119:$BO$168,AE4),SUMIFS(DEPENSES!$AG$119:$AG$168,DEPENSES!$BM$119:$BM$168,$C$7,DEPENSES!$BO$119:$BO$168,AE4,DEPENSES!$G$119:$G$168,$K$7))) -> 0 | AI4: Suspendu | AJ4: =IF($C$7="Toutes les années",IF($K$7="Tous",COUNTIFS(PROJETS!$A$56:$A$95,"PROJ*",PROJETS!$AD$56:$AD$95,"Suspendu"),COUNTIFS(PROJETS!$A$56:$A$95,"PROJ*",PROJETS!$J$56:$J$95,$K$7,PROJETS!$AD$56:$AD$95,"Suspendu")),IF($K$7="Tous",COUNTIFS(PROJETS!$A$56:$A$95,"PROJ*",PROJETS!$AD$56:$AD$95,"Suspendu",PROJETS!$X$56:$X$95,">="&DATE($C$7,1,1),PROJETS!$X$56:$X$95,"<"&DATE($C$7+1,1,1)),COUNTIFS(PROJETS!$A$56:$A$95,"PROJ*",PROJETS!$J$56:$J$95,$K$7,PROJETS!$AD$56:$AD$95,"Suspendu",PROJETS!$X$56:$X$95,">="&DATE($C$7,1,1),PROJETS!$X$56:$X$95,"<"&DATE($C$7+1,1,1)))) -> 0 | AO4: Reportée | AP4: =IF($C$7="Toutes les années",IF($K$7="Tous",COUNTIFS(ACTIVITES!$A$56:$A$105,"ACT*",ACTIVITES!$Z$56:$Z$105,"Reportee"),COUNTIFS(ACTIVITES!$A$56:$A$105,"ACT*",ACTIVITES!$K$56:$K$105,$K$7,ACTIVITES!$Z$56:$Z$105,"Reportee")),IF($K$7="Tous",COUNTIFS(ACTIVITES!$A$56:$A$105,"ACT*",ACTIVITES!$S$56:$S$105,$C$7,ACTIVITES!$Z$56:$Z$105,"Reportee"),COUNTIFS(ACTIVITES!$A$56:$A$105,"ACT*",ACTIVITES!$K$56:$K$105,$K$7,ACTIVITES!$S$56:$S$105,$C$7,ACTIVITES!$Z$56:$Z$105,"Reportee"))) -> 0 | AR4: 2026 | AS4: =COUNTIFS(PROJETS!$A$56:$A$95,"PROJ*",PROJETS!$X$56:$X$95,">="&DATE(AR4,1,1),PROJETS!$X$56:$X$95,"<"&DATE(AR4+1,1,1)) -> 0 | AT4: =COUNTIFS(BENEFICIAIRES!$A$56:$A$115,"BEN*",BENEFICIAIRES!$BB$56:$BB$115,">="&DATE(AR4,1,1),BENEFICIAIRES!$BB$56:$BB$115,"<"&DATE(AR4+1,1,1)) -> 0 | AU4: =SUMIFS(RECETTES!$AB$39:$AB$88,RECETTES!$V$39:$V$88,AR4) -> 0 | AV4: =SUMIFS(DEPENSES!$AG$119:$AG$168,DEPENSES!$BM$119:$BM$168,AR4) -> 0 | AW4: =COUNTIFS(ACTIVITES!$A$56:$A$105,"ACT*",ACTIVITES!$S$56:$S$105,AR4,ACTIVITES!$Z$56:$Z$105,"Realisee") -> 0 | AX4: =AR3 -> 2025 | AY4: =AS3 -> 0 | AZ4: Mars | BA4: =IF($C$7="Toutes les années",SUMIFS(RECETTES!$AB$39:$AB$88,RECETTES!$V$39:$V$88,2026,RECETTES!$W$39:$W$88,3),SUMIFS(RECETTES!$AB$39:$AB$88,RECETTES!$V$39:$V$88,$C$7,RECETTES!$W$39:$W$88,3)) -> 0 | BB4: =IF($C$7="Toutes les années",SUMIFS(DEPENSES!$AG$119:$AG$168,DEPENSES!$BM$119:$BM$168,2026,DEPENSES!$BN$119:$BN$168,3),SUMIFS(DEPENSES!$AG$119:$AG$168,DEPENSES!$BM$119:$BM$168,$C$7,DEPENSES!$BN$119:$BN$168,3)) -> 0 | BC4: =BA4-BB4 -> 0 | BE4: =AE3 -> Mars | BF4: =AF3 -> 0 | BG4: =AG3 -> 0 | BI4: =AI3 -> Terminé | BJ4: =AJ3 -> 0 | BO4: =AO3 -> Réalisée | BP4: =AP3 -> 0
B5: FILTRES DE PILOTAGE | AA5: 2027 | AB5: Avril | AC5: Culture | AE5: Mai | AF5: =IF($C$7="Toutes les années",IF($K$7="Tous",SUMIFS(RECETTES!$AB$39:$AB$88,RECETTES!$X$39:$X$88,AE5),SUMIFS(RECETTES!$AB$39:$AB$88,RECETTES!$X$39:$X$88,AE5,RECETTES!$J$39:$J$88,$K$7)),IF($K$7="Tous",SUMIFS(RECETTES!$AB$39:$AB$88,RECETTES!$V$39:$V$88,$C$7,RECETTES!$X$39:$X$88,AE5),SUMIFS(RECETTES!$AB$39:$AB$88,RECETTES!$V$39:$V$88,$C$7,RECETTES!$X$39:$X$88,AE5,RECETTES!$J$39:$J$88,$K$7))) -> 0 | AG5: =IF($C$7="Toutes les années",IF($K$7="Tous",SUMIFS(DEPENSES!$AG$119:$AG$168,DEPENSES!$BO$119:$BO$168,AE5),SUMIFS(DEPENSES!$AG$119:$AG$168,DEPENSES!$BO$119:$BO$168,AE5,DEPENSES!$G$119:$G$168,$K$7)),IF($K$7="Tous",SUMIFS(DEPENSES!$AG$119:$AG$168,DEPENSES!$BM$119:$BM$168,$C$7,DEPENSES!$BO$119:$BO$168,AE5),SUMIFS(DEPENSES!$AG$119:$AG$168,DEPENSES!$BM$119:$BM$168,$C$7,DEPENSES!$BO$119:$BO$168,AE5,DEPENSES!$G$119:$G$168,$K$7))) -> 0 | AI5: Annulé | AJ5: =IF($C$7="Toutes les années",IF($K$7="Tous",COUNTIFS(PROJETS!$A$56:$A$95,"PROJ*",PROJETS!$AD$56:$AD$95,"Annule"),COUNTIFS(PROJETS!$A$56:$A$95,"PROJ*",PROJETS!$J$56:$J$95,$K$7,PROJETS!$AD$56:$AD$95,"Annule")),IF($K$7="Tous",COUNTIFS(PROJETS!$A$56:$A$95,"PROJ*",PROJETS!$AD$56:$AD$95,"Annule",PROJETS!$X$56:$X$95,">="&DATE($C$7,1,1),PROJETS!$X$56:$X$95,"<"&DATE($C$7+1,1,1)),COUNTIFS(PROJETS!$A$56:$A$95,"PROJ*",PROJETS!$J$56:$J$95,$K$7,PROJETS!$AD$56:$AD$95,"Annule",PROJETS!$X$56:$X$95,">="&DATE($C$7,1,1),PROJETS!$X$56:$X$95,"<"&DATE($C$7+1,1,1)))) -> 0 | AO5: Annulée | AP5: =IF($C$7="Toutes les années",IF($K$7="Tous",COUNTIFS(ACTIVITES!$A$56:$A$105,"ACT*",ACTIVITES!$Z$56:$Z$105,"Annulee"),COUNTIFS(ACTIVITES!$A$56:$A$105,"ACT*",ACTIVITES!$K$56:$K$105,$K$7,ACTIVITES!$Z$56:$Z$105,"Annulee")),IF($K$7="Tous",COUNTIFS(ACTIVITES!$A$56:$A$105,"ACT*",ACTIVITES!$S$56:$S$105,$C$7,ACTIVITES!$Z$56:$Z$105,"Annulee"),COUNTIFS(ACTIVITES!$A$56:$A$105,"ACT*",ACTIVITES!$K$56:$K$105,$K$7,ACTIVITES!$S$56:$S$105,$C$7,ACTIVITES!$Z$56:$Z$105,"Annulee"))) -> 0 | AR5: 2027 | AS5: =COUNTIFS(PROJETS!$A$56:$A$95,"PROJ*",PROJETS!$X$56:$X$95,">="&DATE(AR5,1,1),PROJETS!$X$56:$X$95,"<"&DATE(AR5+1,1,1)) -> 0 | AT5: =COUNTIFS(BENEFICIAIRES!$A$56:$A$115,"BEN*",BENEFICIAIRES!$BB$56:$BB$115,">="&DATE(AR5,1,1),BENEFICIAIRES!$BB$56:$BB$115,"<"&DATE(AR5+1,1,1)) -> 0 | AU5: =SUMIFS(RECETTES!$AB$39:$AB$88,RECETTES!$V$39:$V$88,AR5) -> 0 | AV5: =SUMIFS(DEPENSES!$AG$119:$AG$168,DEPENSES!$BM$119:$BM$168,AR5) -> 0 | AW5: =COUNTIFS(ACTIVITES!$A$56:$A$105,"ACT*",ACTIVITES!$S$56:$S$105,AR5,ACTIVITES!$Z$56:$Z$105,"Realisee") -> 0 | AX5: =AR4 -> 2026 | AY5: =AS4 -> 0 | AZ5: Avril | BA5: =IF($C$7="Toutes les années",SUMIFS(RECETTES!$AB$39:$AB$88,RECETTES!$V$39:$V$88,2026,RECETTES!$W$39:$W$88,4),SUMIFS(RECETTES!$AB$39:$AB$88,RECETTES!$V$39:$V$88,$C$7,RECETTES!$W$39:$W$88,4)) -> 0 | BB5: =IF($C$7="Toutes les années",SUMIFS(DEPENSES!$AG$119:$AG$168,DEPENSES!$BM$119:$BM$168,2026,DEPENSES!$BN$119:$BN$168,4),SUMIFS(DEPENSES!$AG$119:$AG$168,DEPENSES!$BM$119:$BM$168,$C$7,DEPENSES!$BN$119:$BN$168,4)) -> 0 | BC5: =BA5-BB5 -> 0 | BE5: =AE4 -> Avril | BF5: =AF4 -> 0 | BG5: =AG4 -> 0 | BI5: =AI4 -> Suspendu | BJ5: =AJ4 -> 0 | BO5: =AO4 -> Reportée | BP5: =AP4 -> 0
B6: ANNÉE | F6: MOIS | J6: DOMAINE | N6: Les indicateurs opérationnels et financiers suivent les filtres. Les référentiels institutionnels restent cumulatifs. | AA6: 2028 | AB6: Mai | AC6: Environnement | AE6: Juin | AF6: =IF($C$7="Toutes les années",IF($K$7="Tous",SUMIFS(RECETTES!$AB$39:$AB$88,RECETTES!$X$39:$X$88,AE6),SUMIFS(RECETTES!$AB$39:$AB$88,RECETTES!$X$39:$X$88,AE6,RECETTES!$J$39:$J$88,$K$7)),IF($K$7="Tous",SUMIFS(RECETTES!$AB$39:$AB$88,RECETTES!$V$39:$V$88,$C$7,RECETTES!$X$39:$X$88,AE6),SUMIFS(RECETTES!$AB$39:$AB$88,RECETTES!$V$39:$V$88,$C$7,RECETTES!$X$39:$X$88,AE6,RECETTES!$J$39:$J$88,$K$7))) -> 0 | AG6: =IF($C$7="Toutes les années",IF($K$7="Tous",SUMIFS(DEPENSES!$AG$119:$AG$168,DEPENSES!$BO$119:$BO$168,AE6),SUMIFS(DEPENSES!$AG$119:$AG$168,DEPENSES!$BO$119:$BO$168,AE6,DEPENSES!$G$119:$G$168,$K$7)),IF($K$7="Tous",SUMIFS(DEPENSES!$AG$119:$AG$168,DEPENSES!$BM$119:$BM$168,$C$7,DEPENSES!$BO$119:$BO$168,AE6),SUMIFS(DEPENSES!$AG$119:$AG$168,DEPENSES!$BM$119:$BM$168,$C$7,DEPENSES!$BO$119:$BO$168,AE6,DEPENSES!$G$119:$G$168,$K$7))) -> 0 | AR6: 2028 | AS6: =COUNTIFS(PROJETS!$A$56:$A$95,"PROJ*",PROJETS!$X$56:$X$95,">="&DATE(AR6,1,1),PROJETS!$X$56:$X$95,"<"&DATE(AR6+1,1,1)) -> 0 | AT6: =COUNTIFS(BENEFICIAIRES!$A$56:$A$115,"BEN*",BENEFICIAIRES!$BB$56:$BB$115,">="&DATE(AR6,1,1),BENEFICIAIRES!$BB$56:$BB$115,"<"&DATE(AR6+1,1,1)) -> 0 | AU6: =SUMIFS(RECETTES!$AB$39:$AB$88,RECETTES!$V$39:$V$88,AR6) -> 0 | AV6: =SUMIFS(DEPENSES!$AG$119:$AG$168,DEPENSES!$BM$119:$BM$168,AR6) -> 0 | AW6: =COUNTIFS(ACTIVITES!$A$56:$A$105,"ACT*",ACTIVITES!$S$56:$S$105,AR6,ACTIVITES!$Z$56:$Z$105,"Realisee") -> 0 | AX6: =AR5 -> 2027 | AY6: =AS5 -> 0 | AZ6: Mai | BA6: =IF($C$7="Toutes les années",SUMIFS(RECETTES!$AB$39:$AB$88,RECETTES!$V$39:$V$88,2026,RECETTES!$W$39:$W$88,5),SUMIFS(RECETTES!$AB$39:$AB$88,RECETTES!$V$39:$V$88,$C$7,RECETTES!$W$39:$W$88,5)) -> 0 | BB6: =IF($C$7="Toutes les années",SUMIFS(DEPENSES!$AG$119:$AG$168,DEPENSES!$BM$119:$BM$168,2026,DEPENSES!$BN$119:$BN$168,5),SUMIFS(DEPENSES!$AG$119:$AG$168,DEPENSES!$BM$119:$BM$168,$C$7,DEPENSES!$BN$119:$BN$168,5)) -> 0 | BC6: =BA6-BB6 -> 0 | BE6: =AE5 -> Mai | BF6: =AF5 -> 0 | BG6: =AG5 -> 0 | BI6: =AI5 -> Annulé | BJ6: =AJ5 -> 0 | BO6: =AO5 -> Annulée | BP6: =AP5 -> 0
C7: Toutes les années | G7: Tous les mois | K7: Tous | AA7: 2029 | AB7: Juin | AC7: Sante | AE7: Juillet | AF7: =IF($C$7="Toutes les années",IF($K$7="Tous",SUMIFS(RECETTES!$AB$39:$AB$88,RECETTES!$X$39:$X$88,AE7),SUMIFS(RECETTES!$AB$39:$AB$88,RECETTES!$X$39:$X$88,AE7,RECETTES!$J$39:$J$88,$K$7)),IF($K$7="Tous",SUMIFS(RECETTES!$AB$39:$AB$88,RECETTES!$V$39:$V$88,$C$7,RECETTES!$X$39:$X$88,AE7),SUMIFS(RECETTES!$AB$39:$AB$88,RECETTES!$V$39:$V$88,$C$7,RECETTES!$X$39:$X$88,AE7,RECETTES!$J$39:$J$88,$K$7))) -> 0 | AG7: =IF($C$7="Toutes les années",IF($K$7="Tous",SUMIFS(DEPENSES!$AG$119:$AG$168,DEPENSES!$BO$119:$BO$168,AE7),SUMIFS(DEPENSES!$AG$119:$AG$168,DEPENSES!$BO$119:$BO$168,AE7,DEPENSES!$G$119:$G$168,$K$7)),IF($K$7="Tous",SUMIFS(DEPENSES!$AG$119:$AG$168,DEPENSES!$BM$119:$BM$168,$C$7,DEPENSES!$BO$119:$BO$168,AE7),SUMIFS(DEPENSES!$AG$119:$AG$168,DEPENSES!$BM$119:$BM$168,$C$7,DEPENSES!$BO$119:$BO$168,AE7,DEPENSES!$G$119:$G$168,$K$7))) -> 0 | AR7: 2029 | AS7: =COUNTIFS(PROJETS!$A$56:$A$95,"PROJ*",PROJETS!$X$56:$X$95,">="&DATE(AR7,1,1),PROJETS!$X$56:$X$95,"<"&DATE(AR7+1,1,1)) -> 0 | AT7: =COUNTIFS(BENEFICIAIRES!$A$56:$A$115,"BEN*",BENEFICIAIRES!$BB$56:$BB$115,">="&DATE(AR7,1,1),BENEFICIAIRES!$BB$56:$BB$115,"<"&DATE(AR7+1,1,1)) -> 0 | AU7: =SUMIFS(RECETTES!$AB$39:$AB$88,RECETTES!$V$39:$V$88,AR7) -> 0 | AV7: =SUMIFS(DEPENSES!$AG$119:$AG$168,DEPENSES!$BM$119:$BM$168,AR7) -> 0 | AW7: =COUNTIFS(ACTIVITES!$A$56:$A$105,"ACT*",ACTIVITES!$S$56:$S$105,AR7,ACTIVITES!$Z$56:$Z$105,"Realisee") -> 0 | AX7: =AR6 -> 2028 | AY7: =AS6 -> 0 | AZ7: Juin | BA7: =IF($C$7="Toutes les années",SUMIFS(RECETTES!$AB$39:$AB$88,RECETTES!$V$39:$V$88,2026,RECETTES!$W$39:$W$88,6),SUMIFS(RECETTES!$AB$39:$AB$88,RECETTES!$V$39:$V$88,$C$7,RECETTES!$W$39:$W$88,6)) -> 0 | BB7: =IF($C$7="Toutes les années",SUMIFS(DEPENSES!$AG$119:$AG$168,DEPENSES!$BM$119:$BM$168,2026,DEPENSES!$BN$119:$BN$168,6),SUMIFS(DEPENSES!$AG$119:$AG$168,DEPENSES!$BM$119:$BM$168,$C$7,DEPENSES!$BN$119:$BN$168,6)) -> 0 | BC7: =BA7-BB7 -> 0 | BE7: =AE6 -> Juin | BF7: =AF6 -> 0 | BG7: =AG6 -> 0
AA8: 2030 | AB8: Juillet | AC8: Genre | AE8: Août | AF8: =IF($C$7="Toutes les années",IF($K$7="Tous",SUMIFS(RECETTES!$AB$39:$AB$88,RECETTES!$X$39:$X$88,AE8),SUMIFS(RECETTES!$AB$39:$AB$88,RECETTES!$X$39:$X$88,AE8,RECETTES!$J$39:$J$88,$K$7)),IF($K$7="Tous",SUMIFS(RECETTES!$AB$39:$AB$88,RECETTES!$V$39:$V$88,$C$7,RECETTES!$X$39:$X$88,AE8),SUMIFS(RECETTES!$AB$39:$AB$88,RECETTES!$V$39:$V$88,$C$7,RECETTES!$X$39:$X$88,AE8,RECETTES!$J$39:$J$88,$K$7))) -> 0 | AG8: =IF($C$7="Toutes les années",IF($K$7="Tous",SUMIFS(DEPENSES!$AG$119:$AG$168,DEPENSES!$BO$119:$BO$168,AE8),SUMIFS(DEPENSES!$AG$119:$AG$168,DEPENSES!$BO$119:$BO$168,AE8,DEPENSES!$G$119:$G$168,$K$7)),IF($K$7="Tous",SUMIFS(DEPENSES!$AG$119:$AG$168,DEPENSES!$BM$119:$BM$168,$C$7,DEPENSES!$BO$119:$BO$168,AE8),SUMIFS(DEPENSES!$AG$119:$AG$168,DEPENSES!$BM$119:$BM$168,$C$7,DEPENSES!$BO$119:$BO$168,AE8,DEPENSES!$G$119:$G$168,$K$7))) -> 0 | AR8: 2030 | AS8: =COUNTIFS(PROJETS!$A$56:$A$95,"PROJ*",PROJETS!$X$56:$X$95,">="&DATE(AR8,1,1),PROJETS!$X$56:$X$95,"<"&DATE(AR8+1,1,1)) -> 0 | AT8: =COUNTIFS(BENEFICIAIRES!$A$56:$A$115,"BEN*",BENEFICIAIRES!$BB$56:$BB$115,">="&DATE(AR8,1,1),BENEFICIAIRES!$BB$56:$BB$115,"<"&DATE(AR8+1,1,1)) -> 0 | AU8: =SUMIFS(RECETTES!$AB$39:$AB$88,RECETTES!$V$39:$V$88,AR8) -> 0 | AV8: =SUMIFS(DEPENSES!$AG$119:$AG$168,DEPENSES!$BM$119:$BM$168,AR8) -> 0 | AW8: =COUNTIFS(ACTIVITES!$A$56:$A$105,"ACT*",ACTIVITES!$S$56:$S$105,AR8,ACTIVITES!$Z$56:$Z$105,"Realisee") -> 0 | AX8: =AR7 -> 2029 | AY8: =AS7 -> 0 | AZ8: Juillet | BA8: =IF($C$7="Toutes les années",SUMIFS(RECETTES!$AB$39:$AB$88,RECETTES!$V$39:$V$88,2026,RECETTES!$W$39:$W$88,7),SUMIFS(RECETTES!$AB$39:$AB$88,RECETTES!$V$39:$V$88,$C$7,RECETTES!$W$39:$W$88,7)) -> 0 | BB8: =IF($C$7="Toutes les années",SUMIFS(DEPENSES!$AG$119:$AG$168,DEPENSES!$BM$119:$BM$168,2026,DEPENSES!$BN$119:$BN$168,7),SUMIFS(DEPENSES!$AG$119:$AG$168,DEPENSES!$BM$119:$BM$168,$C$7,DEPENSES!$BN$119:$BN$168,7)) -> 0 | BC8: =BA8-BB8 -> 0 | BE8: =AE7 -> Juillet | BF8: =AF7 -> 0 | BG8: =AG7 -> 0
AA9: 2031 | AB9: Août | AC9: Tourisme | AE9: Septembre | AF9: =IF($C$7="Toutes les années",IF($K$7="Tous",SUMIFS(RECETTES!$AB$39:$AB$88,RECETTES!$X$39:$X$88,AE9),SUMIFS(RECETTES!$AB$39:$AB$88,RECETTES!$X$39:$X$88,AE9,RECETTES!$J$39:$J$88,$K$7)),IF($K$7="Tous",SUMIFS(RECETTES!$AB$39:$AB$88,RECETTES!$V$39:$V$88,$C$7,RECETTES!$X$39:$X$88,AE9),SUMIFS(RECETTES!$AB$39:$AB$88,RECETTES!$V$39:$V$88,$C$7,RECETTES!$X$39:$X$88,AE9,RECETTES!$J$39:$J$88,$K$7))) -> 0 | AG9: =IF($C$7="Toutes les années",IF($K$7="Tous",SUMIFS(DEPENSES!$AG$119:$AG$168,DEPENSES!$BO$119:$BO$168,AE9),SUMIFS(DEPENSES!$AG$119:$AG$168,DEPENSES!$BO$119:$BO$168,AE9,DEPENSES!$G$119:$G$168,$K$7)),IF($K$7="Tous",SUMIFS(DEPENSES!$AG$119:$AG$168,DEPENSES!$BM$119:$BM$168,$C$7,DEPENSES!$BO$119:$BO$168,AE9),SUMIFS(DEPENSES!$AG$119:$AG$168,DEPENSES!$BM$119:$BM$168,$C$7,DEPENSES!$BO$119:$BO$168,AE9,DEPENSES!$G$119:$G$168,$K$7))) -> 0 | AR9: 2031 | AS9: =COUNTIFS(PROJETS!$A$56:$A$95,"PROJ*",PROJETS!$X$56:$X$95,">="&DATE(AR9,1,1),PROJETS!$X$56:$X$95,"<"&DATE(AR9+1,1,1)) -> 0 | AT9: =COUNTIFS(BENEFICIAIRES!$A$56:$A$115,"BEN*",BENEFICIAIRES!$BB$56:$BB$115,">="&DATE(AR9,1,1),BENEFICIAIRES!$BB$56:$BB$115,"<"&DATE(AR9+1,1,1)) -> 0 | AU9: =SUMIFS(RECETTES!$AB$39:$AB$88,RECETTES!$V$39:$V$88,AR9) -> 0 | AV9: =SUMIFS(DEPENSES!$AG$119:$AG$168,DEPENSES!$BM$119:$BM$168,AR9) -> 0 | AW9: =COUNTIFS(ACTIVITES!$A$56:$A$105,"ACT*",ACTIVITES!$S$56:$S$105,AR9,ACTIVITES!$Z$56:$Z$105,"Realisee") -> 0 | AX9: =AR8 -> 2030 | AY9: =AS8 -> 0 | AZ9: Août | BA9: =IF($C$7="Toutes les années",SUMIFS(RECETTES!$AB$39:$AB$88,RECETTES!$V$39:$V$88,2026,RECETTES!$W$39:$W$88,8),SUMIFS(RECETTES!$AB$39:$AB$88,RECETTES!$V$39:$V$88,$C$7,RECETTES!$W$39:$W$88,8)) -> 0 | BB9: =IF($C$7="Toutes les années",SUMIFS(DEPENSES!$AG$119:$AG$168,DEPENSES!$BM$119:$BM$168,2026,DEPENSES!$BN$119:$BN$168,8),SUMIFS(DEPENSES!$AG$119:$AG$168,DEPENSES!$BM$119:$BM$168,$C$7,DEPENSES!$BN$119:$BN$168,8)) -> 0 | BC9: =BA9-BB9 -> 0 | BE9: =AE8 -> Août | BF9: =AF8 -> 0 | BG9: =AG8 -> 0
B10: PROJETS | F10: BÉNÉFICIAIRES | J10: ACTIVITÉS RÉALISÉES | N10: BUDGET APPROUVÉ | R10: FINANCEMENTS REÇUS | V10: DÉPENSES | AA10: 2032 | AB10: Septembre | AC10: Sport | AE10: Octobre | AF10: =IF($C$7="Toutes les années",IF($K$7="Tous",SUMIFS(RECETTES!$AB$39:$AB$88,RECETTES!$X$39:$X$88,AE10),SUMIFS(RECETTES!$AB$39:$AB$88,RECETTES!$X$39:$X$88,AE10,RECETTES!$J$39:$J$88,$K$7)),IF($K$7="Tous",SUMIFS(RECETTES!$AB$39:$AB$88,RECETTES!$V$39:$V$88,$C$7,RECETTES!$X$39:$X$88,AE10),SUMIFS(RECETTES!$AB$39:$AB$88,RECETTES!$V$39:$V$88,$C$7,RECETTES!$X$39:$X$88,AE10,RECETTES!$J$39:$J$88,$K$7))) -> 0 | AG10: =IF($C$7="Toutes les années",IF($K$7="Tous",SUMIFS(DEPENSES!$AG$119:$AG$168,DEPENSES!$BO$119:$BO$168,AE10),SUMIFS(DEPENSES!$AG$119:$AG$168,DEPENSES!$BO$119:$BO$168,AE10,DEPENSES!$G$119:$G$168,$K$7)),IF($K$7="Tous",SUMIFS(DEPENSES!$AG$119:$AG$168,DEPENSES!$BM$119:$BM$168,$C$7,DEPENSES!$BO$119:$BO$168,AE10),SUMIFS(DEPENSES!$AG$119:$AG$168,DEPENSES!$BM$119:$BM$168,$C$7,DEPENSES!$BO$119:$BO$168,AE10,DEPENSES!$G$119:$G$168,$K$7))) -> 0 | AR10: 2032 | AS10: =COUNTIFS(PROJETS!$A$56:$A$95,"PROJ*",PROJETS!$X$56:$X$95,">="&DATE(AR10,1,1),PROJETS!$X$56:$X$95,"<"&DATE(AR10+1,1,1)) -> 0 | AT10: =COUNTIFS(BENEFICIAIRES!$A$56:$A$115,"BEN*",BENEFICIAIRES!$BB$56:$BB$115,">="&DATE(AR10,1,1),BENEFICIAIRES!$BB$56:$BB$115,"<"&DATE(AR10+1,1,1)) -> 0 | AU10: =SUMIFS(RECETTES!$AB$39:$AB$88,RECETTES!$V$39:$V$88,AR10) -> 0 | AV10: =SUMIFS(DEPENSES!$AG$119:$AG$168,DEPENSES!$BM$119:$BM$168,AR10) -> 0 | AW10: =COUNTIFS(ACTIVITES!$A$56:$A$105,"ACT*",ACTIVITES!$S$56:$S$105,AR10,ACTIVITES!$Z$56:$Z$105,"Realisee") -> 0 | AX10: =AR9 -> 2031 | AY10: =AS9 -> 0 | AZ10: Septembre | BA10: =IF($C$7="Toutes les années",SUMIFS(RECETTES!$AB$39:$AB$88,RECETTES!$V$39:$V$88,2026,RECETTES!$W$39:$W$88,9),SUMIFS(RECETTES!$AB$39:$AB$88,RECETTES!$V$39:$V$88,$C$7,RECETTES!$W$39:$W$88,9)) -> 0 | BB10: =IF($C$7="Toutes les années",SUMIFS(DEPENSES!$AG$119:$AG$168,DEPENSES!$BM$119:$BM$168,2026,DEPENSES!$BN$119:$BN$168,9),SUMIFS(DEPENSES!$AG$119:$AG$168,DEPENSES!$BM$119:$BM$168,$C$7,DEPENSES!$BN$119:$BN$168,9)) -> 0 | BC10: =BA10-BB10 -> 0 | BE10: =AE9 -> Septembre | BF10: =AF9 -> 0 | BG10: =AG9 -> 0
B11: =IF($C$7="Toutes les années",IF($K$7="Tous",COUNTIF(PROJETS!$A$56:$A$95,"PROJ*"),COUNTIFS(PROJETS!$A$56:$A$95,"PROJ*",PROJETS!$J$56:$J$95,$K$7)),IF($K$7="Tous",COUNTIFS(PROJETS!$A$56:$A$95,"PROJ*",PROJETS!$X$56:$X$95,">="&DATE($C$7,1,1),PROJETS!$X$56:$X$95,"<"&DATE($C$7+1,1,1)),COUNTIFS(PROJETS!$A$56:$A$95,"PROJ*",PROJETS!$J$56:$J$95,$K$7,PROJETS!$X$56:$X$95,">="&DATE($C$7,1,1),PROJETS!$X$56:$X$95,"<"&DATE($C$7+1,1,1)))) -> 1 | F11: =IF($C$7="Toutes les années",IF($K$7="Tous",COUNTIF(BENEFICIAIRES!$A$56:$A$115,"BEN*"),COUNTIFS(BENEFICIAIRES!$A$56:$A$115,"BEN*",BENEFICIAIRES!$BA$56:$BA$115,$K$7)),IF($K$7="Tous",COUNTIFS(BENEFICIAIRES!$A$56:$A$115,"BEN*",BENEFICIAIRES!$BB$56:$BB$115,">="&DATE($C$7,1,1),BENEFICIAIRES!$BB$56:$BB$115,"<"&DATE($C$7+1,1,1)),COUNTIFS(BENEFICIAIRES!$A$56:$A$115,"BEN*",BENEFICIAIRES!$BA$56:$BA$115,$K$7,BENEFICIAIRES!$BB$56:$BB$115,">="&DATE($C$7,1,1),BENEFICIAIRES!$BB$56:$BB$115,"<"&DATE($C$7+1,1,1)))) -> 1 | J11: =IF($C$7="Toutes les années",IF($K$7="Tous",COUNTIFS(ACTIVITES!$A$56:$A$105,"ACT*",ACTIVITES!$Z$56:$Z$105,"Realisee"),COUNTIFS(ACTIVITES!$A$56:$A$105,"ACT*",ACTIVITES!$K$56:$K$105,$K$7,ACTIVITES!$Z$56:$Z$105,"Realisee")),IF($K$7="Tous",IF($G$7="Tous les mois",COUNTIFS(ACTIVITES!$A$56:$A$105,"ACT*",ACTIVITES!$S$56:$S$105,$C$7,ACTIVITES!$Z$56:$Z$105,"Realisee"),COUNTIFS(ACTIVITES!$A$56:$A$105,"ACT*",ACTIVITES!$S$56:$S$105,$C$7,ACTIVITES!$Q$56:$Q$105,$G$7,ACTIVITES!$Z$56:$Z$105,"Realisee")),IF($G$7="Tous les mois",COUNTIFS(ACTIVITES!$A$56:$A$105,"ACT*",ACTIVITES!$K$56:$K$105,$K$7,ACTIVITES!$S$56:$S$105,$C$7,ACTIVITES!$Z$56:$Z$105,"Realisee"),COUNTIFS(ACTIVITES!$A$56:$A$105,"ACT*",ACTIVITES!$K$56:$K$105,$K$7,ACTIVITES!$S$56:$S$105,$C$7,ACTIVITES!$Q$56:$Q$105,$G$7,ACTIVITES!$Z$56:$Z$105,"Realisee")))) -> 0 | N11: =IF($C$7="Toutes les années",IF($K$7="Tous",SUM(BUDGET!$AB$28:$AB$67),SUMIFS(BUDGET!$AB$28:$AB$67,BUDGET!$J$28:$J$67,$K$7)),IF($K$7="Tous",SUMIFS(BUDGET!$AB$28:$AB$67,BUDGET!$B$28:$B$67,$C$7),SUMIFS(BUDGET!$AB$28:$AB$67,BUDGET!$B$28:$B$67,$C$7,BUDGET!$J$28:$J$67,$K$7))) -> 0 | R11: =IF($C$7="Toutes les années",IF($K$7="Tous",SUM(RECETTES!$AB$39:$AB$88),SUMIFS(RECETTES!$AB$39:$AB$88,RECETTES!$J$39:$J$88,$K$7)),IF($K$7="Tous",SUMIFS(RECETTES!$AB$39:$AB$88,RECETTES!$V$39:$V$88,$C$7),SUMIFS(RECETTES!$AB$39:$AB$88,RECETTES!$V$39:$V$88,$C$7,RECETTES!$J$39:$J$88,$K$7))) -> 0 | V11: =IF($C$7="Toutes les années",IF($K$7="Tous",SUM(DEPENSES!$AG$119:$AG$168),SUMIFS(DEPENSES!$AG$119:$AG$168,DEPENSES!$G$119:$G$168,$K$7)),IF($K$7="Tous",SUMIFS(DEPENSES!$AG$119:$AG$168,DEPENSES!$BM$119:$BM$168,$C$7),SUMIFS(DEPENSES!$AG$119:$AG$168,DEPENSES!$BM$119:$BM$168,$C$7,DEPENSES!$G$119:$G$168,$K$7))) -> 29999 | AA11: 2033 | AB11: Octobre | AC11: Agriculture et developpement rural | AE11: Novembre | AF11: =IF($C$7="Toutes les années",IF($K$7="Tous",SUMIFS(RECETTES!$AB$39:$AB$88,RECETTES!$X$39:$X$88,AE11),SUMIFS(RECETTES!$AB$39:$AB$88,RECETTES!$X$39:$X$88,AE11,RECETTES!$J$39:$J$88,$K$7)),IF($K$7="Tous",SUMIFS(RECETTES!$AB$39:$AB$88,RECETTES!$V$39:$V$88,$C$7,RECETTES!$X$39:$X$88,AE11),SUMIFS(RECETTES!$AB$39:$AB$88,RECETTES!$V$39:$V$88,$C$7,RECETTES!$X$39:$X$88,AE11,RECETTES!$J$39:$J$88,$K$7))) -> 0 | AG11: =IF($C$7="Toutes les années",IF($K$7="Tous",SUMIFS(DEPENSES!$AG$119:$AG$168,DEPENSES!$BO$119:$BO$168,AE11),SUMIFS(DEPENSES!$AG$119:$AG$168,DEPENSES!$BO$119:$BO$168,AE11,DEPENSES!$G$119:$G$168,$K$7)),IF($K$7="Tous",SUMIFS(DEPENSES!$AG$119:$AG$168,DEPENSES!$BM$119:$BM$168,$C$7,DEPENSES!$BO$119:$BO$168,AE11),SUMIFS(DEPENSES!$AG$119:$AG$168,DEPENSES!$BM$119:$BM$168,$C$7,DEPENSES!$BO$119:$BO$168,AE11,DEPENSES!$G$119:$G$168,$K$7))) -> 0 | AR11: 2033 | AS11: =COUNTIFS(PROJETS!$A$56:$A$95,"PROJ*",PROJETS!$X$56:$X$95,">="&DATE(AR11,1,1),PROJETS!$X$56:$X$95,"<"&DATE(AR11+1,1,1)) -> 0 | AT11: =COUNTIFS(BENEFICIAIRES!$A$56:$A$115,"BEN*",BENEFICIAIRES!$BB$56:$BB$115,">="&DATE(AR11,1,1),BENEFICIAIRES!$BB$56:$BB$115,"<"&DATE(AR11+1,1,1)) -> 0 | AU11: =SUMIFS(RECETTES!$AB$39:$AB$88,RECETTES!$V$39:$V$88,AR11) -> 0 | AV11: =SUMIFS(DEPENSES!$AG$119:$AG$168,DEPENSES!$BM$119:$BM$168,AR11) -> 0 | AW11: =COUNTIFS(ACTIVITES!$A$56:$A$105,"ACT*",ACTIVITES!$S$56:$S$105,AR11,ACTIVITES!$Z$56:$Z$105,"Realisee") -> 0 | AX11: =AR10 -> 2032 | AY11: =AS10 -> 0 | AZ11: Octobre | BA11: =IF($C$7="Toutes les années",SUMIFS(RECETTES!$AB$39:$AB$88,RECETTES!$V$39:$V$88,2026,RECETTES!$W$39:$W$88,10),SUMIFS(RECETTES!$AB$39:$AB$88,RECETTES!$V$39:$V$88,$C$7,RECETTES!$W$39:$W$88,10)) -> 0 | BB11: =IF($C$7="Toutes les années",SUMIFS(DEPENSES!$AG$119:$AG$168,DEPENSES!$BM$119:$BM$168,2026,DEPENSES!$BN$119:$BN$168,10),SUMIFS(DEPENSES!$AG$119:$AG$168,DEPENSES!$BM$119:$BM$168,$C$7,DEPENSES!$BN$119:$BN$168,10)) -> 0 | BC11: =BA11-BB11 -> 0 | BE11: =AE10 -> Octobre | BF11: =AF10 -> 0 | BG11: =AG10 -> 0
AB12: Novembre | AC12: Elevage | AE12: Décembre | AF12: =IF($C$7="Toutes les années",IF($K$7="Tous",SUMIFS(RECETTES!$AB$39:$AB$88,RECETTES!$X$39:$X$88,AE12),SUMIFS(RECETTES!$AB$39:$AB$88,RECETTES!$X$39:$X$88,AE12,RECETTES!$J$39:$J$88,$K$7)),IF($K$7="Tous",SUMIFS(RECETTES!$AB$39:$AB$88,RECETTES!$V$39:$V$88,$C$7,RECETTES!$X$39:$X$88,AE12),SUMIFS(RECETTES!$AB$39:$AB$88,RECETTES!$V$39:$V$88,$C$7,RECETTES!$X$39:$X$88,AE12,RECETTES!$J$39:$J$88,$K$7))) -> 0 | AG12: =IF($C$7="Toutes les années",IF($K$7="Tous",SUMIFS(DEPENSES!$AG$119:$AG$168,DEPENSES!$BO$119:$BO$168,AE12),SUMIFS(DEPENSES!$AG$119:$AG$168,DEPENSES!$BO$119:$BO$168,AE12,DEPENSES!$G$119:$G$168,$K$7)),IF($K$7="Tous",SUMIFS(DEPENSES!$AG$119:$AG$168,DEPENSES!$BM$119:$BM$168,$C$7,DEPENSES!$BO$119:$BO$168,AE12),SUMIFS(DEPENSES!$AG$119:$AG$168,DEPENSES!$BM$119:$BM$168,$C$7,DEPENSES!$BO$119:$BO$168,AE12,DEPENSES!$G$119:$G$168,$K$7))) -> 0 | AZ12: Novembre | BA12: =IF($C$7="Toutes les années",SUMIFS(RECETTES!$AB$39:$AB$88,RECETTES!$V$39:$V$88,2026,RECETTES!$W$39:$W$88,11),SUMIFS(RECETTES!$AB$39:$AB$88,RECETTES!$V$39:$V$88,$C$7,RECETTES!$W$39:$W$88,11)) -> 0 | BB12: =IF($C$7="Toutes les années",SUMIFS(DEPENSES!$AG$119:$AG$168,DEPENSES!$BM$119:$BM$168,2026,DEPENSES!$BN$119:$BN$168,11),SUMIFS(DEPENSES!$AG$119:$AG$168,DEPENSES!$BM$119:$BM$168,$C$7,DEPENSES!$BN$119:$BN$168,11)) -> 0 | BC12: =BA12-BB12 -> 0 | BE12: =AE11 -> Novembre | BF12: =AF11 -> 0 | BG12: =AG11 -> 0
AB13: Décembre | AC13: Peche et aquaculture | AZ13: Décembre | BA13: =IF($C$7="Toutes les années",SUMIFS(RECETTES!$AB$39:$AB$88,RECETTES!$V$39:$V$88,2026,RECETTES!$W$39:$W$88,12),SUMIFS(RECETTES!$AB$39:$AB$88,RECETTES!$V$39:$V$88,$C$7,RECETTES!$W$39:$W$88,12)) -> 0 | BB13: =IF($C$7="Toutes les années",SUMIFS(DEPENSES!$AG$119:$AG$168,DEPENSES!$BM$119:$BM$168,2026,DEPENSES!$BN$119:$BN$168,12),SUMIFS(DEPENSES!$AG$119:$AG$168,DEPENSES!$BM$119:$BM$168,$C$7,DEPENSES!$BN$119:$BN$168,12)) -> 0 | BC13: =BA13-BB13 -> 0 | BE13: =AE12 -> Décembre | BF13: =AF12 -> 0 | BG13: =AG12 -> 0
AC14: Securite alimentaire et nutrition
B15: SOLDE BUDGÉTAIRE | F15: TAUX D'EXÉCUTION | J15: PERFORMANCE PROJETS | N15: PARTENAIRES ACTIFS | R15: DONATEURS ACTIFS | V15: RH ACTIVES | AC15: Eau, hygiene et assainissement
B16: =N11-V11 -> -29999 | F16: =IFERROR(V11/N11,0) -> 0 | J16: =IF($C$7="Toutes les années",IFERROR(AVERAGEIF(PROJETS!$A$56:$A$95,"PROJ*",PROJETS!$BD$56:$BD$95),0),IFERROR(AVERAGEIFS(PROJETS!$BD$56:$BD$95,PROJETS!$A$56:$A$95,"PROJ*",PROJETS!$X$56:$X$95,">="&DATE($C$7,1,1),PROJETS!$X$56:$X$95,"<"&DATE($C$7+1,1,1)),0)) -> 0.45 | N16: =COUNTIFS(PARTENAIRES!$A$56:$A$115,"PART*",PARTENAIRES!$AN$56:$AN$115,"Actif") -> 0 | R16: =COUNTIFS(DONATEURS!$A$56:$A$205,"DON*",DONATEURS!$AB$56:$AB$205,"Actif") -> 0 | V16: =COUNTIFS('RESSOURCES HUMAINES'!$A$27:$A$76,"RH*",'RESSOURCES HUMAINES'!$P$27:$P$76,"Actif") -> 0 | AC16: Protection sociale
AC17: Protection de l'enfance
AC18: Jeunesse
AC19: Autonomisation des femmes
B20: FINANCES — RECETTES VS DÉPENSES | N20: PORTEFEUILLE DES PROJETS — STATUT | AC20: Developpement communautaire
AC21: Inclusion sociale
AC22: Handicap et inclusion des personnes vulnerables
AC23: Emploi et insertion professionnelle
AC24: Developpement economique local
AC25: Artisanat
AC26: Numerique et transformation digitale
AC27: Technologies et innovation
AC28: Recherche et developpement
AC29: Gouvernance et citoyennete
AC30: Droits humains
AC31: Paix, cohesion sociale et prevention des conflits
AC32: Action humanitaire et gestion des urgences
... AC34: Gestion durable des ressources naturelles
AA35: ALERTES | AC35: Biodiversite et conservation | AD35: FINANCES
B36: BÉNÉFICIAIRES — RÉPARTITION PAR SEXE | N36: ACTIVITÉS — STATUT D'AVANCEMENT | AA36: Projets en retard | AB36: =B54 -> 1 | AC36: Infrastructures et equipements communautaires | AD36: Budget approuvé | AE36: =N11 -> 0
AA37: Dépassements budgétaires | AB37: =J54 -> 0 | AC37: Developpement urbain et territorial | AD37: Financements reçus | AE37: =R11 -> 0
AA38: Dépenses en anomalie | AB38: =R54 -> 0 | AC38: Communication et information | AD38: Dépenses | AE38: =V11 -> 29999
AA39: S&E en alerte | AB39: =B57 -> 0 | AC39: Mobilite et echanges culturels
AA40: Activités en retard | AB40: =J57 -> 0 | AC40: Patrimoine et tourisme culturel
AA41: Donateurs à relancer | AB41: =R57 -> 0 | AC41: Autre domaine
B52: ÉVOLUTION & COURBES KPI — 2024 À 2033
B53: Projets en retard | J53: Projets en dépassement budgétaire | R53: Dépenses en anomalie
B54: =COUNTIFS(PROJETS!$A$56:$A$95,"PROJ*",PROJETS!$BE$56:$BE$95,"Oui") -> 1 | J54: =COUNTIFS(PROJETS!$A$56:$A$95,"PROJ*",PROJETS!$BG$56:$BG$95,"Oui") -> 0 | R54: =COUNTIFS(DEPENSES!$A$119:$A$168,"DEP*",DEPENSES!$BS$119:$BS$168,"<>Normal",DEPENSES!$BS$119:$BS$168,"<>") -> 0
B56: Indicateurs S&E en alerte | J56: Activités en retard | R56: Donateurs à relancer
B57: =COUNTIFS('SUIVI-EVALUATION'!$AY$55:$AY$104,"Oui") -> 0 | J57: =COUNTIFS(ACTIVITES!$A$56:$A$105,"ACT*",ACTIVITES!$AB$56:$AB$105,"Oui") -> 0 | R57: =COUNTIFS(DONATEURS!$AV$56:$AV$205,"Oui") -> 0
B60: ÉVOLUTION ANNUELLE — 2024 À 2033
B69: Source : données des feuilles du classeur O.N.G BK. Cette feuille est le seul élément modifié. Les listes déroulantes en haut permettent de changer la période d'analyse.
B71: ALERTES DE PILOTAGE | N71: STRUCTURE FINANCIÈRE
B72: Lecture rapide des points nécessitant une attention managériale et de la composition des flux financiers selon les filtres sélectionnés.
B89: Les graphiques se mettent à jour avec les filtres Année, Mois et Domaine. Les données techniques nécessaires aux graphiques sont masquées pour préserver la lisibilité.
A91: SUIVI DE L’EFFECTIF DES MEMBRES – ONG BK
A93: EFFECTIF TOTAL | C93: FEMMES | E93: HOMMES | G93: BUREAU EXÉCUTIF | I93: CCE
A94: =COUNTA(ONG!B270:B469) -> 14 | C94: =COUNTIF(ONG!D270:D469,"Femme") -> 6 | E94: =COUNTIF(ONG!D270:D469,"Homme") -> 8 | G94: =COUNTIF(ONG!H270:H469,"BE") -> 7 | I94: =COUNTIF(ONG!H270:H469,"CCE") -> 2
A97: Année | B97: Effectif total | C97: Femmes | D97: Hommes
A98: 2020 | B98: =ONG!O12 -> 0 | C98: =ONG!P12 -> 0 | D98: =ONG!Q12 -> 0
A99: 2021 | B99: =ONG!O13 -> 0 | C99: =ONG!P13 -> 0 | D99: =ONG!Q13 -> 0
A100: 2022 | B100: =ONG!O14 -> 0 | C100: =ONG!P14 -> 0 | D100: =ONG!Q14 -> 0
A101: 2023 | B101: =ONG!O15 -> 0 | C101: =ONG!P15 -> 0 | D101: =ONG!Q15 -> 0
A102: 2024 | B102: =ONG!O16 -> 14 | C102: =ONG!P16 -> 6 | D102: =ONG!Q16 -> 8
A103: 2025 | B103: =ONG!O17 -> 0 | C103: =ONG!P17 -> 0 | D103: =ONG!Q17 -> 0
A104: 2026 | B104: =ONG!O18 -> 0 | C104: =ONG!P18 -> 0 | D104: =ONG!Q18 -> 0
A105: 2027 | B105: =ONG!O19 -> 0 | C105: =ONG!P19 -> 0 | D105: =ONG!Q19 -> 0
A106: 2028 | B106: =ONG!O20 -> 0 | C106: =ONG!P20 -> 0 | D106: =ONG!Q20 -> 0
A107: 2029 | B107: =ONG!O21 -> 0 | C107: =ONG!P21 -> 0 | D107: =ONG!Q21 -> 0
A108: 2030 | B108: =ONG!O22 -> 0 | C108: =ONG!P22 -> 0 | D108: =ONG!Q22 -> 0
A109: 2031 | B109: =ONG!O23 -> 0 | C109: =ONG!P23 -> 0 | D109: =ONG!Q23 -> 0
... A113: 2035 | B113: =ONG!O27 -> 0 | C113: =ONG!P27 -> 0 | D113: =ONG!Q27 -> 0
A115: Femmes | B115: =COUNTIF(ONG!D270:D469,"Femme") -> 6
A116: Hommes | B116: =COUNTIF(ONG!D270:D469,"Homme") -> 8
A119: BE | B119: =COUNTIF(ONG!H270:H469,"BE") -> 7
A120: CCE | B120: =COUNTIF(ONG!H270:H469,"CCE") -> 2
A121: Membre | B121: =COUNTIF(ONG!H270:H469,"Membre") -> 5

Sheet ONG
A1: O.N.G BK — FICHE D'IDENTIFICATION ET D'INFORMATIONS INSTITUTIONNELLES | L1: SOMMAIRE ACTUALISÉ | N1: SOMMAIRE ACTUALISÉ – ONG BK
A2: Referentiel institutionnel du classeur — Donnons la joie a la jeunesse | L2: Total ONG | M2: =COUNTA(B270:B469) -> 14 | N2: Registre des membres | O2: =COUNTA(B270:B469) -> 14
A3: Date de derniere mise a jour : | D3: Annee de reference : | F3: Statut de l'organisation : | G3: Actif | L3: Femmes | M3: =COUNTIF(D270:D469,"Femme") -> 6 | N3: Effectif total | O3: =COUNTA(B270:B469) -> 14
L4: Hommes | M4: =COUNTIF(D270:D469,"Homme") -> 8 | N4: Femmes | O4: =COUNTIF(D270:D469,"Femme") -> 6
A5: LEGENDE : texte bleu = champ a completer par l'ONG | texte vert italique = recupere automatiquement depuis PARAMETRES (ou une future feuille) | valeur grisee en indicateur = sera calculee automatiquement des la creation de la feuille source correspondante | L5: BE | M5: =COUNTIF(H270:H469,"BE") -> 7 | N5: Hommes | O5: =COUNTIF(D270:D469,"Homme") -> 8
L6: Membres CCE | M6: =COUNTIF(H270:H469,"CCE") -> 2 | N6: Bureau exécutif (BE) | O6: =COUNTIF(H270:H469,"BE") -> 7
A7: SOMMAIRE — cliquez sur une section pour y acceder | N7: CCE | O7: =COUNTIF(H270:H469,"CCE") -> 2
A8: 1. IDENTITE DE L'ONG | G8: fiche | N8: Membres | O8: =COUNTIF(H270:H469,"Membre") -> 5
A9: 2. INFORMATIONS JURIDIQUES | G9: fiche
A10: 3. SIEGE ET LOCALISATION | G10: fiche
A11: 4. CONTACTS OFFICIELS | G11: tableau | N11: Année | O11: Effectif total | P11: Femmes | Q11: Hommes | R11: BE | S11: CCE
A12: 5. VISION | G12: zone de texte | N12: 2020 | O12: =COUNTIF($I$270:$I$469,N12) -> 0 | P12: =COUNTIFS($I$270:$I$469,N12,$D$270:$D$469,"Femme") -> 0 | Q12: =COUNTIFS($I$270:$I$469,N12,$D$270:$D$469,"Homme") -> 0 | R12: =COUNTIFS($I$270:$I$469,N12,$H$270:$H$469,"BE") -> 0 | S12: =COUNTIFS($I$270:$I$469,N12,$H$270:$H$469,"CCE") -> 0
A13: 6. MISSION | G13: zone de texte | N13: 2021 | O13: =COUNTIF($I$270:$I$469,N13) -> 0 | P13: =COUNTIFS($I$270:$I$469,N13,$D$270:$D$469,"Femme") -> 0 | Q13: =COUNTIFS($I$270:$I$469,N13,$D$270:$D$469,"Homme") -> 0 | R13: =COUNTIFS($I$270:$I$469,N13,$H$270:$H$469,"BE") -> 0 | S13: =COUNTIFS($I$270:$I$469,N13,$H$270:$H$469,"CCE") -> 0
A14: 7. VALEURS | G14: tableau | N14: 2022 | O14: =COUNTIF($I$270:$I$469,N14) -> 0 | P14: =COUNTIFS($I$270:$I$469,N14,$D$270:$D$469,"Femme") -> 0 | Q14: =COUNTIFS($I$270:$I$469,N14,$D$270:$D$469,"Homme") -> 0 | R14: =COUNTIFS($I$270:$I$469,N14,$H$270:$H$469,"BE") -> 0 | S14: =COUNTIFS($I$270:$I$469,N14,$H$270:$H$469,"CCE") -> 0
A15: 8. OBJECTIFS STRATEGIQUES | G15: tableau | N15: 2023 | O15: =COUNTIF($I$270:$I$469,N15) -> 0 | P15: =COUNTIFS($I$270:$I$469,N15,$D$270:$D$469,"Femme") -> 0 | Q15: =COUNTIFS($I$270:$I$469,N15,$D$270:$D$469,"Homme") -> 0 | R15: =COUNTIFS($I$270:$I$469,N15,$H$270:$H$469,"BE") -> 0 | S15: =COUNTIFS($I$270:$I$469,N15,$H$270:$H$469,"CCE") -> 0
A16: 9. DOMAINES D'INTERVENTION | G16: tableau | N16: 2024 | O16: =COUNTIF($I$270:$I$469,N16) -> 14 | P16: =COUNTIFS($I$270:$I$469,N16,$D$270:$D$469,"Femme") -> 6 | Q16: =COUNTIFS($I$270:$I$469,N16,$D$270:$D$469,"Homme") -> 8 | R16: =COUNTIFS($I$270:$I$469,N16,$H$270:$H$469,"BE") -> 7 | S16: =COUNTIFS($I$270:$I$469,N16,$H$270:$H$469,"CCE") -> 2
A17: 10. ZONES D'INTERVENTION | G17: tableau | N17: 2025 | O17: =COUNTIF($I$270:$I$469,N17) -> 0 | P17: =COUNTIFS($I$270:$I$469,N17,$D$270:$D$469,"Femme") -> 0 | Q17: =COUNTIFS($I$270:$I$469,N17,$D$270:$D$469,"Homme") -> 0 | R17: =COUNTIFS($I$270:$I$469,N17,$H$270:$H$469,"BE") -> 0 | S17: =COUNTIFS($I$270:$I$469,N17,$H$270:$H$469,"CCE") -> 0
A18: 11. ORGANISATION INTERNE | G18: tableau | N18: 2026 | O18: =COUNTIF($I$270:$I$469,N18) -> 0 | P18: =COUNTIFS($I$270:$I$469,N18,$D$270:$D$469,"Femme") -> 0 | Q18: =COUNTIFS($I$270:$I$469,N18,$D$270:$D$469,"Homme") -> 0 | R18: =COUNTIFS($I$270:$I$469,N18,$H$270:$H$469,"BE") -> 0 | S18: =COUNTIFS($I$270:$I$469,N18,$H$270:$H$469,"CCE") -> 0
A19: 12. EFFECTIF GLOBAL | G19: indicateurs | N19: 2027 | O19: =COUNTIF($I$270:$I$469,N19) -> 0 | P19: =COUNTIFS($I$270:$I$469,N19,$D$270:$D$469,"Femme") -> 0 | Q19: =COUNTIFS($I$270:$I$469,N19,$D$270:$D$469,"Homme") -> 0 | R19: =COUNTIFS($I$270:$I$469,N19,$H$270:$H$469,"BE") -> 0 | S19: =COUNTIFS($I$270:$I$469,N19,$H$270:$H$469,"CCE") -> 0
A20: 13. PARTENARIATS INSTITUTIONNELS | G20: tableau | N20: 2028 | O20: =COUNTIF($I$270:$I$469,N20) -> 0 | P20: =COUNTIFS($I$270:$I$469,N20,$D$270:$D$469,"Femme") -> 0 | Q20: =COUNTIFS($I$270:$I$469,N20,$D$270:$D$469,"Homme") -> 0 | R20: =COUNTIFS($I$270:$I$469,N20,$H$270:$H$469,"BE") -> 0 | S20: =COUNTIFS($I$270:$I$469,N20,$H$270:$H$469,"CCE") -> 0
A21: 14. SOURCES DE FINANCEMENT | G21: tableau | N21: 2029 | O21: =COUNTIF($I$270:$I$469,N21) -> 0 | P21: =COUNTIFS($I$270:$I$469,N21,$D$270:$D$469,"Femme") -> 0 | Q21: =COUNTIFS($I$270:$I$469,N21,$D$270:$D$469,"Homme") -> 0 | R21: =COUNTIFS($I$270:$I$469,N21,$H$270:$H$469,"BE") -> 0 | S21: =COUNTIFS($I$270:$I$469,N21,$H$270:$H$469,"CCE") -> 0
A22: 15. DOCUMENTS OFFICIELS | G22: tableau | N22: 2030 | O22: =COUNTIF($I$270:$I$469,N22) -> 0 | P22: =COUNTIFS($I$270:$I$469,N22,$D$270:$D$469,"Femme") -> 0 | Q22: =COUNTIFS($I$270:$I$469,N22,$D$270:$D$469,"Homme") -> 0 | R22: =COUNTIFS($I$270:$I$469,N22,$H$270:$H$469,"BE") -> 0 | S22: =COUNTIFS($I$270:$I$469,N22,$H$270:$H$469,"CCE") -> 0
A23: 16. INFORMATIONS BANCAIRES | G23: tableau | N23: 2031 | O23: =COUNTIF($I$270:$I$469,N23) -> 0 | P23: =COUNTIFS($I$270:$I$469,N23,$D$270:$D$469,"Femme") -> 0 | Q23: =COUNTIFS($I$270:$I$469,N23,$D$270:$D$469,"Homme") -> 0 | R23: =COUNTIFS($I$270:$I$469,N23,$H$270:$H$469,"BE") -> 0 | S23: =COUNTIFS($I$270:$I$469,N23,$H$270:$H$469,"CCE") -> 0
... A27: 20. GOUVERNANCE - ORGANES | G27: tableau | N27: 2035 | O27: =COUNTIF($I$270:$I$469,N27) -> 0 | P27: =COUNTIFS($I$270:$I$469,N27,$D$270:$D$469,"Femme") -> 0 | Q27: =COUNTIFS($I$270:$I$469,N27,$D$270:$D$469,"Homme") -> 0 | R27: =COUNTIFS($I$270:$I$469,N27,$H$270:$H$469,"BE") -> 0 | S27: =COUNTIFS($I$270:$I$469,N27,$H$270:$H$469,"CCE") -> 0
A28: 21. REUNIONS ET GOUVERNANCE | G28: tableau
A29: 22. INDICATEURS INSTITUTIONNELS | G29: indicateurs
A30: 23. HISTORIQUE DES MODIFICATIONS | G30: tableau
A32: 1. IDENTITE DE L'ONG
A33: Nom officiel de l'ONG | C33: O.N.G BK
A34: Sigle | C34: BK O.N.G
A35: Nom court | C35: BK
A36: Type d'organisation
A37: Statut juridique
A38: Date de creation
A39: Date de reconnaissance officielle
A40: Numero d'enregistrement
A41: Numero d'agrement
A42: Numero d'identification fiscale (si applicable)
A43: Pays d'enregistrement | C43: Congo
A44: Annee de creation
A45: Devise / slogan | C45: Donnons la joie a la jeunesse
A46: Site internet
A47: Adresse e-mail officielle
A48: Telephone officiel
A49: Adresse physique
A50: Adresse postale
A51: ↑ Retour au sommaire
A53: 2. INFORMATIONS JURIDIQUES
A54: Forme juridique
A55: Autorite ayant delivre l'agrement
A56: Numero d'agrement
A57: Date d'agrement
A58: Date d'expiration de l'agrement (si applicable)
... A62: Statut juridique
A63: Pays d'enregistrement | C63: Congo
A64: Juridiction competente
A65: Document justificatif principal
A66: ↑ Retour au sommaire
A68: 3. SIEGE ET LOCALISATION
A69: Localite de reference (PARAMETRES)
A70: Pays | C70: =IFERROR(INDEX(#REF!,MATCH($C$69,#REF!,0)),"")
A71: Departement / Province | C71: =IFERROR(INDEX(#REF!,MATCH($C$69,#REF!,0)),"")
A72: District / Commune | C72: =IFERROR(INDEX(#REF!,MATCH($C$69,#REF!,0)),"")
A73: Arrondissement | C73: =IFERROR(INDEX(#REF!,MATCH($C$69,#REF!,0)),"")
A74: Adresse (rue / avenue)
A75: Boite postale
A76: Telephone
A77: E-mail
A78: Coordonnees GPS (si disponibles)
A79: ↑ Retour au sommaire
A81: 4. CONTACTS OFFICIELS
A82: Fonction | B82: Nom complet | C82: Telephone | D82: Email | E82: Statut
A83: President | E83: Actif
A84: Directeur executif | E84: Actif
A85: Secretaire general | E85: Actif
A86: Responsable administratif et financier | E86: Actif
A87: Responsable des programmes | E87: Actif
A88: Responsable suivi-evaluation | E88: Actif
A89: Responsable communication | E89: Actif
A90: Responsable partenariats | E90: Actif
A91: ↑ Retour au sommaire
A93: 5. VISION
A98: ↑ Retour au sommaire
A100: 6. MISSION
A105: ↑ Retour au sommaire
A107: 7. VALEURS
A108: Code | B108: Valeur | C108: Description
A109: VAL01 | B109: Integrite
A110: VAL02 | B110: Solidarite
A111: VAL03 | B111: Inclusion
A112: VAL04 | B112: Responsabilite
A113: VAL05 | B113: Innovation
A114: VAL06 | B114: Transparence
A115: VAL07 | B115: Equite
A116: VAL08 | B116: Respect
A117: VAL09 | B117: Engagement
A118: ↑ Retour au sommaire
A120: 8. OBJECTIFS STRATEGIQUES
A121: Code | B121: Objectif strategique | C121: Description | D121: Periode | E121: Statut
A122: OS01 | B122: Exemple : Developper les competences des jeunes | C122: (ligne d'exemple - a remplacer/completer) | D122: 2026-2030 | E122: Actif
...

Sheet BENEFICIAIRES
A1: O.N.G BK — BASE DE DONNEES DES BENEFICIAIRES | Q1: -> ONG
A2: Annee de reference : | D2: 2026 | F2: Derniere mise a jour : | I2: =TODAY() -> 46305 | K2: Nombre total de beneficiaires : | O2: =COUNTIF(tbl_Beneficiaires[ID Beneficiaire],"BEN*") -> 1 | Q2: -> PARAMETRES
A4: LEGENDE : texte bleu = champ a completer manuellement | texte vert italique = donnee calculee automatiquement | ne pas modifier les colonnes calculees.
A6: SYNTHESE GENERALE (calcul automatique)
A7: Total beneficiaires | B7: Hommes | C7: Femmes | D7: Autres / non precise | E7: Enfants (0-17 ans) | F7: Jeunes (18-24 ans) | G7: Adultes (25-64 ans) | H7: Personnes agees (65+) | I7: Personnes handicap | J7: Menages distincts | K7: Actifs | L7: Sortis du programme | M7: Année sélectionnée | N7: Total
A8: =IF($N$7="Total",COUNTIF(A56:A115,"BEN*"),COUNTIFS(A56:A115,"BEN*",BB56:BB115,">="&DATE(VALUE($N$7),1,1),BB56:BB115,"<"&DATE(VALUE($N$7)+1,1,1))) -> 1 | B8: =IF($N$7="Total",COUNTIFS(A56:A115,"BEN*",H56:H115,"Masculin"),COUNTIFS(A56:A115,"BEN*",H56:H115,"Masculin",BB56:BB115,">="&DATE(VALUE($N$7),1,1),BB56:BB115,"<"&DATE(VALUE($N$7)+1,1,1))) -> 0 | C8: =IF($N$7="Total",COUNTIFS(A56:A115,"BEN*",H56:H115,"Feminin"),COUNTIFS(A56:A115,"BEN*",H56:H115,"Feminin",BB56:BB115,">="&DATE(VALUE($N$7),1,1),BB56:BB115,"<"&DATE(VALUE($N$7)+1,1,1))) -> 1 | D8: =IF($N$7="Total",COUNTIFS(A56:A115,"BEN*",H56:H115,"Non precise"),COUNTIFS(A56:A115,"BEN*",H56:H115,"Non precise",BB56:BB115,">="&DATE(VALUE($N$7),1,1),BB56:BB115,"<"&DATE(VALUE($N$7)+1,1,1))) -> 0 | E8: =IF($N$7="Total",COUNTIFS(A56:A115,"BEN*",J56:J115,"<18"),COUNTIFS(A56:A115,"BEN*",J56:J115,"<18",BB56:BB115,">="&DATE(VALUE($N$7),1,1),BB56:BB115,"<"&DATE(VALUE($N$7)+1,1,1))) -> 0 | F8: =IF($N$7="Total",COUNTIFS(A56:A115,"BEN*",J56:J115,">=18",J56:J115,"<=24"),COUNTIFS(A56:A115,"BEN*",J56:J115,">=18",J56:J115,"<=24",BB56:BB115,">="&DATE(VALUE($N$7),1,1),BB56:BB115,"<"&DATE(VALUE($N$7)+1,1,1))) -> 1 | G8: =IF($N$7="Total",COUNTIFS(A56:A115,"BEN*",J56:J115,">=25",J56:J115,"<=64"),COUNTIFS(A56:A115,"BEN*",J56:J115,">=25",J56:J115,"<=64",BB56:BB115,">="&DATE(VALUE($N$7),1,1),BB56:BB115,"<"&DATE(VALUE($N$7)+1,1,1))) -> 0 | H8: =IF($N$7="Total",COUNTIFS(A56:A115,"BEN*",J56:J115,">=65"),COUNTIFS(A56:A115,"BEN*",J56:J115,">=65",BB56:BB115,">="&DATE(VALUE($N$7),1,1),BB56:BB115,"<"&DATE(VALUE($N$7)+1,1,1))) -> 0 | I8: =IF($N$7="Total",COUNTIFS(A56:A115,"BEN*",V56:V115,"Oui"),COUNTIFS(A56:A115,"BEN*",V56:V115,"Oui",BB56:BB115,">="&DATE(VALUE($N$7),1,1),BB56:BB115,"<"&DATE(VALUE($N$7)+1,1,1))) -> 0 | J8: =IF($N$7="Total",SUMPRODUCT((N56:N115<>"")/COUNTIF(N56:N115,N56:N115&"")),SUMPRODUCT((N56:N115<>"")*(BB56:BB115>=DATE(VALUE($N$7),1,1))*(BB56:BB115<DATE(VALUE($N$7)+1,1,1))/COUNTIFS(N56:N115,N56:N115,BB56:BB115,">="&DATE(VALUE($N$7),1,1),BB56:BB115,"<"&DATE(VALUE($N$7)+1,1,1)))) -> 0 | K8: =IF($N$7="Total",COUNTIFS(A56:A115,"BEN*",BD56:BD115,"Actif"),COUNTIFS(A56:A115,"BEN*",BD56:BD115,"Actif",BB56:BB115,">="&DATE(VALUE($N$7),1,1),BB56:BB115,"<"&DATE(VALUE($N$7)+1,1,1))) -> 1 | L8: =IF($N$7="Total",COUNTIFS(A56:A115,"BEN*",BD56:BD115,"Sorti du programme"),COUNTIFS(A56:A115,"BEN*",BD56:BD115,"Sorti du programme",BB56:BB115,">="&DATE(VALUE($N$7),1,1),BB56:BB115,"<"&DATE(VALUE($N$7)+1,1,1))) -> 0
A10: ANALYSES AUTOMATIQUES (alimentent le futur TABLEAU DE BORD)
A11: Domaine d'intervention | B11: Nb beneficiaires | D11: Departement | E11: Nb beneficiaires | G11: Projet (nom) | H11: Nb beneficiaires
A12: Education | B12: =COUNTIFS(tbl_Beneficiaires[Domaine d''intervention],A12) -> 1 | D12: Brazzaville | E12: =COUNTIFS(tbl_Beneficiaires[Departement],D12) -> 1 | H12: =IF(G12="","",COUNTIFS(tbl_Beneficiaires[Nom du projet],G12))
A13: Formation professionnelle | B13: =COUNTIFS(tbl_Beneficiaires[Domaine d''intervention],A13) -> 0 | D13: Pointe-Noire | E13: =COUNTIFS(tbl_Beneficiaires[Departement],D13) -> 0 | H13: =IF(G13="","",COUNTIFS(tbl_Beneficiaires[Nom du projet],G13))
A14: Entrepreneuriat | B14: =COUNTIFS(tbl_Beneficiaires[Domaine d''intervention],A14) -> 0 | E14: =IF(D14="","",COUNTIFS(tbl_Beneficiaires[Departement],D14)) | H14: =IF(G14="","",COUNTIFS(tbl_Beneficiaires[Nom du projet],G14))
A15: Culture | B15: =COUNTIFS(tbl_Beneficiaires[Domaine d''intervention],A15) -> 0 | E15: =IF(D15="","",COUNTIFS(tbl_Beneficiaires[Departement],D15)) | H15: =IF(G15="","",COUNTIFS(tbl_Beneficiaires[Nom du projet],G15))
A16: Environnement | B16: =COUNTIFS(tbl_Beneficiaires[Domaine d''intervention],A16) -> 0 | E16: =IF(D16="","",COUNTIFS(tbl_Beneficiaires[Departement],D16)) | H16: =IF(G16="","",COUNTIFS(tbl_Beneficiaires[Nom du projet],G16))
A17: Sante | B17: =COUNTIFS(tbl_Beneficiaires[Domaine d''intervention],A17) -> 0 | E17: =IF(D17="","",COUNTIFS(tbl_Beneficiaires[Departement],D17)) | H17: =IF(G17="","",COUNTIFS(tbl_Beneficiaires[Nom du projet],G17))
A18: Genre | B18: =COUNTIFS(tbl_Beneficiaires[Domaine d''intervention],A18) -> 0 | E18: =IF(D18="","",COUNTIFS(tbl_Beneficiaires[Departement],D18)) | H18: =IF(G18="","",COUNTIFS(tbl_Beneficiaires[Nom du projet],G18))
A19: Tourisme | B19: =COUNTIFS(tbl_Beneficiaires[Domaine d''intervention],A19) -> 0 | E19: =IF(D19="","",COUNTIFS(tbl_Beneficiaires[Departement],D19)) | H19: =IF(G19="","",COUNTIFS(tbl_Beneficiaires[Nom du projet],G19))
A20: Sport | B20: =COUNTIFS(tbl_Beneficiaires[Domaine d''intervention],A20) -> 0 | E20: =IF(D20="","",COUNTIFS(tbl_Beneficiaires[Departement],D20)) | H20: =IF(G20="","",COUNTIFS(tbl_Beneficiaires[Nom du projet],G20))
A21: Agriculture et developpement rural | B21: =COUNTIFS(tbl_Beneficiaires[Domaine d''intervention],A21) -> 0 | E21: =IF(D21="","",COUNTIFS(tbl_Beneficiaires[Departement],D21)) | H21: =IF(G21="","",COUNTIFS(tbl_Beneficiaires[Nom du projet],G21))
A22: Elevage | B22: =COUNTIFS(tbl_Beneficiaires[Domaine d''intervention],A22) -> 0
A23: Peche et aquaculture | B23: =COUNTIFS(tbl_Beneficiaires[Domaine d''intervention],A23) -> 0 | G23: -> saisir un nom de projet par ligne ci-dessus ; a connecter automatiquement des la creation de la feuille PROJETS.
A24: Securite alimentaire et nutrition | B24: =COUNTIFS(tbl_Beneficiaires[Domaine d''intervention],A24) -> 0
A25: Eau, hygiene et assainissement | B25: =COUNTIFS(tbl_Beneficiaires[Domaine d''intervention],A25) -> 0
A26: Protection sociale | B26: =COUNTIFS(tbl_Beneficiaires[Domaine d''intervention],A26) -> 0
A27: Protection de l'enfance | B27: =COUNTIFS(tbl_Beneficiaires[Domaine d''intervention],A27) -> 0
A28: Jeunesse | B28: =COUNTIFS(tbl_Beneficiaires[Domaine d''intervention],A28) -> 0
A29: Autonomisation des femmes | B29: =COUNTIFS(tbl_Beneficiaires[Domaine d''intervention],A29) -> 0
A30: Developpement communautaire | B30: =COUNTIFS(tbl_Beneficiaires[Domaine d''intervention],A30) -> 0
A31: Inclusion sociale | B31: =COUNTIFS(tbl_Beneficiaires[Domaine d''intervention],A31) -> 0
A32: Handicap et inclusion des personnes vulnerables | B32: =COUNTIFS(tbl_Beneficiaires[Domaine d''intervention],A32) -> 0
A33: Emploi et insertion professionnelle | B33: =COUNTIFS(tbl_Beneficiaires[Domaine d''intervention],A33) -> 0
A34: Developpement economique local | B34: =COUNTIFS(tbl_Beneficiaires[Domaine d''intervention],A34) -> 0
A35: Artisanat | B35: =COUNTIFS(tbl_Beneficiaires[Domaine d''intervention],A35) -> 0
... A51: Autre domaine | B51: =COUNTIFS(tbl_Beneficiaires[Domaine d''intervention],A51) -> 0
A54: TABLEAU PRINCIPAL — LISTE DES BENEFICIAIRES
A55: ID Beneficiaire | B55: Type de beneficiaire | C55: Categorie beneficiaire | D55: Nom | E55: Postnom | F55: Prenom | G55: Nom complet | H55: Sexe | I55: Date de naissance | J55: Age | K55: Tranche d'age | L55: Situation matrimoniale | M55: Nationalite | N55: ID menage | O55: Nom du menage | P55: Taille du menage | Q55: Responsable du menage | R55: Nb hommes menage | S55: Nb femmes menage | T55: Nb enfants menage | U55: Nb pers. vulnerables menage | V55: Handicap | W55: Enfant vulnerable | X55: Pers. agee vulnerable | Y55: Femme vulnerable | Z55: Menage vulnerable | AA55: Personne deplacee | AB55: Autre vulnerabilite | AC55: Niveau instruction | AD55: Situation professionnelle | AE55: Profession | AF55: Secteur d'activite | AG55: Statut professionnel | AH55: Niveau de revenu | AI55: Activite generatrice revenus | AJ55: Statut entrepreneurial | AK55: Situation economique | AL55: Localite | AM55: Pays | AN55: Departement | AO55: District/Commune | AP55: Arrondissement | AQ55: Quartier/Village | AR55: Adresse / zone | AS55: Zone d'intervention | AT55: Telephone principal | AU55: Telephone secondaire | AV55: E-mail | AW55: Contact urgence (nom) | AX55: Telephone contact urgence | AY55: ID projet | AZ55: Nom du projet | BA55: Domaine d'intervention | BB55: Date integration projet | BC55: Statut ds le projet | BD55: Statut du beneficiaire | BE55: Date d'inscription | BF55: Date de sortie | BG55: Motif de sortie | BH55: Consentement obtenu | BI55: Autorisation usage donnees | BJ55: Autorisation photo | BK55: Autorisation communication | BL55: Source information | BM55: Date de collecte | BN55: ID agent | BO55: Nom de l'agent | BP55: Fonction agent | BQ55: Methode de collecte | BR55: Type de document | BS55: N° / reference document | BT55: Document verifie | BU55: Date de verification | BV55: Anciennete (annees) | BW55: Nb activites suivies | BX55: Nb appuis recus | BY55: Alerte doublon | BZ55: Observations
A56: =IF(D56="","","BEN"&TEXT(ROW()-55,"00000")) -> BEN00001 | B56: Individu | D56: MABIALA | E56: Nzoussi | F56: Christel | G56: =TRIM(D56&" "&E56&" "&F56) -> MABIALA Nzoussi Christel | H56: Feminin | I56: 37330 | J56: =IF(I56="","",DATEDIF(I56,TODAY(),"y")) -> 24 | K56: =IF(J56="","",IF(J56<5,"0-4 ans",IF(J56<10,"5-9 ans",IF(J56<15,"10-14 ans",IF(J56<18,"15-17 ans",IF(J56<25,"18-24 ans",IF(J56<35,"25-34 ans",IF(J56<45,"35-44 ans",IF(J56<55,"45-54 ans",IF(J56<65,"55-64 ans","65 ans et plus")))))))))) -> 18-24 ans | L56: Celibataire | V56: Non | AL56: Makélékélé | AM56: =IFERROR(INDEX(PARAMETRES!$B$536:$B$586,MATCH(AL56,PARAMETRES!$J$536:$J$586,0)),"") -> Congo | AN56: =IFERROR(INDEX(PARAMETRES!$D$536:$D$586,MATCH(AL56,PARAMETRES!$J$536:$J$586,0)),"") -> Brazzaville | AO56: =IFERROR(INDEX(PARAMETRES!$F$536:$F$586,MATCH(AL56,PARAMETRES!$J$536:$J$586,0)),"") -> Brazzaville | AP56: =IFERROR(INDEX(PARAMETRES!$G$536:$G$586,MATCH(AL56,PARAMETRES!$J$536:$J$586,0)),"") -> ARR01 | AY56: PROJ0001 | AZ56: Projet d'appui a l'insertion professionnelle des jeunes | BA56: Education | BC56: Actif | BD56: Actif | BE56: 45323 | BH56: Oui | BV56: =IF(BE56="","",DATEDIF(BE56,TODAY(),"y")) -> 2 | BW56: =COUNTIF(tbl_Beneficiaires_Activites[ID Beneficiaire],A56) -> 0 | BX56: =COUNTIF(tbl_Beneficiaires_Appuis[ID Beneficiaire],A56) -> 0 | BY56: =IF(D56="","",IF(COUNTIFS($D$56:$D$115,D56,$F$56:$F$115,F56,$I$56:$I$115,I56)>1,"DOUBLON POSSIBLE","OK")) -> OK
A57: =IF(D57="","","BEN"&TEXT(ROW()-55,"00000")) | G57: =TRIM(D57&" "&E57&" "&F57) | J57: =IF(I57="","",DATEDIF(I57,TODAY(),"y")) | K57: =IF(J57="","",IF(J57<5,"0-4 ans",IF(J57<10,"5-9 ans",IF(J57<15,"10-14 ans",IF(J57<18,"15-17 ans",IF(J57<25,"18-24 ans",IF(J57<35,"25-34 ans",IF(J57<45,"35-44 ans",IF(J57<55,"45-54 ans",IF(J57<65,"55-64 ans","65 ans et plus")))))))))) | AM57: =IFERROR(INDEX(PARAMETRES!$B$536:$B$586,MATCH(AL57,PARAMETRES!$J$536:$J$586,0)),"") | AN57: =IFERROR(INDEX(PARAMETRES!$D$536:$D$586,MATCH(AL57,PARAMETRES!$J$536:$J$586,0)),"") | AO57: =IFERROR(INDEX(PARAMETRES!$F$536:$F$586,MATCH(AL57,PARAMETRES!$J$536:$J$586,0)),"") | AP57: =IFERROR(INDEX(PARAMETRES!$G$536:$G$586,MATCH(AL57,PARAMETRES!$J$536:$J$586,0)),"") | BV57: =IF(BE57="","",DATEDIF(BE57,TODAY(),"y")) | BW57: =COUNTIF(tbl_Beneficiaires_Activites[ID Beneficiaire],A57) -> 40 | BX57: =COUNTIF(tbl_Beneficiaires_Appuis[ID Beneficiaire],A57) -> 40 | BY57: =IF(D57="","",IF(COUNTIFS($D$56:$D$115,D57,$F$56:$F$115,F57,$I$56:$I$115,I57)>1,"DOUBLON POSSIBLE","OK"))
A58: =IF(D58="","","BEN"&TEXT(ROW()-55,"00000")) | G58: =TRIM(D58&" "&E58&" "&F58) | J58: =IF(I58="","",DATEDIF(I58,TODAY(),"y")) | K58: =IF(J58="","",IF(J58<5,"0-4 ans",IF(J58<10,"5-9 ans",IF(J58<15,"10-14 ans",IF(J58<18,"15-17 ans",IF(J58<25,"18-24 ans",IF(J58<35,"25-34 ans",IF(J58<45,"35-44 ans",IF(J58<55,"45-54 ans",IF(J58<65,"55-64 ans","65 ans et plus")))))))))) | AM58: =IFERROR(INDEX(PARAMETRES!$B$536:$B$586,MATCH(AL58,PARAMETRES!$J$536:$J$586,0)),"") | AN58: =IFERROR(INDEX(PARAMETRES!$D$536:$D$586,MATCH(AL58,PARAMETRES!$J$536:$J$586,0)),"") | AO58: =IFERROR(INDEX(PARAMETRES!$F$536:$F$586,MATCH(AL58,PARAMETRES!$J$536:$J$586,0)),"") | AP58: =IFERROR(INDEX(PARAMETRES!$G$536:$G$586,MATCH(AL58,PARAMETRES!$J$536:$J$586,0)),"") | BV58: =IF(BE58="","",DATEDIF(BE58,TODAY(),"y")) | BW58: =COUNTIF(tbl_Beneficiaires_Activites[ID Beneficiaire],A58) -> 40 | BX58: =COUNTIF(tbl_Beneficiaires_Appuis[ID Beneficiaire],A58) -> 40 | BY58: =IF(D58="","",IF(COUNTIFS($D$56:$D$115,D58,$F$56:$F$115,F58,$I$56:$I$115,I58)>1,"DOUBLON POSSIBLE","OK"))
A59: =IF(D59="","","BEN"&TEXT(ROW()-55,"00000")) | G59: =TRIM(D59&" "&E59&" "&F59) | J59: =IF(I59="","",DATEDIF(I59,TODAY(),"y")) | K59: =IF(J59="","",IF(J59<5,"0-4 ans",IF(J59<10,"5-9 ans",IF(J59<15,"10-14 ans",IF(J59<18,"15-17 ans",IF(J59<25,"18-24 ans",IF(J59<35,"25-34 ans",IF(J59<45,"35-44 ans",IF(J59<55,"45-54 ans",IF(J59<65,"55-64 ans","65 ans et plus")))))))))) | AM59: =IFERROR(INDEX(PARAMETRES!$B$536:$B$586,MATCH(AL59,PARAMETRES!$J$536:$J$586,0)),"") | AN59: =IFERROR(INDEX(PARAMETRES!$D$536:$D$586,MATCH(AL59,PARAMETRES!$J$536:$J$586,0)),"") | AO59: =IFERROR(INDEX(PARAMETRES!$F$536:$F$586,MATCH(AL59,PARAMETRES!$J$536:$J$586,0)),"") | AP59: =IFERROR(INDEX(PARAMETRES!$G$536:$G$586,MATCH(AL59,PARAMETRES!$J$536:$J$586,0)),"") | BV59: =IF(BE59="","",DATEDIF(BE59,TODAY(),"y")) | BW59: =COUNTIF(tbl_Beneficiaires_Activites[ID Beneficiaire],A59) -> 40 | BX59: =COUNTIF(tbl_Beneficiaires_Appuis[ID Beneficiaire],A59) -> 40 | BY59: =IF(D59="","",IF(COUNTIFS($D$56:$D$115,D59,$F$56:$F$115,F59,$I$56:$I$115,I59)>1,"DOUBLON POSSIBLE","OK"))
A60: =IF(D60="","","BEN"&TEXT(ROW()-55,"00000")) | G60: =TRIM(D60&" "&E60&" "&F60) | J60: =IF(I60="","",DATEDIF(I60,TODAY(),"y")) | K60: =IF(J60="","",IF(J60<5,"0-4 ans",IF(J60<10,"5-9 ans",IF(J60<15,"10-14 ans",IF(J60<18,"15-17 ans",IF(J60<25,"18-24 ans",IF(J60<35,"25-34 ans",IF(J60<45,"35-44 ans",IF(J60<55,"45-54 ans",IF(J60<65,"55-64 ans","65 ans et plus")))))))))) | AM60: =IFERROR(INDEX(PARAMETRES!$B$536:$B$586,MATCH(AL60,PARAMETRES!$J$536:$J$586,0)),"") | AN60: =IFERROR(INDEX(PARAMETRES!$D$536:$D$586,MATCH(AL60,PARAMETRES!$J$536:$J$586,0)),"") | AO60: =IFERROR(INDEX(PARAMETRES!$F$536:$F$586,MATCH(AL60,PARAMETRES!$J$536:$J$586,0)),"") | AP60: =IFERROR(INDEX(PARAMETRES!$G$536:$G$586,MATCH(AL60,PARAMETRES!$J$536:$J$586,0)),"") | BV60: =IF(BE60="","",DATEDIF(BE60,TODAY(),"y")) | BW60: =COUNTIF(tbl_Beneficiaires_Activites[ID Beneficiaire],A60) -> 40 | BX60: =COUNTIF(tbl_Beneficiaires_Appuis[ID Beneficiaire],A60) -> 40 | BY60: =IF(D60="","",IF(COUNTIFS($D$56:$D$115,D60,$F$56:$F$115,F60,$I$56:$I$115,I60)>1,"DOUBLON POSSIBLE","OK"))
A61: =IF(D61="","","BEN"&TEXT(ROW()-55,"00000")) | G61: =TRIM(D61&" "&E61&" "&F61) | J61: =IF(I61="","",DATEDIF(I61,TODAY(),"y")) | K61: =IF(J61="","",IF(J61<5,"0-4 ans",IF(J61<10,"5-9 ans",IF(J61<15,"10-14 ans",IF(J61<18,"15-17 ans",IF(J61<25,"18-24 ans",IF(J61<35,"25-34 ans",IF(J61<45,"35-44 ans",IF(J61<55,"45-54 ans",IF(J61<65,"55-64 ans","65 ans et plus")))))))))) | AM61: =IFERROR(INDEX(PARAMETRES!$B$536:$B$586,MATCH(AL61,PARAMETRES!$J$536:$J$586,0)),"") | AN61: =IFERROR(INDEX(PARAMETRES!$D$536:$D$586,MATCH(AL61,PARAMETRES!$J$536:$J$586,0)),"") | AO61: =IFERROR(INDEX(PARAMETRES!$F$536:$F$586,MATCH(AL61,PARAMETRES!$J$536:$J$586,0)),"") | AP61: =IFERROR(INDEX(PARAMETRES!$G$536:$G$586,MATCH(AL61,PARAMETRES!$J$536:$J$586,0)),"") | BV61: =IF(BE61="","",DATEDIF(BE61,TODAY(),"y")) | BW61: =COUNTIF(tbl_Beneficiaires_Activites[ID Beneficiaire],A61) -> 40 | BX61: =COUNTIF(tbl_Beneficiaires_Appuis[ID Beneficiaire],A61) -> 40 | BY61: =IF(D61="","",IF(COUNTIFS($D$56:$D$115,D61,$F$56:$F$115,F61,$I$56:$I$115,I61)>1,"DOUBLON POSSIBLE","OK"))
A62: =IF(D62="","","BEN"&TEXT(ROW()-55,"00000")) | G62: =TRIM(D62&" "&E62&" "&F62) | J62: =IF(I62="","",DATEDIF(I62,TODAY(),"y")) | K62: =IF(J62="","",IF(J62<5,"0-4 ans",IF(J62<10,"5-9 ans",IF(J62<15,"10-14 ans",IF(J62<18,"15-17 ans",IF(J62<25,"18-24 ans",IF(J62<35,"25-34 ans",IF(J62<45,"35-44 ans",IF(J62<55,"45-54 ans",IF(J62<65,"55-64 ans","65 ans et plus")))))))))) | AM62: =IFERROR(INDEX(PARAMETRES!$B$536:$B$586,MATCH(AL62,PARAMETRES!$J$536:$J$586,0)),"") | AN62: =IFERROR(INDEX(PARAMETRES!$D$536:$D$586,MATCH(AL62,PARAMETRES!$J$536:$J$586,0)),"") | AO62: =IFERROR(INDEX(PARAMETRES!$F$536:$F$586,MATCH(AL62,PARAMETRES!$J$536:$J$586,0)),"") | AP62: =IFERROR(INDEX(PARAMETRES!$G$536:$G$586,MATCH(AL62,PARAMETRES!$J$536:$J$586,0)),"") | BV62: =IF(BE62="","",DATEDIF(BE62,TODAY(),"y")) | BW62: =COUNTIF(tbl_Beneficiaires_Activites[ID Beneficiaire],A62) -> 40 | BX62: =COUNTIF(tbl_Beneficiaires_Appuis[ID Beneficiaire],A62) -> 40 | BY62: =IF(D62="","",IF(COUNTIFS($D$56:$D$115,D62,$F$56:$F$115,F62,$I$56:$I$115,I62)>1,"DOUBLON POSSIBLE","OK"))
A63: =IF(D63="","","BEN"&TEXT(ROW()-55,"00000")) | G63: =TRIM(D63&" "&E63&" "&F63) | J63: =IF(I63="","",DATEDIF(I63,TODAY(),"y")) | K63: =IF(J63="","",IF(J63<5,"0-4 ans",IF(J63<10,"5-9 ans",IF(J63<15,"10-14 ans",IF(J63<18,"15-17 ans",IF(J63<25,"18-24 ans",IF(J63<35,"25-34 ans",IF(J63<45,"35-44 ans",IF(J63<55,"45-54 ans",IF(J63<65,"55-64 ans","65 ans et plus")))))))))) | AM63: =IFERROR(INDEX(PARAMETRES!$B$536:$B$586,MATCH(AL63,PARAMETRES!$J$536:$J$586,0)),"") | AN63: =IFERROR(INDEX(PARAMETRES!$D$536:$D$586,MATCH(AL63,PARAMETRES!$J$536:$J$586,0)),"") | AO63: =IFERROR(INDEX(PARAMETRES!$F$536:$F$586,MATCH(AL63,PARAMETRES!$J$536:$J$586,0)),"") | AP63: =IFERROR(INDEX(PARAMETRES!$G$536:$G$586,MATCH(AL63,PARAMETRES!$J$536:$J$586,0)),"") | BV63: =IF(BE63="","",DATEDIF(BE63,TODAY(),"y")) | BW63: =COUNTIF(tbl_Beneficiaires_Activites[ID Beneficiaire],A63) -> 40 | BX63: =COUNTIF(tbl_Beneficiaires_Appuis[ID Beneficiaire],A63) -> 40 | BY63: =IF(D63="","",IF(COUNTIFS($D$56:$D$115,D63,$F$56:$F$115,F63,$I$56:$I$115,I63)>1,"DOUBLON POSSIBLE","OK"))
A64: =IF(D64="","","BEN"&TEXT(ROW()-55,"00000")) | G64: =TRIM(D64&" "&E64&" "&F64) | J64: =IF(I64="","",DATEDIF(I64,TODAY(),"y")) | K64: =IF(J64="","",IF(J64<5,"0-4 ans",IF(J64<10,"5-9 ans",IF(J64<15,"10-14 ans",IF(J64<18,"15-17 ans",IF(J64<25,"18-24 ans",IF(J64<35,"25-34 ans",IF(J64<45,"35-44 ans",IF(J64<55,"45-54 ans",IF(J64<65,"55-64 ans","65 ans et plus")))))))))) | AM64: =IFERROR(INDEX(PARAMETRES!$B$536:$B$586,MATCH(AL64,PARAMETRES!$J$536:$J$586,0)),"") | AN64: =IFERROR(INDEX(PARAMETRES!$D$536:$D$586,MATCH(AL64,PARAMETRES!$J$536:$J$586,0)),"") | AO64: =IFERROR(INDEX(PARAMETRES!$F$536:$F$586,MATCH(AL64,PARAMETRES!$J$536:$J$586,0)),"") | AP64: =IFERROR(INDEX(PARAMETRES!$G$536:$G$586,MATCH(AL64,PARAMETRES!$J$536:$J$586,0)),"") | BV64: =IF(BE64="","",DATEDIF(BE64,TODAY(),"y")) | BW64: =COUNTIF(tbl_Beneficiaires_Activites[ID Beneficiaire],A64) -> 40 | BX64: =COUNTIF(tbl_Beneficiaires_Appuis[ID Beneficiaire],A64) -> 40 | BY64: =IF(D64="","",IF(COUNTIFS($D$56:$D$115,D64,$F$56:$F$115,F64,$I$56:$I$115,I64)>1,"DOUBLON POSSIBLE","OK"))
A65: =IF(D65="","","BEN"&TEXT(ROW()-55,"00000")) | G65: =TRIM(D65&" "&E65&" "&F65) | J65: =IF(I65="","",DATEDIF(I65,TODAY(),"y")) | K65: =IF(J65="","",IF(J65<5,"0-4 ans",IF(J65<10,"5-9 ans",IF(J65<15,"10-14 ans",IF(J65<18,"15-17 ans",IF(J65<25,"18-24 ans",IF(J65<35,"25-34 ans",IF(J65<45,"35-44 ans",IF(J65<55,"45-54 ans",IF(J65<65,"55-64 ans","65 ans et plus")))))))))) | AM65: =IFERROR(INDEX(PARAMETRES!$B$536:$B$586,MATCH(AL65,PARAMETRES!$J$536:$J$586,0)),"") | AN65: =IFERROR(INDEX(PARAMETRES!$D$536:$D$586,MATCH(AL65,PARAMETRES!$J$536:$J$586,0)),"") | AO65: =IFERROR(INDEX(PARAMETRES!$F$536:$F$586,MATCH(AL65,PARAMETRES!$J$536:$J$586,0)),"") | AP65: =IFERROR(INDEX(PARAMETRES!$G$536:$G$586,MATCH(AL65,PARAMETRES!$J$536:$J$586,0)),"") | BV65: =IF(BE65="","",DATEDIF(BE65,TODAY(),"y")) | BW65: =COUNTIF(tbl_Beneficiaires_Activites[ID Beneficiaire],A65) -> 40 | BX65: =COUNTIF(tbl_Beneficiaires_Appuis[ID Beneficiaire],A65) -> 40 | BY65: =IF(D65="","",IF(COUNTIFS($D$56:$D$115,D65,$F$56:$F$115,F65,$I$56:$I$115,I65)>1,"DOUBLON POSSIBLE","OK"))
A66: =IF(D66="","","BEN"&TEXT(ROW()-55,"00000")) | G66: =TRIM(D66&" "&E66&" "&F66) | J66: =IF(I66="","",DATEDIF(I66,TODAY(),"y")) | K66: =IF(J66="","",IF(J66<5,"0-4 ans",IF(J66<10,"5-9 ans",IF(J66<15,"10-14 ans",IF(J66<18,"15-17 ans",IF(J66<25,"18-24 ans",IF(J66<35,"25-34 ans",IF(J66<45,"35-44 ans",IF(J66<55,"45-54 ans",IF(J66<65,"55-64 ans","65 ans et plus")))))))))) | AM66: =IFERROR(INDEX(PARAMETRES!$B$536:$B$586,MATCH(AL66,PARAMETRES!$J$536:$J$586,0)),"") | AN66: =IFERROR(INDEX(PARAMETRES!$D$536:$D$586,MATCH(AL66,PARAMETRES!$J$536:$J$586,0)),"") | AO66: =IFERROR(INDEX(PARAMETRES!$F$536:$F$586,MATCH(AL66,PARAMETRES!$J$536:$J$586,0)),"") | AP66: =IFERROR(INDEX(PARAMETRES!$G$536:$G$586,MATCH(AL66,PARAMETRES!$J$536:$J$586,0)),"") | BV66: =IF(BE66="","",DATEDIF(BE66,TODAY(),"y")) | BW66: =COUNTIF(tbl_Beneficiaires_Activites[ID Beneficiaire],A66) -> 40 | BX66: =COUNTIF(tbl_Beneficiaires_Appuis[ID Beneficiaire],A66) -> 40 | BY66: =IF(D66="","",IF(COUNTIFS($D$56:$D$115,D66,$F$56:$F$115,F66,$I$56:$I$115,I66)>1,"DOUBLON POSSIBLE","OK"))
A67: =IF(D67="","","BEN"&TEXT(ROW()-55,"00000")) | G67: =TRIM(D67&" "&E67&" "&F67) | J67: =IF(I67="","",DATEDIF(I67,TODAY(),"y")) | K67: =IF(J67="","",IF(J67<5,"0-4 ans",IF(J67<10,"5-9 ans",IF(J67<15,"10-14 ans",IF(J67<18,"15-17 ans",IF(J67<25,"18-24 ans",IF(J67<35,"25-34 ans",IF(J67<45,"35-44 ans",IF(J67<55,"45-54 ans",IF(J67<65,"55-64 ans","65 ans et plus")))))))))) | AM67: =IFERROR(INDEX(PARAMETRES!$B$536:$B$586,MATCH(AL67,PARAMETRES!$J$536:$J$586,0)),"") | AN67: =IFERROR(INDEX(PARAMETRES!$D$536:$D$586,MATCH(AL67,PARAMETRES!$J$536:$J$586,0)),"") | AO67: =IFERROR(INDEX(PARAMETRES!$F$536:$F$586,MATCH(AL67,PARAMETRES!$J$536:$J$586,0)),"") | AP67: =IFERROR(INDEX(PARAMETRES!$G$536:$G$586,MATCH(AL67,PARAMETRES!$J$536:$J$586,0)),"") | BV67: =IF(BE67="","",DATEDIF(BE67,TODAY(),"y")) | BW67: =COUNTIF(tbl_Beneficiaires_Activites[ID Beneficiaire],A67) -> 40 | BX67: =COUNTIF(tbl_Beneficiaires_Appuis[ID Beneficiaire],A67) -> 40 | BY67: =IF(D67="","",IF(COUNTIFS($D$56:$D$115,D67,$F$56:$F$115,F67,$I$56:$I$115,I67)>1,"DOUBLON POSSIBLE","OK"))
A68: =IF(D68="","","BEN"&TEXT(ROW()-55,"00000")) | G68: =TRIM(D68&" "&E68&" "&F68) | J68: =IF(I68="","",DATEDIF(I68,TODAY(),"y")) | K68: =IF(J68="","",IF(J68<5,"0-4 ans",IF(J68<10,"5-9 ans",IF(J68<15,"10-14 ans",IF(J68<18,"15-17 ans",IF(J68<25,"18-24 ans",IF(J68<35,"25-34 ans",IF(J68<45,"35-44 ans",IF(J68<55,"45-54 ans",IF(J68<65,"55-64 ans","65 ans et plus")))))))))) | AM68: =IFERROR(INDEX(PARAMETRES!$B$536:$B$586,MATCH(AL68,PARAMETRES!$J$536:$J$586,0)),"") | AN68: =IFERROR(INDEX(PARAMETRES!$D$536:$D$586,MATCH(AL68,PARAMETRES!$J$536:$J$586,0)),"") | AO68: =IFERROR(INDEX(PARAMETRES!$F$536:$F$586,MATCH(AL68,PARAMETRES!$J$536:$J$586,0)),"") | AP68: =IFERROR(INDEX(PARAMETRES!$G$536:$G$586,MATCH(AL68,PARAMETRES!$J$536:$J$586,0)),"") | BV68: =IF(BE68="","",DATEDIF(BE68,TODAY(),"y")) | BW68: =COUNTIF(tbl_Beneficiaires_Activites[ID Beneficiaire],A68) -> 40 | BX68: =COUNTIF(tbl_Beneficiaires_Appuis[ID Beneficiaire],A68) -> 40 | BY68: =IF(D68="","",IF(COUNTIFS($D$56:$D$115,D68,$F$56:$F$115,F68,$I$56:$I$115,I68)>1,"DOUBLON POSSIBLE","OK"))
... A115: =IF(D115="","","BEN"&TEXT(ROW()-55,"00000")) | G115: =TRIM(D115&" "&E115&" "&F115) | J115: =IF(I115="","",DATEDIF(I115,TODAY(),"y")) | K115: =IF(J115="","",IF(J115<5,"0-4 ans",IF(J115<10,"5-9 ans",IF(J115<15,"10-14 ans",IF(J115<18,"15-17 ans",IF(J115<25,"18-24 ans",IF(J115<35,"25-34 ans",IF(J115<45,"35-44 ans",IF(J115<55,"45-54 ans",IF(J115<65,"55-64 ans","65 ans et plus")))))))))) | AM115: =IFERROR(INDEX(PARAMETRES!$B$536:$B$586,MATCH(AL115,PARAMETRES!$J$536:$J$586,0)),"") | AN115: =IFERROR(INDEX(PARAMETRES!$D$536:$D$586,MATCH(AL115,PARAMETRES!$J$536:$J$586,0)),"") | AO115: =IFERROR(INDEX(PARAMETRES!$F$536:$F$586,MATCH(AL115,PARAMETRES!$J$536:$J$586,0)),"") | AP115: =IFERROR(INDEX(PARAMETRES!$G$536:$G$586,MATCH(AL115,PARAMETRES!$J$536:$J$586,0)),"") | BV115: =IF(BE115="","",DATEDIF(BE115,TODAY(),"y")) | BW115: =COUNTIF(tbl_Beneficiaires_Activites[ID Beneficiaire],A115) -> 40 | BX115: =COUNTIF(tbl_Beneficiaires_Appuis[ID Beneficiaire],A115) -> 40 | BY115: =IF(D115="","",IF(COUNTIFS($D$56:$D$115,D115,$F$56:$F$115,F115,$I$56:$I$115,I115)>1,"DOUBLON POSSIBLE","OK"))
A118: PARTICIPATIONS AUX ACTIVITES (une ligne par participation — un beneficiaire peut en avoir plusieurs)
A119: ID Participation | B119: ID Beneficiaire | C119: ID activite | D119: Activite | E119: Type d'activite | F119: Date participation | G119: Presence | H119: Resultat | I119: Observation
A120: =IF(B120="","","PART"&TEXT(ROW()-119,"00000"))
A121: =IF(B121="","","PART"&TEXT(ROW()-119,"00000"))
A122: =IF(B122="","","PART"&TEXT(ROW()-119,"00000"))
A123: =IF(B123="","","PART"&TEXT(ROW()-119,"00000"))
A124: =IF(B124="","","PART"&TEXT(ROW()-119,"00000"))
A125: =IF(B125="","","PART"&TEXT(ROW()-119,"00000"))
A126: =IF(B126="","","PART"&TEXT(ROW()-119,"00000"))
A127: =IF(B127="","","PART"&TEXT(ROW()-119,"00000"))
A128: =IF(B128="","","PART"&TEXT(ROW()-119,"00000"))
A129: =IF(B129="","","PART"&TEXT(ROW()-119,"00000"))
A130: =IF(B130="","","PART"&TEXT(ROW()-119,"00000"))
A131: =IF(B131="","","PART"&TEXT(ROW()-119,"00000"))
... A159: =IF(B159="","","PART"&TEXT(ROW()-119,"00000"))
A162: APPUIS / SERVICES RECUS (une ligne par appui — un beneficiaire peut en avoir plusieurs)
A163: ID Appui | B163: ID Beneficiaire | C163: Date | D163: Type d'appui | E163: Quantite | F163: Valeur estimee | G163: Projet | H163: Observation
A164: =IF(B164="","","APP"&TEXT(ROW()-163,"00000"))
A165: =IF(B165="","","APP"&TEXT(ROW()-163,"00000"))
A166: =IF(B166="","","APP"&TEXT(ROW()-163,"00000"))
A167: =IF(B167="","","APP"&TEXT(ROW()-163,"00000"))
A168: =IF(B168="","","APP"&TEXT(ROW()-163,"00000"))
A169: =IF(B169="","","APP"&TEXT(ROW()-163,"00000"))
A170: =IF(B170="","","APP"&TEXT(ROW()-163,"00000"))
A171: =IF(B171="","","APP"&TEXT(ROW()-163,"00000"))
A172: =IF(B172="","","APP"&TEXT(ROW()-163,"00000"))
A173: =IF(B173="","","APP"&TEXT(ROW()-163,"00000"))
A174: =IF(B174="","","APP"&TEXT(ROW()-163,"00000"))
A175: =IF(B175="","","APP"&TEXT(ROW()-163,"00000"))
... A203: =IF(B203="","","APP"&TEXT(ROW()-163,"00000"))
A206: Note : les liens vers PROJETS, ACTIVITES, SUIVI-EVALUATION et RAPPORTS seront ajoutes automatiquement des que ces feuilles seront creees, afin de ne jamais generer de lien casse.

Sheet PROJETS
A1: O.N.G BK — GESTION DES PROJETS | Q1: -> ONG | R1: -> BENEFICIAIRES
A2: Derniere mise a jour : voir cellule ci-dessous — Cette feuille alimentera ACTIVITES, PARTENAIRES, DONATEURS, BUDGET, RECETTES/FINANCEMENTS, DEPENSES, RH, SUIVI-EVALUATION, RAPPORTS et TABLEAU DE BORD.
A4: LEGENDE : texte bleu = champ a completer manuellement | texte vert italique = donnee calculee automatiquement | ne pas modifier les colonnes calculees.
A6: SYNTHESE GENERALE DES PROJETS (calcul automatique)
A7: Total projets | B7: En preparation | C7: Soumis | D7: Approuves | E7: En cours | F7: Termines | G7: Suspendus | H7: Budget total approuve (FCFA) | I7: Financements recus (FCFA) | J7: Avancement moyen (%) | K7: Année sélectionnée | L7: Total
A8: =IF($L$7="Total",COUNTIF(A56:A95,"PROJ*"),COUNTIFS(A56:A95,"PROJ*",X56:X95,">="&DATE(VALUE($L$7),1,1),X56:X95,"<"&DATE(VALUE($L$7)+1,1,1))) -> 1 | B8: =IF($L$7="Total",COUNTIFS(A56:A95,"PROJ*",AD56:AD95,"En preparation"),COUNTIFS(A56:A95,"PROJ*",AD56:AD95,"En preparation",X56:X95,">="&DATE(VALUE($L$7),1,1),X56:X95,"<"&DATE(VALUE($L$7)+1,1,1))) -> 0 | C8: =IF($L$7="Total",COUNTIFS(A56:A95,"PROJ*",AD56:AD95,"Soumis"),COUNTIFS(A56:A95,"PROJ*",AD56:AD95,"Soumis",X56:X95,">="&DATE(VALUE($L$7),1,1),X56:X95,"<"&DATE(VALUE($L$7)+1,1,1))) -> 0 | D8: =IF($L$7="Total",COUNTIFS(A56:A95,"PROJ*",AD56:AD95,"Approuve"),COUNTIFS(A56:A95,"PROJ*",AD56:AD95,"Approuve",X56:X95,">="&DATE(VALUE($L$7),1,1),X56:X95,"<"&DATE(VALUE($L$7)+1,1,1))) -> 0 | E8: =IF($L$7="Total",COUNTIFS(A56:A95,"PROJ*",AD56:AD95,"En cours"),COUNTIFS(A56:A95,"PROJ*",AD56:AD95,"En cours",X56:X95,">="&DATE(VALUE($L$7),1,1),X56:X95,"<"&DATE(VALUE($L$7)+1,1,1))) -> 1 | F8: =IF($L$7="Total",COUNTIFS(A56:A95,"PROJ*",AD56:AD95,"Termine"),COUNTIFS(A56:A95,"PROJ*",AD56:AD95,"Termine",X56:X95,">="&DATE(VALUE($L$7),1,1),X56:X95,"<"&DATE(VALUE($L$7)+1,1,1))) -> 0 | G8: =IF($L$7="Total",COUNTIFS(A56:A95,"PROJ*",AD56:AD95,"Suspendu"),COUNTIFS(A56:A95,"PROJ*",AD56:AD95,"Suspendu",X56:X95,">="&DATE(VALUE($L$7),1,1),X56:X95,"<"&DATE(VALUE($L$7)+1,1,1))) -> 0 | H8: =IF($L$7="Total",SUM(AG56:AG95),SUMIFS(AG56:AG95,A56:A95,"PROJ*",X56:X95,">="&DATE(VALUE($L$7),1,1),X56:X95,"<"&DATE(VALUE($L$7)+1,1,1))) -> 11000000 | I8: =IF($L$7="Total",SUMIF(A56:A95,"PROJ*",AH56:AH95),SUMIFS(AH56:AH95,A56:A95,"PROJ*",X56:X95,">="&DATE(VALUE($L$7),1,1),X56:X95,"<"&DATE(VALUE($L$7)+1,1,1))) -> 6000000 | J8: =IF($L$7="Total",IFERROR(AVERAGEIF(A56:A95,"PROJ*",BD56:BD95),0),IFERROR(AVERAGEIFS(BD56:BD95,A56:A95,"PROJ*",X56:X95,">="&DATE(VALUE($L$7),1,1),X56:X95,"<"&DATE(VALUE($L$7)+1,1,1)),0)) -> 0.45
A10: ANALYSES AUTOMATIQUES
A11: Statut du projet | B11: Nb projets | D11: Domaine d'intervention | E11: Nb projets
A12: Actif | B12: =COUNTIFS(tbl_Projets[Statut du projet],A12) -> 0 | D12: Education | E12: =COUNTIFS(tbl_Projets[Domaine d''intervention],D12) -> 1
A13: Actif | B13: =COUNTIFS(tbl_Projets[Statut du projet],A13) -> 0 | D13: Formation professionnelle | E13: =COUNTIFS(tbl_Projets[Domaine d''intervention],D13) -> 0
A14: Actif | B14: =COUNTIFS(tbl_Projets[Statut du projet],A14) -> 0 | D14: Entrepreneuriat | E14: =COUNTIFS(tbl_Projets[Domaine d''intervention],D14) -> 0
A15: Actif | B15: =COUNTIFS(tbl_Projets[Statut du projet],A15) -> 0 | D15: Culture | E15: =COUNTIFS(tbl_Projets[Domaine d''intervention],D15) -> 0
A16: Actif | B16: =COUNTIFS(tbl_Projets[Statut du projet],A16) -> 0 | D16: Environnement | E16: =COUNTIFS(tbl_Projets[Domaine d''intervention],D16) -> 0
A17: Actif | B17: =COUNTIFS(tbl_Projets[Statut du projet],A17) -> 0 | D17: Sante | E17: =COUNTIFS(tbl_Projets[Domaine d''intervention],D17) -> 0
A18: Actif | B18: =COUNTIFS(tbl_Projets[Statut du projet],A18) -> 0 | D18: Genre | E18: =COUNTIFS(tbl_Projets[Domaine d''intervention],D18) -> 0
A19: Actif | B19: =COUNTIFS(tbl_Projets[Statut du projet],A19) -> 0 | D19: Tourisme | E19: =COUNTIFS(tbl_Projets[Domaine d''intervention],D19) -> 0
A20: Actif | B20: =COUNTIFS(tbl_Projets[Statut du projet],A20) -> 0 | D20: Sport | E20: =COUNTIFS(tbl_Projets[Domaine d''intervention],D20) -> 0
A21: Actif | B21: =COUNTIFS(tbl_Projets[Statut du projet],A21) -> 0 | D21: Agriculture et developpement rural | E21: =COUNTIFS(tbl_Projets[Domaine d''intervention],D21) -> 0
A22: Actif | B22: =COUNTIFS(tbl_Projets[Statut du projet],A22) -> 0 | D22: Elevage | E22: =COUNTIFS(tbl_Projets[Domaine d''intervention],D22) -> 0
A23: Actif | B23: =COUNTIFS(tbl_Projets[Statut du projet],A23) -> 0 | D23: Peche et aquaculture | E23: =COUNTIFS(tbl_Projets[Domaine d''intervention],D23) -> 0
... A26: Actif | B26: =COUNTIFS(tbl_Projets[Statut du projet],A26) -> 0 | D26: Protection sociale | E26: =COUNTIFS(tbl_Projets[Domaine d''intervention],D26) -> 0
D27: Protection de l'enfance | E27: =COUNTIFS(tbl_Projets[Domaine d''intervention],D27) -> 0
D28: Jeunesse | E28: =COUNTIFS(tbl_Projets[Domaine d''intervention],D28) -> 0
D29: Autonomisation des femmes | E29: =COUNTIFS(tbl_Projets[Domaine d''intervention],D29) -> 0
D30: Developpement communautaire | E30: =COUNTIFS(tbl_Projets[Domaine d''intervention],D30) -> 0
D31: Inclusion sociale | E31: =COUNTIFS(tbl_Projets[Domaine d''intervention],D31) -> 0
D32: Handicap et inclusion des personnes vulnerables | E32: =COUNTIFS(tbl_Projets[Domaine d''intervention],D32) -> 0
D33: Emploi et insertion professionnelle | E33: =COUNTIFS(tbl_Projets[Domaine d''intervention],D33) -> 0
D34: Developpement economique local | E34: =COUNTIFS(tbl_Projets[Domaine d''intervention],D34) -> 0
D35: Artisanat | E35: =COUNTIFS(tbl_Projets[Domaine d''intervention],D35) -> 0
D36: Numerique et transformation digitale | E36: =COUNTIFS(tbl_Projets[Domaine d''intervention],D36) -> 0
D37: Technologies et innovation | E37: =COUNTIFS(tbl_Projets[Domaine d''intervention],D37) -> 0
D38: Recherche et developpement | E38: =COUNTIFS(tbl_Projets[Domaine d''intervention],D38) -> 0
... D51: Autre domaine | E51: =COUNTIFS(tbl_Projets[Domaine d''intervention],D51) -> 0
A54: TABLEAU PRINCIPAL — LISTE DES PROJETS
A55: ID Projet | B55: Code interne | C55: Titre complet du projet | D55: Acronyme | E55: Resume | F55: Contexte | G55: Probleme identifie | H55: Justification | I55: Description intervention | J55: Domaine d'intervention | K55: Type de projet | L55: Objectif general | M55: ID responsable | N55: Nom du responsable | O55: Fonction responsable | P55: Telephone responsable | Q55: Email responsable | R55: Localite | S55: Pays | T55: Departement | U55: District/Commune | V55: Arrondissement | W55: Zone specifique | X55: Date debut prevue | Y55: Date debut reelle | Z55: Date fin prevue | AA55: Date fin reelle | AB55: Duree prevue (j) | AC55: Duree reelle (j) | AD55: Statut du projet | AE55: Niveau de priorite | AF55: Budget demande (FCFA) | AG55: Budget approuve (FCFA) | AH55: Financement recu (FCFA) | AI55: Depenses realisees (FCFA) | AJ55: Budget disponible (FCFA) | AK55: Solde (FCFA) | AL55: Taux execution budgetaire | AM55: Nb beneficiaires prevu | AN55: Nb femmes prevu | AO55: Nb hommes prevu | AP55: Nb jeunes prevu | AQ55: Nb enfants prevu | AR55: Nb menages prevu | AS55: Nb beneficiaires reels | AT55: Nb femmes reelles | AU55: Nb hommes reels | AV55: Nb pers. vulnerables reelles | AW55: Nb pers. handicap reelles | AX55: Nb activites total | AY55: Activites planifiees | AZ55: Activites en cours | BA55: Activites realisees | BB55: Activites annulees | BC55: Taux realisation activites | BD55: Taux d'avancement (%) | BE55: Projet en retard | BF55: Echeance proche (<30j) | BG55: Budget en depassement | BH55: Financement insuffisant | BI55: Observations
A56: =IF(C56="","","PROJ"&TEXT(ROW()-55,"0000")) -> PROJ0001 | B56: BK-EDU-2024-01 | C56: Projet d'appui a l'insertion professionnelle des jeunes | D56: PAIJ | E56: Formation professionnelle et accompagnement de 100 jeunes vers l'emploi. | J56: Education | K56: Projet de formation | L56: Ameliorer l'insertion professionnelle des jeunes de Brazzaville. | N56: Jean MABIALA | O56: Coordinateur de projet | R56: Bacongo | S56: =IFERROR(INDEX(PARAMETRES!$B$536:$B$586,MATCH(R56,PARAMETRES!$J$536:$J$586,0)),"") -> Congo | T56: =IFERROR(INDEX(PARAMETRES!$D$536:$D$586,MATCH(R56,PARAMETRES!$J$536:$J$586,0)),"") -> Brazzaville | U56: =IFERROR(INDEX(PARAMETRES!$F$536:$F$586,MATCH(R56,PARAMETRES!$J$536:$J$586,0)),"") -> Brazzaville | V56: =IFERROR(INDEX(PARAMETRES!$G$536:$G$586,MATCH(R56,PARAMETRES!$J$536:$J$586,0)),"") -> ARR02 | X56: 45292 | Z56: 45657 | AB56: =IF(OR(X56="",Z56=""),"",Z56-X56) -> 365 | AC56: =IF(OR(Y56="",AA56=""),"",AA56-Y56) | AD56: En cours | AE56: Haute | AF56: 12000000 | AG56: 11000000 | AH56: =IF(A56="",0,SUMIF(tbl_Projets_Financements[ID Projet],A56,tbl_Projets_Financements[Montant recu])) -> 6000000 | AI56: 4000000 | AJ56: =IF(AG56="",0,AG56)-IF(AI56="",0,AI56) -> 7000000 | AK56: =AH56-AI56 -> 2000000 | AL56: =IF(OR(AG56="",AG56=0),0,AI56/AG56) -> 0.36363636 | AM56: 100 | AN56: 50 | AO56: 50 | AS56: =IF(A56="",0,COUNTIFS(tbl_Beneficiaires[ID projet],A56)) -> 1 | AT56: =IF(A56="",0,COUNTIFS(tbl_Beneficiaires[ID projet],A56,tbl_Beneficiaires[Sexe],"Feminin")) -> 1 | AU56: =IF(A56="",0,COUNTIFS(tbl_Beneficiaires[ID projet],A56,tbl_Beneficiaires[Sexe],"Masculin")) -> 0 | AV56: =IF(A56="",0,COUNTIFS(tbl_Beneficiaires[ID projet],A56,tbl_Beneficiaires[Menage vulnerable],"Oui")) -> 0 | AW56: =IF(A56="",0,COUNTIFS(tbl_Beneficiaires[ID projet],A56,tbl_Beneficiaires[Handicap],"Oui")) -> 0 | AX56: 10 | AY56: 9 | AZ56: 5 | BA56: 3 | BB56: 1 | BC56: =IF(OR(AX56="",AX56=0),0,BA56/AX56) -> 0.3 | BD56: 0.45 | BE56: =IF(A56="","",IF(AND(Z56<>"",TODAY()>Z56,NOT(OR(AD56="Termine",AD56="Cloture",AD56="Annule",AD56="Non retenu"))),"OUI","NON")) -> OUI | BF56: =IF(A56="","",IF(AND(Z56<>"",(Z56-TODAY())>=0,(Z56-TODAY())<=30,NOT(OR(AD56="Termine",AD56="Cloture",AD56="Annule",AD56="Non retenu"))),"OUI","NON")) -> NON | BG56: =IF(A56="","",IF(AI56>AG56,"OUI","NON")) -> NON | BH56: =IF(A56="","",IF(AH56<AG56,"OUI","NON")) -> OUI
A57: =IF(C57="","","PROJ"&TEXT(ROW()-55,"0000")) | S57: =IFERROR(INDEX(PARAMETRES!$B$536:$B$586,MATCH(R57,PARAMETRES!$J$536:$J$586,0)),"") | T57: =IFERROR(INDEX(PARAMETRES!$D$536:$D$586,MATCH(R57,PARAMETRES!$J$536:$J$586,0)),"") | U57: =IFERROR(INDEX(PARAMETRES!$F$536:$F$586,MATCH(R57,PARAMETRES!$J$536:$J$586,0)),"") | V57: =IFERROR(INDEX(PARAMETRES!$G$536:$G$586,MATCH(R57,PARAMETRES!$J$536:$J$586,0)),"") | AB57: =IF(OR(X57="",Z57=""),"",Z57-X57) | AC57: =IF(OR(Y57="",AA57=""),"",AA57-Y57) | AH57: =IF(A57="",0,SUMIF(tbl_Projets_Financements[ID Projet],A57,tbl_Projets_Financements[Montant recu])) -> 0 | AJ57: =IF(AG57="",0,AG57)-IF(AI57="",0,AI57) -> 0 | AK57: =AH57-AI57 -> 0 | AL57: =IF(OR(AG57="",AG57=0),0,AI57/AG57) -> 0 | AS57: =IF(A57="",0,COUNTIFS(tbl_Beneficiaires[ID projet],A57)) -> 0 | AT57: =IF(A57="",0,COUNTIFS(tbl_Beneficiaires[ID projet],A57,tbl_Beneficiaires[Sexe],"Feminin")) -> 0 | AU57: =IF(A57="",0,COUNTIFS(tbl_Beneficiaires[ID projet],A57,tbl_Beneficiaires[Sexe],"Masculin")) -> 0 | AV57: =IF(A57="",0,COUNTIFS(tbl_Beneficiaires[ID projet],A57,tbl_Beneficiaires[Menage vulnerable],"Oui")) -> 0 | AW57: =IF(A57="",0,COUNTIFS(tbl_Beneficiaires[ID projet],A57,tbl_Beneficiaires[Handicap],"Oui")) -> 0 | BC57: =IF(OR(AX57="",AX57=0),0,BA57/AX57) -> 0 | BE57: =IF(A57="","",IF(AND(Z57<>"",TODAY()>Z57,NOT(OR(AD57="Termine",AD57="Cloture",AD57="Annule",AD57="Non retenu"))),"OUI","NON")) | BF57: =IF(A57="","",IF(AND(Z57<>"",(Z57-TODAY())>=0,(Z57-TODAY())<=30,NOT(OR(AD57="Termine",AD57="Cloture",AD57="Annule",AD57="Non retenu"))),"OUI","NON")) | BG57: =IF(A57="","",IF(AI57>AG57,"OUI","NON")) | BH57: =IF(A57="","",IF(AH57<AG57,"OUI","NON"))
A58: =IF(C58="","","PROJ"&TEXT(ROW()-55,"0000")) | S58: =IFERROR(INDEX(PARAMETRES!$B$536:$B$586,MATCH(R58,PARAMETRES!$J$536:$J$586,0)),"") | T58: =IFERROR(INDEX(PARAMETRES!$D$536:$D$586,MATCH(R58,PARAMETRES!$J$536:$J$586,0)),"") | U58: =IFERROR(INDEX(PARAMETRES!$F$536:$F$586,MATCH(R58,PARAMETRES!$J$536:$J$586,0)),"") | V58: =IFERROR(INDEX(PARAMETRES!$G$536:$G$586,MATCH(R58,PARAMETRES!$J$536:$J$586,0)),"") | AB58: =IF(OR(X58="",Z58=""),"",Z58-X58) | AC58: =IF(OR(Y58="",AA58=""),"",AA58-Y58) | AH58: =IF(A58="",0,SUMIF(tbl_Projets_Financements[ID Projet],A58,tbl_Projets_Financements[Montant recu])) -> 0 | AJ58: =IF(AG58="",0,AG58)-IF(AI58="",0,AI58) -> 0 | AK58: =AH58-AI58 -> 0 | AL58: =IF(OR(AG58="",AG58=0),0,AI58/AG58) -> 0 | AS58: =IF(A58="",0,COUNTIFS(tbl_Beneficiaires[ID projet],A58)) -> 0 | AT58: =IF(A58="",0,COUNTIFS(tbl_Beneficiaires[ID projet],A58,tbl_Beneficiaires[Sexe],"Feminin")) -> 0 | AU58: =IF(A58="",0,COUNTIFS(tbl_Beneficiaires[ID projet],A58,tbl_Beneficiaires[Sexe],"Masculin")) -> 0 | AV58: =IF(A58="",0,COUNTIFS(tbl_Beneficiaires[ID projet],A58,tbl_Beneficiaires[Menage vulnerable],"Oui")) -> 0 | AW58: =IF(A58="",0,COUNTIFS(tbl_Beneficiaires[ID projet],A58,tbl_Beneficiaires[Handicap],"Oui")) -> 0 | BC58: =IF(OR(AX58="",AX58=0),0,BA58/AX58) -> 0 | BE58: =IF(A58="","",IF(AND(Z58<>"",TODAY()>Z58,NOT(OR(AD58="Termine",AD58="Cloture",AD58="Annule",AD58="Non retenu"))),"OUI","NON")) | BF58: =IF(A58="","",IF(AND(Z58<>"",(Z58-TODAY())>=0,(Z58-TODAY())<=30,NOT(OR(AD58="Termine",AD58="Cloture",AD58="Annule",AD58="Non retenu"))),"OUI","NON")) | BG58: =IF(A58="","",IF(AI58>AG58,"OUI","NON")) | BH58: =IF(A58="","",IF(AH58<AG58,"OUI","NON"))
A59: =IF(C59="","","PROJ"&TEXT(ROW()-55,"0000")) | S59: =IFERROR(INDEX(PARAMETRES!$B$536:$B$586,MATCH(R59,PARAMETRES!$J$536:$J$586,0)),"") | T59: =IFERROR(INDEX(PARAMETRES!$D$536:$D$586,MATCH(R59,PARAMETRES!$J$536:$J$586,0)),"") | U59: =IFERROR(INDEX(PARAMETRES!$F$536:$F$586,MATCH(R59,PARAMETRES!$J$536:$J$586,0)),"") | V59: =IFERROR(INDEX(PARAMETRES!$G$536:$G$586,MATCH(R59,PARAMETRES!$J$536:$J$586,0)),"") | AB59: =IF(OR(X59="",Z59=""),"",Z59-X59) | AC59: =IF(OR(Y59="",AA59=""),"",AA59-Y59) | AH59: =IF(A59="",0,SUMIF(tbl_Projets_Financements[ID Projet],A59,tbl_Projets_Financements[Montant recu])) -> 0 | AJ59: =IF(AG59="",0,AG59)-IF(AI59="",0,AI59) -> 0 | AK59: =AH59-AI59 -> 0 | AL59: =IF(OR(AG59="",AG59=0),0,AI59/AG59) -> 0 | AS59: =IF(A59="",0,COUNTIFS(tbl_Beneficiaires[ID projet],A59)) -> 0 | AT59: =IF(A59="",0,COUNTIFS(tbl_Beneficiaires[ID projet],A59,tbl_Beneficiaires[Sexe],"Feminin")) -> 0 | AU59: =IF(A59="",0,COUNTIFS(tbl_Beneficiaires[ID projet],A59,tbl_Beneficiaires[Sexe],"Masculin")) -> 0 | AV59: =IF(A59="",0,COUNTIFS(tbl_Beneficiaires[ID projet],A59,tbl_Beneficiaires[Menage vulnerable],"Oui")) -> 0 | AW59: =IF(A59="",0,COUNTIFS(tbl_Beneficiaires[ID projet],A59,tbl_Beneficiaires[Handicap],"Oui")) -> 0 | BC59: =IF(OR(AX59="",AX59=0),0,BA59/AX59) -> 0 | BE59: =IF(A59="","",IF(AND(Z59<>"",TODAY()>Z59,NOT(OR(AD59="Termine",AD59="Cloture",AD59="Annule",AD59="Non retenu"))),"OUI","NON")) | BF59: =IF(A59="","",IF(AND(Z59<>"",(Z59-TODAY())>=0,(Z59-TODAY())<=30,NOT(OR(AD59="Termine",AD59="Cloture",AD59="Annule",AD59="Non retenu"))),"OUI","NON")) | BG59: =IF(A59="","",IF(AI59>AG59,"OUI","NON")) | BH59: =IF(A59="","",IF(AH59<AG59,"OUI","NON"))
A60: =IF(C60="","","PROJ"&TEXT(ROW()-55,"0000")) | S60: =IFERROR(INDEX(PARAMETRES!$B$536:$B$586,MATCH(R60,PARAMETRES!$J$536:$J$586,0)),"") | T60: =IFERROR(INDEX(PARAMETRES!$D$536:$D$586,MATCH(R60,PARAMETRES!$J$536:$J$586,0)),"") | U60: =IFERROR(INDEX(PARAMETRES!$F$536:$F$586,MATCH(R60,PARAMETRES!$J$536:$J$586,0)),"") | V60: =IFERROR(INDEX(PARAMETRES!$G$536:$G$586,MATCH(R60,PARAMETRES!$J$536:$J$586,0)),"") | AB60: =IF(OR(X60="",Z60=""),"",Z60-X60) | AC60: =IF(OR(Y60="",AA60=""),"",AA60-Y60) | AH60: =IF(A60="",0,SUMIF(tbl_Projets_Financements[ID Projet],A60,tbl_Projets_Financements[Montant recu])) -> 0 | AJ60: =IF(AG60="",0,AG60)-IF(AI60="",0,AI60) -> 0 | AK60: =AH60-AI60 -> 0 | AL60: =IF(OR(AG60="",AG60=0),0,AI60/AG60) -> 0 | AS60: =IF(A60="",0,COUNTIFS(tbl_Beneficiaires[ID projet],A60)) -> 0 | AT60: =IF(A60="",0,COUNTIFS(tbl_Beneficiaires[ID projet],A60,tbl_Beneficiaires[Sexe],"Feminin")) -> 0 | AU60: =IF(A60="",0,COUNTIFS(tbl_Beneficiaires[ID projet],A60,tbl_Beneficiaires[Sexe],"Masculin")) -> 0 | AV60: =IF(A60="",0,COUNTIFS(tbl_Beneficiaires[ID projet],A60,tbl_Beneficiaires[Menage vulnerable],"Oui")) -> 0 | AW60: =IF(A60="",0,COUNTIFS(tbl_Beneficiaires[ID projet],A60,tbl_Beneficiaires[Handicap],"Oui")) -> 0 | BC60: =IF(OR(AX60="",AX60=0),0,BA60/AX60) -> 0 | BE60: =IF(A60="","",IF(AND(Z60<>"",TODAY()>Z60,NOT(OR(AD60="Termine",AD60="Cloture",AD60="Annule",AD60="Non retenu"))),"OUI","NON")) | BF60: =IF(A60="","",IF(AND(Z60<>"",(Z60-TODAY())>=0,(Z60-TODAY())<=30,NOT(OR(AD60="Termine",AD60="Cloture",AD60="Annule",AD60="Non retenu"))),"OUI","NON")) | BG60: =IF(A60="","",IF(AI60>AG60,"OUI","NON")) | BH60: =IF(A60="","",IF(AH60<AG60,"OUI","NON"))
A61: =IF(C61="","","PROJ"&TEXT(ROW()-55,"0000")) | S61: =IFERROR(INDEX(PARAMETRES!$B$536:$B$586,MATCH(R61,PARAMETRES!$J$536:$J$586,0)),"") | T61: =IFERROR(INDEX(PARAMETRES!$D$536:$D$586,MATCH(R61,PARAMETRES!$J$536:$J$586,0)),"") | U61: =IFERROR(INDEX(PARAMETRES!$F$536:$F$586,MATCH(R61,PARAMETRES!$J$536:$J$586,0)),"") | V61: =IFERROR(INDEX(PARAMETRES!$G$536:$G$586,MATCH(R61,PARAMETRES!$J$536:$J$586,0)),"") | AB61: =IF(OR(X61="",Z61=""),"",Z61-X61) | AC61: =IF(OR(Y61="",AA61=""),"",AA61-Y61) | AH61: =IF(A61="",0,SUMIF(tbl_Projets_Financements[ID Projet],A61,tbl_Projets_Financements[Montant recu])) -> 0 | AJ61: =IF(AG61="",0,AG61)-IF(AI61="",0,AI61) -> 0 | AK61: =AH61-AI61 -> 0 | AL61: =IF(OR(AG61="",AG61=0),0,AI61/AG61) -> 0 | AS61: =IF(A61="",0,COUNTIFS(tbl_Beneficiaires[ID projet],A61)) -> 0 | AT61: =IF(A61="",0,COUNTIFS(tbl_Beneficiaires[ID projet],A61,tbl_Beneficiaires[Sexe],"Feminin")) -> 0 | AU61: =IF(A61="",0,COUNTIFS(tbl_Beneficiaires[ID projet],A61,tbl_Beneficiaires[Sexe],"Masculin")) -> 0 | AV61: =IF(A61="",0,COUNTIFS(tbl_Beneficiaires[ID projet],A61,tbl_Beneficiaires[Menage vulnerable],"Oui")) -> 0 | AW61: =IF(A61="",0,COUNTIFS(tbl_Beneficiaires[ID projet],A61,tbl_Beneficiaires[Handicap],"Oui")) -> 0 | BC61: =IF(OR(AX61="",AX61=0),0,BA61/AX61) -> 0 | BE61: =IF(A61="","",IF(AND(Z61<>"",TODAY()>Z61,NOT(OR(AD61="Termine",AD61="Cloture",AD61="Annule",AD61="Non retenu"))),"OUI","NON")) | BF61: =IF(A61="","",IF(AND(Z61<>"",(Z61-TODAY())>=0,(Z61-TODAY())<=30,NOT(OR(AD61="Termine",AD61="Cloture",AD61="Annule",AD61="Non retenu"))),"OUI","NON")) | BG61: =IF(A61="","",IF(AI61>AG61,"OUI","NON")) | BH61: =IF(A61="","",IF(AH61<AG61,"OUI","NON"))
A62: =IF(C62="","","PROJ"&TEXT(ROW()-55,"0000")) | S62: =IFERROR(INDEX(PARAMETRES!$B$536:$B$586,MATCH(R62,PARAMETRES!$J$536:$J$586,0)),"") | T62: =IFERROR(INDEX(PARAMETRES!$D$536:$D$586,MATCH(R62,PARAMETRES!$J$536:$J$586,0)),"") | U62: =IFERROR(INDEX(PARAMETRES!$F$536:$F$586,MATCH(R62,PARAMETRES!$J$536:$J$586,0)),"") | V62: =IFERROR(INDEX(PARAMETRES!$G$536:$G$586,MATCH(R62,PARAMETRES!$J$536:$J$586,0)),"") | AB62: =IF(OR(X62="",Z62=""),"",Z62-X62) | AC62: =IF(OR(Y62="",AA62=""),"",AA62-Y62) | AH62: =IF(A62="",0,SUMIF(tbl_Projets_Financements[ID Projet],A62,tbl_Projets_Financements[Montant recu])) -> 0 | AJ62: =IF(AG62="",0,AG62)-IF(AI62="",0,AI62) -> 0 | AK62: =AH62-AI62 -> 0 | AL62: =IF(OR(AG62="",AG62=0),0,AI62/AG62) -> 0 | AS62: =IF(A62="",0,COUNTIFS(tbl_Beneficiaires[ID projet],A62)) -> 0 | AT62: =IF(A62="",0,COUNTIFS(tbl_Beneficiaires[ID projet],A62,tbl_Beneficiaires[Sexe],"Feminin")) -> 0 | AU62: =IF(A62="",0,COUNTIFS(tbl_Beneficiaires[ID projet],A62,tbl_Beneficiaires[Sexe],"Masculin")) -> 0 | AV62: =IF(A62="",0,COUNTIFS(tbl_Beneficiaires[ID projet],A62,tbl_Beneficiaires[Menage vulnerable],"Oui")) -> 0 | AW62: =IF(A62="",0,COUNTIFS(tbl_Beneficiaires[ID projet],A62,tbl_Beneficiaires[Handicap],"Oui")) -> 0 | BC62: =IF(OR(AX62="",AX62=0),0,BA62/AX62) -> 0 | BE62: =IF(A62="","",IF(AND(Z62<>"",TODAY()>Z62,NOT(OR(AD62="Termine",AD62="Cloture",AD62="Annule",AD62="Non retenu"))),"OUI","NON")) | BF62: =IF(A62="","",IF(AND(Z62<>"",(Z62-TODAY())>=0,(Z62-TODAY())<=30,NOT(OR(AD62="Termine",AD62="Cloture",AD62="Annule",AD62="Non retenu"))),"OUI","NON")) | BG62: =IF(A62="","",IF(AI62>AG62,"OUI","NON")) | BH62: =IF(A62="","",IF(AH62<AG62,"OUI","NON"))
A63: =IF(C63="","","PROJ"&TEXT(ROW()-55,"0000")) | S63: =IFERROR(INDEX(PARAMETRES!$B$536:$B$586,MATCH(R63,PARAMETRES!$J$536:$J$586,0)),"") | T63: =IFERROR(INDEX(PARAMETRES!$D$536:$D$586,MATCH(R63,PARAMETRES!$J$536:$J$586,0)),"") | U63: =IFERROR(INDEX(PARAMETRES!$F$536:$F$586,MATCH(R63,PARAMETRES!$J$536:$J$586,0)),"") | V63: =IFERROR(INDEX(PARAMETRES!$G$536:$G$586,MATCH(R63,PARAMETRES!$J$536:$J$586,0)),"") | AB63: =IF(OR(X63="",Z63=""),"",Z63-X63) | AC63: =IF(OR(Y63="",AA63=""),"",AA63-Y63) | AH63: =IF(A63="",0,SUMIF(tbl_Projets_Financements[ID Projet],A63,tbl_Projets_Financements[Montant recu])) -> 0 | AJ63: =IF(AG63="",0,AG63)-IF(AI63="",0,AI63) -> 0 | AK63: =AH63-AI63 -> 0 | AL63: =IF(OR(AG63="",AG63=0),0,AI63/AG63) -> 0 | AS63: =IF(A63="",0,COUNTIFS(tbl_Beneficiaires[ID projet],A63)) -> 0 | AT63: =IF(A63="",0,COUNTIFS(tbl_Beneficiaires[ID projet],A63,tbl_Beneficiaires[Sexe],"Feminin")) -> 0 | AU63: =IF(A63="",0,COUNTIFS(tbl_Beneficiaires[ID projet],A63,tbl_Beneficiaires[Sexe],"Masculin")) -> 0 | AV63: =IF(A63="",0,COUNTIFS(tbl_Beneficiaires[ID projet],A63,tbl_Beneficiaires[Menage vulnerable],"Oui")) -> 0 | AW63: =IF(A63="",0,COUNTIFS(tbl_Beneficiaires[ID projet],A63,tbl_Beneficiaires[Handicap],"Oui")) -> 0 | BC63: =IF(OR(AX63="",AX63=0),0,BA63/AX63) -> 0 | BE63: =IF(A63="","",IF(AND(Z63<>"",TODAY()>Z63,NOT(OR(AD63="Termine",AD63="Cloture",AD63="Annule",AD63="Non retenu"))),"OUI","NON")) | BF63: =IF(A63="","",IF(AND(Z63<>"",(Z63-TODAY())>=0,(Z63-TODAY())<=30,NOT(OR(AD63="Termine",AD63="Cloture",AD63="Annule",AD63="Non retenu"))),"OUI","NON")) | BG63: =IF(A63="","",IF(AI63>AG63,"OUI","NON")) | BH63: =IF(A63="","",IF(AH63<AG63,"OUI","NON"))
A64: =IF(C64="","","PROJ"&TEXT(ROW()-55,"0000")) | S64: =IFERROR(INDEX(PARAMETRES!$B$536:$B$586,MATCH(R64,PARAMETRES!$J$536:$J$586,0)),"") | T64: =IFERROR(INDEX(PARAMETRES!$D$536:$D$586,MATCH(R64,PARAMETRES!$J$536:$J$586,0)),"") | U64: =IFERROR(INDEX(PARAMETRES!$F$536:$F$586,MATCH(R64,PARAMETRES!$J$536:$J$586,0)),"") | V64: =IFERROR(INDEX(PARAMETRES!$G$536:$G$586,MATCH(R64,PARAMETRES!$J$536:$J$586,0)),"") | AB64: =IF(OR(X64="",Z64=""),"",Z64-X64) | AC64: =IF(OR(Y64="",AA64=""),"",AA64-Y64) | AH64: =IF(A64="",0,SUMIF(tbl_Projets_Financements[ID Projet],A64,tbl_Projets_Financements[Montant recu])) -> 0 | AJ64: =IF(AG64="",0,AG64)-IF(AI64="",0,AI64) -> 0 | AK64: =AH64-AI64 -> 0 | AL64: =IF(OR(AG64="",AG64=0),0,AI64/AG64) -> 0 | AS64: =IF(A64="",0,COUNTIFS(tbl_Beneficiaires[ID projet],A64)) -> 0 | AT64: =IF(A64="",0,COUNTIFS(tbl_Beneficiaires[ID projet],A64,tbl_Beneficiaires[Sexe],"Feminin")) -> 0 | AU64: =IF(A64="",0,COUNTIFS(tbl_Beneficiaires[ID projet],A64,tbl_Beneficiaires[Sexe],"Masculin")) -> 0 | AV64: =IF(A64="",0,COUNTIFS(tbl_Beneficiaires[ID projet],A64,tbl_Beneficiaires[Menage vulnerable],"Oui")) -> 0 | AW64: =IF(A64="",0,COUNTIFS(tbl_Beneficiaires[ID projet],A64,tbl_Beneficiaires[Handicap],"Oui")) -> 0 | BC64: =IF(OR(AX64="",AX64=0),0,BA64/AX64) -> 0 | BE64: =IF(A64="","",IF(AND(Z64<>"",TODAY()>Z64,NOT(OR(AD64="Termine",AD64="Cloture",AD64="Annule",AD64="Non retenu"))),"OUI","NON")) | BF64: =IF(A64="","",IF(AND(Z64<>"",(Z64-TODAY())>=0,(Z64-TODAY())<=30,NOT(OR(AD64="Termine",AD64="Cloture",AD64="Annule",AD64="Non retenu"))),"OUI","NON")) | BG64: =IF(A64="","",IF(AI64>AG64,"OUI","NON")) | BH64: =IF(A64="","",IF(AH64<AG64,"OUI","NON"))
A65: =IF(C65="","","PROJ"&TEXT(ROW()-55,"0000")) | S65: =IFERROR(INDEX(PARAMETRES!$B$536:$B$586,MATCH(R65,PARAMETRES!$J$536:$J$586,0)),"") | T65: =IFERROR(INDEX(PARAMETRES!$D$536:$D$586,MATCH(R65,PARAMETRES!$J$536:$J$586,0)),"") | U65: =IFERROR(INDEX(PARAMETRES!$F$536:$F$586,MATCH(R65,PARAMETRES!$J$536:$J$586,0)),"") | V65: =IFERROR(INDEX(PARAMETRES!$G$536:$G$586,MATCH(R65,PARAMETRES!$J$536:$J$586,0)),"") | AB65: =IF(OR(X65="",Z65=""),"",Z65-X65) | AC65: =IF(OR(Y65="",AA65=""),"",AA65-Y65) | AH65: =IF(A65="",0,SUMIF(tbl_Projets_Financements[ID Projet],A65,tbl_Projets_Financements[Montant recu])) -> 0 | AJ65: =IF(AG65="",0,AG65)-IF(AI65="",0,AI65) -> 0 | AK65: =AH65-AI65 -> 0 | AL65: =IF(OR(AG65="",AG65=0),0,AI65/AG65) -> 0 | AS65: =IF(A65="",0,COUNTIFS(tbl_Beneficiaires[ID projet],A65)) -> 0 | AT65: =IF(A65="",0,COUNTIFS(tbl_Beneficiaires[ID projet],A65,tbl_Beneficiaires[Sexe],"Feminin")) -> 0 | AU65: =IF(A65="",0,COUNTIFS(tbl_Beneficiaires[ID projet],A65,tbl_Beneficiaires[Sexe],"Masculin")) -> 0 | AV65: =IF(A65="",0,COUNTIFS(tbl_Beneficiaires[ID projet],A65,tbl_Beneficiaires[Menage vulnerable],"Oui")) -> 0 | AW65: =IF(A65="",0,COUNTIFS(tbl_Beneficiaires[ID projet],A65,tbl_Beneficiaires[Handicap],"Oui")) -> 0 | BC65: =IF(OR(AX65="",AX65=0),0,BA65/AX65) -> 0 | BE65: =IF(A65="","",IF(AND(Z65<>"",TODAY()>Z65,NOT(OR(AD65="Termine",AD65="Cloture",AD65="Annule",AD65="Non retenu"))),"OUI","NON")) | BF65: =IF(A65="","",IF(AND(Z65<>"",(Z65-TODAY())>=0,(Z65-TODAY())<=30,NOT(OR(AD65="Termine",AD65="Cloture",AD65="Annule",AD65="Non retenu"))),"OUI","NON")) | BG65: =IF(A65="","",IF(AI65>AG65,"OUI","NON")) | BH65: =IF(A65="","",IF(AH65<AG65,"OUI","NON"))
A66: =IF(C66="","","PROJ"&TEXT(ROW()-55,"0000")) | S66: =IFERROR(INDEX(PARAMETRES!$B$536:$B$586,MATCH(R66,PARAMETRES!$J$536:$J$586,0)),"") | T66: =IFERROR(INDEX(PARAMETRES!$D$536:$D$586,MATCH(R66,PARAMETRES!$J$536:$J$586,0)),"") | U66: =IFERROR(INDEX(PARAMETRES!$F$536:$F$586,MATCH(R66,PARAMETRES!$J$536:$J$586,0)),"") | V66: =IFERROR(INDEX(PARAMETRES!$G$536:$G$586,MATCH(R66,PARAMETRES!$J$536:$J$586,0)),"") | AB66: =IF(OR(X66="",Z66=""),"",Z66-X66) | AC66: =IF(OR(Y66="",AA66=""),"",AA66-Y66) | AH66: =IF(A66="",0,SUMIF(tbl_Projets_Financements[ID Projet],A66,tbl_Projets_Financements[Montant recu])) -> 0 | AJ66: =IF(AG66="",0,AG66)-IF(AI66="",0,AI66) -> 0 | AK66: =AH66-AI66 -> 0 | AL66: =IF(OR(AG66="",AG66=0),0,AI66/AG66) -> 0 | AS66: =IF(A66="",0,COUNTIFS(tbl_Beneficiaires[ID projet],A66)) -> 0 | AT66: =IF(A66="",0,COUNTIFS(tbl_Beneficiaires[ID projet],A66,tbl_Beneficiaires[Sexe],"Feminin")) -> 0 | AU66: =IF(A66="",0,COUNTIFS(tbl_Beneficiaires[ID projet],A66,tbl_Beneficiaires[Sexe],"Masculin")) -> 0 | AV66: =IF(A66="",0,COUNTIFS(tbl_Beneficiaires[ID projet],A66,tbl_Beneficiaires[Menage vulnerable],"Oui")) -> 0 | AW66: =IF(A66="",0,COUNTIFS(tbl_Beneficiaires[ID projet],A66,tbl_Beneficiaires[Handicap],"Oui")) -> 0 | BC66: =IF(OR(AX66="",AX66=0),0,BA66/AX66) -> 0 | BE66: =IF(A66="","",IF(AND(Z66<>"",TODAY()>Z66,NOT(OR(AD66="Termine",AD66="Cloture",AD66="Annule",AD66="Non retenu"))),"OUI","NON")) | BF66: =IF(A66="","",IF(AND(Z66<>"",(Z66-TODAY())>=0,(Z66-TODAY())<=30,NOT(OR(AD66="Termine",AD66="Cloture",AD66="Annule",AD66="Non retenu"))),"OUI","NON")) | BG66: =IF(A66="","",IF(AI66>AG66,"OUI","NON")) | BH66: =IF(A66="","",IF(AH66<AG66,"OUI","NON"))
A67: =IF(C67="","","PROJ"&TEXT(ROW()-55,"0000")) | S67: =IFERROR(INDEX(PARAMETRES!$B$536:$B$586,MATCH(R67,PARAMETRES!$J$536:$J$586,0)),"") | T67: =IFERROR(INDEX(PARAMETRES!$D$536:$D$586,MATCH(R67,PARAMETRES!$J$536:$J$586,0)),"") | U67: =IFERROR(INDEX(PARAMETRES!$F$536:$F$586,MATCH(R67,PARAMETRES!$J$536:$J$586,0)),"") | V67: =IFERROR(INDEX(PARAMETRES!$G$536:$G$586,MATCH(R67,PARAMETRES!$J$536:$J$586,0)),"") | AB67: =IF(OR(X67="",Z67=""),"",Z67-X67) | AC67: =IF(OR(Y67="",AA67=""),"",AA67-Y67) | AH67: =IF(A67="",0,SUMIF(tbl_Projets_Financements[ID Projet],A67,tbl_Projets_Financements[Montant recu])) -> 0 | AJ67: =IF(AG67="",0,AG67)-IF(AI67="",0,AI67) -> 0 | AK67: =AH67-AI67 -> 0 | AL67: =IF(OR(AG67="",AG67=0),0,AI67/AG67) -> 0 | AS67: =IF(A67="",0,COUNTIFS(tbl_Beneficiaires[ID projet],A67)) -> 0 | AT67: =IF(A67="",0,COUNTIFS(tbl_Beneficiaires[ID projet],A67,tbl_Beneficiaires[Sexe],"Feminin")) -> 0 | AU67: =IF(A67="",0,COUNTIFS(tbl_Beneficiaires[ID projet],A67,tbl_Beneficiaires[Sexe],"Masculin")) -> 0 | AV67: =IF(A67="",0,COUNTIFS(tbl_Beneficiaires[ID projet],A67,tbl_Beneficiaires[Menage vulnerable],"Oui")) -> 0 | AW67: =IF(A67="",0,COUNTIFS(tbl_Beneficiaires[ID projet],A67,tbl_Beneficiaires[Handicap],"Oui")) -> 0 | BC67: =IF(OR(AX67="",AX67=0),0,BA67/AX67) -> 0 | BE67: =IF(A67="","",IF(AND(Z67<>"",TODAY()>Z67,NOT(OR(AD67="Termine",AD67="Cloture",AD67="Annule",AD67="Non retenu"))),"OUI","NON")) | BF67: =IF(A67="","",IF(AND(Z67<>"",(Z67-TODAY())>=0,(Z67-TODAY())<=30,NOT(OR(AD67="Termine",AD67="Cloture",AD67="Annule",AD67="Non retenu"))),"OUI","NON")) | BG67: =IF(A67="","",IF(AI67>AG67,"OUI","NON")) | BH67: =IF(A67="","",IF(AH67<AG67,"OUI","NON"))
A68: =IF(C68="","","PROJ"&TEXT(ROW()-55,"0000")) | S68: =IFERROR(INDEX(PARAMETRES!$B$536:$B$586,MATCH(R68,PARAMETRES!$J$536:$J$586,0)),"") | T68: =IFERROR(INDEX(PARAMETRES!$D$536:$D$586,MATCH(R68,PARAMETRES!$J$536:$J$586,0)),"") | U68: =IFERROR(INDEX(PARAMETRES!$F$536:$F$586,MATCH(R68,PARAMETRES!$J$536:$J$586,0)),"") | V68: =IFERROR(INDEX(PARAMETRES!$G$536:$G$586,MATCH(R68,PARAMETRES!$J$536:$J$586,0)),"") | AB68: =IF(OR(X68="",Z68=""),"",Z68-X68) | AC68: =IF(OR(Y68="",AA68=""),"",AA68-Y68) | AH68: =IF(A68="",0,SUMIF(tbl_Projets_Financements[ID Projet],A68,tbl_Projets_Financements[Montant recu])) -> 0 | AJ68: =IF(AG68="",0,AG68)-IF(AI68="",0,AI68) -> 0 | AK68: =AH68-AI68 -> 0 | AL68: =IF(OR(AG68="",AG68=0),0,AI68/AG68) -> 0 | AS68: =IF(A68="",0,COUNTIFS(tbl_Beneficiaires[ID projet],A68)) -> 0 | AT68: =IF(A68="",0,COUNTIFS(tbl_Beneficiaires[ID projet],A68,tbl_Beneficiaires[Sexe],"Feminin")) -> 0 | AU68: =IF(A68="",0,COUNTIFS(tbl_Beneficiaires[ID projet],A68,tbl_Beneficiaires[Sexe],"Masculin")) -> 0 | AV68: =IF(A68="",0,COUNTIFS(tbl_Beneficiaires[ID projet],A68,tbl_Beneficiaires[Menage vulnerable],"Oui")) -> 0 | AW68: =IF(A68="",0,COUNTIFS(tbl_Beneficiaires[ID projet],A68,tbl_Beneficiaires[Handicap],"Oui")) -> 0 | BC68: =IF(OR(AX68="",AX68=0),0,BA68/AX68) -> 0 | BE68: =IF(A68="","",IF(AND(Z68<>"",TODAY()>Z68,NOT(OR(AD68="Termine",AD68="Cloture",AD68="Annule",AD68="Non retenu"))),"OUI","NON")) | BF68: =IF(A68="","",IF(AND(Z68<>"",(Z68-TODAY())>=0,(Z68-TODAY())<=30,NOT(OR(AD68="Termine",AD68="Cloture",AD68="Annule",AD68="Non retenu"))),"OUI","NON")) | BG68: =IF(A68="","",IF(AI68>AG68,"OUI","NON")) | BH68: =IF(A68="","",IF(AH68<AG68,"OUI","NON"))
... A95: =IF(C95="","","PROJ"&TEXT(ROW()-55,"0000")) | S95: =IFERROR(INDEX(PARAMETRES!$B$536:$B$586,MATCH(R95,PARAMETRES!$J$536:$J$586,0)),"") | T95: =IFERROR(INDEX(PARAMETRES!$D$536:$D$586,MATCH(R95,PARAMETRES!$J$536:$J$586,0)),"") | U95: =IFERROR(INDEX(PARAMETRES!$F$536:$F$586,MATCH(R95,PARAMETRES!$J$536:$J$586,0)),"") | V95: =IFERROR(INDEX(PARAMETRES!$G$536:$G$586,MATCH(R95,PARAMETRES!$J$536:$J$586,0)),"") | AB95: =IF(OR(X95="",Z95=""),"",Z95-X95) | AC95: =IF(OR(Y95="",AA95=""),"",AA95-Y95) | AH95: =IF(A95="",0,SUMIF(tbl_Projets_Financements[ID Projet],A95,tbl_Projets_Financements[Montant recu])) -> 0 | AJ95: =IF(AG95="",0,AG95)-IF(AI95="",0,AI95) -> 0 | AK95: =AH95-AI95 -> 0 | AL95: =IF(OR(AG95="",AG95=0),0,AI95/AG95) -> 0 | AS95: =IF(A95="",0,COUNTIFS(tbl_Beneficiaires[ID projet],A95)) -> 0 | AT95: =IF(A95="",0,COUNTIFS(tbl_Beneficiaires[ID projet],A95,tbl_Beneficiaires[Sexe],"Feminin")) -> 0 | AU95: =IF(A95="",0,COUNTIFS(tbl_Beneficiaires[ID projet],A95,tbl_Beneficiaires[Sexe],"Masculin")) -> 0 | AV95: =IF(A95="",0,COUNTIFS(tbl_Beneficiaires[ID projet],A95,tbl_Beneficiaires[Menage vulnerable],"Oui")) -> 0 | AW95: =IF(A95="",0,COUNTIFS(tbl_Beneficiaires[ID projet],A95,tbl_Beneficiaires[Handicap],"Oui")) -> 0 | BC95: =IF(OR(AX95="",AX95=0),0,BA95/AX95) -> 0 | BE95: =IF(A95="","",IF(AND(Z95<>"",TODAY()>Z95,NOT(OR(AD95="Termine",AD95="Cloture",AD95="Annule",AD95="Non retenu"))),"OUI","NON")) | BF95: =IF(A95="","",IF(AND(Z95<>"",(Z95-TODAY())>=0,(Z95-TODAY())<=30,NOT(OR(AD95="Termine",AD95="Cloture",AD95="Annule",AD95="Non retenu"))),"OUI","NON")) | BG95: =IF(A95="","",IF(AI95>AG95,"OUI","NON")) | BH95: =IF(A95="","",IF(AH95<AG95,"OUI","NON"))
A98: OBJECTIFS SPECIFIQUES PAR PROJET
A99: ID Projet | B99: Code objectif | C99: Objectif specifique | D99: Indicateur associe | E99: Valeur cible | F99: Echeance | G99: Statut
A132: RESULTATS ATTENDUS PAR PROJET
A133: ID Projet | B133: Code resultat | C133: Resultat attendu | D133: Indicateur | E133: Situation reference | F133: Cible | G133: Realisation | H133: Taux atteinte
H134: =IF(OR(F134="",F134=0,G134=""),"",G134/F134)
H135: =IF(OR(F135="",F135=0,G135=""),"",G135/F135)
H136: =IF(OR(F136="",F136=0,G136=""),"",G136/F136)
H137: =IF(OR(F137="",F137=0,G137=""),"",G137/F137)
H138: =IF(OR(F138="",F138=0,G138=""),"",G138/F138)
H139: =IF(OR(F139="",F139=0,G139=""),"",G139/F139)
H140: =IF(OR(F140="",F140=0,G140=""),"",G140/F140)
H141: =IF(OR(F141="",F141=0,G141=""),"",G141/F141)
H142: =IF(OR(F142="",F142=0,G142=""),"",G142/F142)
H143: =IF(OR(F143="",F143=0,G143=""),"",G143/F143)
H144: =IF(OR(F144="",F144=0,G144=""),"",G144/F144)
H145: =IF(OR(F145="",F145=0,G145=""),"",G145/F145)
... H163: =IF(OR(F163="",F163=0,G163=""),"",G163/F163)
A166: EQUIPE DU PROJET
A167: ID Projet | B167: ID employe | C167: Nom | D167: Fonction | E167: Role dans le projet | F167: Date d'affectation | G167: Statut
A200: PARTENAIRES DU PROJET
A201: ID Projet | B201: ID partenaire | C201: Nom du partenaire | D201: Type de partenaire | E201: Role | F201: Statut
A234: FINANCEMENTS / DONATEURS DU PROJET
A235: ID Projet | B235: ID donateur | C235: Nom donateur | D235: Type donateur | E235: Source de financement | F235: Type de financement | G235: Montant demande | H235: Montant accorde | I235: Montant recu | J235: Devise | K235: Date de reception | L235: Statut
A236: PROJ0001 | C236: Fondation XYZ | E236: Fonds propres | F236: Subvention | G236: 10000000 | H236: 10000000 | I236: 6000000 | J236: FCFA | K236: 45323 | L236: Actif
A268: ZONES D'INTERVENTION DU PROJET (multi-localites)
A269: ID Projet | B269: Localite | C269: Pays | D269: Departement | E269: District/Commune | F269: Arrondissement | G269: Zone specifique
C270: =IFERROR(INDEX(#REF!,MATCH(B270,#REF!,0)),"") | D270: =IFERROR(INDEX(#REF!,MATCH(B270,#REF!,0)),"") | E270: =IFERROR(INDEX(#REF!,MATCH(B270,#REF!,0)),"") | F270: =IFERROR(INDEX(#REF!,MATCH(B270,#REF!,0)),"")
C271: =IFERROR(INDEX(#REF!,MATCH(B271,#REF!,0)),"") | D271: =IFERROR(INDEX(#REF!,MATCH(B271,#REF!,0)),"") | E271: =IFERROR(INDEX(#REF!,MATCH(B271,#REF!,0)),"") | F271: =IFERROR(INDEX(#REF!,MATCH(B271,#REF!,0)),"")
C272: =IFERROR(INDEX(#REF!,MATCH(B272,#REF!,0)),"") | D272: =IFERROR(INDEX(#REF!,MATCH(B272,#REF!,0)),"") | E272: =IFERROR(INDEX(#REF!,MATCH(B272,#REF!,0)),"") | F272: =IFERROR(INDEX(#REF!,MATCH(B272,#REF!,0)),"")
C273: =IFERROR(INDEX(#REF!,MATCH(B273,#REF!,0)),"") | D273: =IFERROR(INDEX(#REF!,MATCH(B273,#REF!,0)),"") | E273: =IFERROR(INDEX(#REF!,MATCH(B273,#REF!,0)),"") | F273: =IFERROR(INDEX(#REF!,MATCH(B273,#REF!,0)),"")
C274: =IFERROR(INDEX(#REF!,MATCH(B274,#REF!,0)),"") | D274: =IFERROR(INDEX(#REF!,MATCH(B274,#REF!,0)),"") | E274: =IFERROR(INDEX(#REF!,MATCH(B274,#REF!,0)),"") | F274: =IFERROR(INDEX(#REF!,MATCH(B274,#REF!,0)),"")
C275: =IFERROR(INDEX(#REF!,MATCH(B275,#REF!,0)),"") | D275: =IFERROR(INDEX(#REF!,MATCH(B275,#REF!,0)),"") | E275: =IFERROR(INDEX(#REF!,MATCH(B275,#REF!,0)),"") | F275: =IFERROR(INDEX(#REF!,MATCH(B275,#REF!,0)),"")
C276: =IFERROR(INDEX(#REF!,MATCH(B276,#REF!,0)),"") | D276: =IFERROR(INDEX(#REF!,MATCH(B276,#REF!,0)),"") | E276: =IFERROR(INDEX(#REF!,MATCH(B276,#REF!,0)),"") | F276: =IFERROR(INDEX(#REF!,MATCH(B276,#REF!,0)),"")
C277: =IFERROR(INDEX(#REF!,MATCH(B277,#REF!,0)),"") | D277: =IFERROR(INDEX(#REF!,MATCH(B277,#REF!,0)),"") | E277: =IFERROR(INDEX(#REF!,MATCH(B277,#REF!,0)),"") | F277: =IFERROR(INDEX(#REF!,MATCH(B277,#REF!,0)),"")
C278: =IFERROR(INDEX(#REF!,MATCH(B278,#REF!,0)),"") | D278: =IFERROR(INDEX(#REF!,MATCH(B278,#REF!,0)),"") | E278: =IFERROR(INDEX(#REF!,MATCH(B278,#REF!,0)),"") | F278: =IFERROR(INDEX(#REF!,MATCH(B278,#REF!,0)),"")
C279: =IFERROR(INDEX(#REF!,MATCH(B279,#REF!,0)),"") | D279: =IFERROR(INDEX(#REF!,MATCH(B279,#REF!,0)),"") | E279: =IFERROR(INDEX(#REF!,MATCH(B279,#REF!,0)),"") | F279: =IFERROR(INDEX(#REF!,MATCH(B279,#REF!,0)),"")
C280: =IFERROR(INDEX(#REF!,MATCH(B280,#REF!,0)),"") | D280: =IFERROR(INDEX(#REF!,MATCH(B280,#REF!,0)),"") | E280: =IFERROR(INDEX(#REF!,MATCH(B280,#REF!,0)),"") | F280: =IFERROR(INDEX(#REF!,MATCH(B280,#REF!,0)),"")
C281: =IFERROR(INDEX(#REF!,MATCH(B281,#REF!,0)),"") | D281: =IFERROR(INDEX(#REF!,MATCH(B281,#REF!,0)),"") | E281: =IFERROR(INDEX(#REF!,MATCH(B281,#REF!,0)),"") | F281: =IFERROR(INDEX(#REF!,MATCH(B281,#REF!,0)),"")
... C299: =IFERROR(INDEX(#REF!,MATCH(B299,#REF!,0)),"") | D299: =IFERROR(INDEX(#REF!,MATCH(B299,#REF!,0)),"") | E299: =IFERROR(INDEX(#REF!,MATCH(B299,#REF!,0)),"") | F299: =IFERROR(INDEX(#REF!,MATCH(B299,#REF!,0)),"")
A302: CALENDRIER / ETAPES DU PROJET
A303: ID Projet | B303: Etape | C303: Date prevue | D303: Date reelle | E303: Responsable | F303: Statut | G303: % realisation
A336: RISQUES DU PROJET
A337: ID Projet | B337: ID risque | C337: Risque principal | D337: Niveau de risque | E337: Probabilite | F337: Impact | G337: Mesure d'attenuation | H337: Responsable | I337: Statut
B338: =IF(A338="","","RIS"&TEXT(ROW()-337,"0000"))
B339: =IF(A339="","","RIS"&TEXT(ROW()-337,"0000"))
B340: =IF(A340="","","RIS"&TEXT(ROW()-337,"0000"))
B341: =IF(A341="","","RIS"&TEXT(ROW()-337,"0000"))
B342: =IF(A342="","","RIS"&TEXT(ROW()-337,"0000"))
B343: =IF(A343="","","RIS"&TEXT(ROW()-337,"0000"))
B344: =IF(A344="","","RIS"&TEXT(ROW()-337,"0000"))
...

Sheet ACTIVITES
A1: O.N.G BK — PLANIFICATION ET SUIVI DES ACTIVITES | Q1: -> PROJETS | R1: -> BENEFICIAIRES | S1: -> PARAMETRES
A2: Derniere mise a jour : voir cellule ci-dessous — Cette feuille alimente PROJETS, BENEFICIAIRES, BUDGET, RECETTES/FINANCEMENTS, DEPENSES, RESSOURCES HUMAINES, SUIVI-EVALUATION, RAPPORTS et TABLEAU DE BORD.
A4: LEGENDE : texte bleu = champ a completer manuellement | texte vert italique = donnee calculee automatiquement | ne pas modifier les colonnes calculees.
A6: SYNTHESE GENERALE DES ACTIVITES (calcul automatique)
A7: Total activites | B7: Planifiees | C7: En cours | D7: Realisees | E7: Reportees | F7: Annulees | G7: Taux global de realisation | H7: Nb projets concernes | I7: Total | J7: Total
A8: =COUNTIF(A56:A105,"ACT*") -> 1 | B8: =IF($I$7="Total",COUNTIFS(A56:A105,"ACT*",Z56:Z105,"Planifiee"),COUNTIFS(A56:A105,"ACT*",Z56:Z105,"Planifiee",S56:S105,$I$7)) -> 0 | C8: =IF($I$7="Total",COUNTIFS(A56:A105,"ACT*",Z56:Z105,"En cours"),COUNTIFS(A56:A105,"ACT*",Z56:Z105,"En cours",S56:S105,$I$7)) -> 1 | D8: =IF($I$7="Total",COUNTIFS(A56:A105,"ACT*",Z56:Z105,"Realisee"),COUNTIFS(A56:A105,"ACT*",Z56:Z105,"Realisee",S56:S105,$I$7)) -> 0 | E8: =IF($I$7="Total",COUNTIFS(A56:A105,"ACT*",Z56:Z105,"Reportee"),COUNTIFS(A56:A105,"ACT*",Z56:Z105,"Reportee",S56:S105,$I$7)) -> 0 | F8: =IF($I$7="Total",COUNTIFS(A56:A105,"ACT*",Z56:Z105,"Annulee"),COUNTIFS(A56:A105,"ACT*",Z56:Z105,"Annulee",S56:S105,$I$7)) -> 0 | G8: =IFERROR(D8/A8,0) -> 0 | H8: =SUMPRODUCT((C56:C105<>"")/COUNTIF(C56:C105,C56:C105&"")) -> 1
A10: ANALYSES AUTOMATIQUES
A11: Statut de l'activite | B11: Nb activites | D11: Type d'activite | E11: Nb activites | G11: Domaine d'intervention | H11: Nb activites
A12: Planifiee | B12: =COUNTIFS(tbl_Activites[Statut de l''activite],A12) -> 0 | D12: Formation | E12: =COUNTIFS(tbl_Activites[Type d''activite],D12) -> 0 | G12: Education | H12: =COUNTIFS(tbl_Activites[Domaine d''intervention (activite)],G12) -> 0
A13: En preparation | B13: =COUNTIFS(tbl_Activites[Statut de l''activite],A13) -> 0 | D13: Atelier | E13: =COUNTIFS(tbl_Activites[Type d''activite],D13) -> 0 | G13: Formation professionnelle | H13: =COUNTIFS(tbl_Activites[Domaine d''intervention (activite)],G13) -> 0
A14: Validee | B14: =COUNTIFS(tbl_Activites[Statut de l''activite],A14) -> 0 | D14: Seminaire | E14: =COUNTIFS(tbl_Activites[Type d''activite],D14) -> 0 | G14: Entrepreneuriat | H14: =COUNTIFS(tbl_Activites[Domaine d''intervention (activite)],G14) -> 0
A15: En cours | B15: =COUNTIFS(tbl_Activites[Statut de l''activite],A15) -> 1 | D15: Conference | E15: =COUNTIFS(tbl_Activites[Type d''activite],D15) -> 0 | G15: Culture | H15: =COUNTIFS(tbl_Activites[Domaine d''intervention (activite)],G15) -> 0
A16: Realisee | B16: =COUNTIFS(tbl_Activites[Statut de l''activite],A16) -> 0 | D16: Sensibilisation | E16: =COUNTIFS(tbl_Activites[Type d''activite],D16) -> 0 | G16: Environnement | H16: =COUNTIFS(tbl_Activites[Domaine d''intervention (activite)],G16) -> 0
A17: Partiellement realisee | B17: =COUNTIFS(tbl_Activites[Statut de l''activite],A17) -> 0 | D17: Campagne | E17: =COUNTIFS(tbl_Activites[Type d''activite],D17) -> 0 | G17: Sante | H17: =COUNTIFS(tbl_Activites[Domaine d''intervention (activite)],G17) -> 0
A18: Reportee | B18: =COUNTIFS(tbl_Activites[Statut de l''activite],A18) -> 0 | D18: Coaching | E18: =COUNTIFS(tbl_Activites[Type d''activite],D18) -> 0 | G18: Genre | H18: =COUNTIFS(tbl_Activites[Domaine d''intervention (activite)],G18) -> 0
A19: Suspendue | B19: =COUNTIFS(tbl_Activites[Statut de l''activite],A19) -> 0 | D19: Accompagnement | E19: =COUNTIFS(tbl_Activites[Type d''activite],D19) -> 0 | G19: Tourisme | H19: =COUNTIFS(tbl_Activites[Domaine d''intervention (activite)],G19) -> 0
A20: Annulee | B20: =COUNTIFS(tbl_Activites[Statut de l''activite],A20) -> 0 | D20: Distribution | E20: =COUNTIFS(tbl_Activites[Type d''activite],D20) -> 0 | G20: Sport | H20: =COUNTIFS(tbl_Activites[Domaine d''intervention (activite)],G20) -> 0
D21: Consultation | E21: =COUNTIFS(tbl_Activites[Type d''activite],D21) -> 0 | G21: Agriculture et developpement rural | H21: =COUNTIFS(tbl_Activites[Domaine d''intervention (activite)],G21) -> 0
D22: Enquete | E22: =COUNTIFS(tbl_Activites[Type d''activite],D22) -> 0 | G22: Elevage | H22: =COUNTIFS(tbl_Activites[Domaine d''intervention (activite)],G22) -> 0
D23: Etude | E23: =COUNTIFS(tbl_Activites[Type d''activite],D23) -> 0 | G23: Peche et aquaculture | H23: =COUNTIFS(tbl_Activites[Domaine d''intervention (activite)],G23) -> 0
D24: Recherche | E24: =COUNTIFS(tbl_Activites[Type d''activite],D24) -> 0 | G24: Securite alimentaire et nutrition | H24: =COUNTIFS(tbl_Activites[Domaine d''intervention (activite)],G24) -> 0
D25: Mission terrain | E25: =COUNTIFS(tbl_Activites[Type d''activite],D25) -> 0 | G25: Eau, hygiene et assainissement | H25: =COUNTIFS(tbl_Activites[Domaine d''intervention (activite)],G25) -> 0
D26: Visite | E26: =COUNTIFS(tbl_Activites[Type d''activite],D26) -> 0 | G26: Protection sociale | H26: =COUNTIFS(tbl_Activites[Domaine d''intervention (activite)],G26) -> 0
D27: Reunion | E27: =COUNTIFS(tbl_Activites[Type d''activite],D27) -> 0 | G27: Protection de l'enfance | H27: =COUNTIFS(tbl_Activites[Domaine d''intervention (activite)],G27) -> 0
D28: Forum | E28: =COUNTIFS(tbl_Activites[Type d''activite],D28) -> 0 | G28: Jeunesse | H28: =COUNTIFS(tbl_Activites[Domaine d''intervention (activite)],G28) -> 0
D29: Concours | E29: =COUNTIFS(tbl_Activites[Type d''activite],D29) -> 0 | G29: Autonomisation des femmes | H29: =COUNTIFS(tbl_Activites[Domaine d''intervention (activite)],G29) -> 0
D30: Competition sportive | E30: =COUNTIFS(tbl_Activites[Type d''activite],D30) -> 0 | G30: Developpement communautaire | H30: =COUNTIFS(tbl_Activites[Domaine d''intervention (activite)],G30) -> 0
D31: Evenement culturel | E31: =COUNTIFS(tbl_Activites[Type d''activite],D31) -> 0 | G31: Inclusion sociale | H31: =COUNTIFS(tbl_Activites[Domaine d''intervention (activite)],G31) -> 0
D32: Exposition | E32: =COUNTIFS(tbl_Activites[Type d''activite],D32) -> 0 | G32: Handicap et inclusion des personnes vulnerables | H32: =COUNTIFS(tbl_Activites[Domaine d''intervention (activite)],G32) -> 0
... D41: Autre | E41: =COUNTIFS(tbl_Activites[Type d''activite],D41) -> 0 | G41: Paix, cohesion sociale et prevention des conflits | H41: =COUNTIFS(tbl_Activites[Domaine d''intervention (activite)],G41) -> 0
G42: Action humanitaire et gestion des urgences | H42: =COUNTIFS(tbl_Activites[Domaine d''intervention (activite)],G42) -> 0
G43: Climat et resilience | H43: =COUNTIFS(tbl_Activites[Domaine d''intervention (activite)],G43) -> 0
G44: Gestion durable des ressources naturelles | H44: =COUNTIFS(tbl_Activites[Domaine d''intervention (activite)],G44) -> 0
G45: Biodiversite et conservation | H45: =COUNTIFS(tbl_Activites[Domaine d''intervention (activite)],G45) -> 0
G46: Infrastructures et equipements communautaires | H46: =COUNTIFS(tbl_Activites[Domaine d''intervention (activite)],G46) -> 0
G47: Developpement urbain et territorial | H47: =COUNTIFS(tbl_Activites[Domaine d''intervention (activite)],G47) -> 0
G48: Communication et information | H48: =COUNTIFS(tbl_Activites[Domaine d''intervention (activite)],G48) -> 0
G49: Mobilite et echanges culturels | H49: =COUNTIFS(tbl_Activites[Domaine d''intervention (activite)],G49) -> 0
G50: Patrimoine et tourisme culturel | H50: =COUNTIFS(tbl_Activites[Domaine d''intervention (activite)],G50) -> 0
G51: Autre domaine | H51: =COUNTIFS(tbl_Activites[Domaine d''intervention (activite)],G51) -> 0
A54: TABLEAU PRINCIPAL — LISTE DES ACTIVITES
A55: ID Activite | B55: Code interne | C55: ID Projet | D55: Nom du projet | E55: Domaine d'intervention (projet) | F55: Responsable du projet | G55: Intitule de l'activite | H55: Description | I55: Objectif de l'activite | J55: Type d'activite | K55: Domaine d'intervention (activite) | L55: Date prevue | M55: Heure debut prevue | N55: Heure fin prevue | O55: Duree prevue (h) | P55: Frequence | Q55: Mois | R55: Trimestre | S55: Annee | T55: Date reelle | U55: Heure reelle debut | V55: Heure reelle fin | W55: Duree reelle (h) | X55: Activite realisee | Y55: Niveau de realisation (%) | Z55: Statut de l'activite | AA55: Ecart (jours) | AB55: Activite en retard | AC55: ID responsable | AD55: Nom responsable | AE55: Fonction responsable | AF55: Telephone responsable | AG55: Email responsable | AH55: Localite | AI55: Pays | AJ55: Departement | AK55: District/Commune | AL55: Arrondissement | AM55: Site exact / Adresse | AN55: Coordonnees GPS | AO55: Nb beneficiaires prevu | AP55: Hommes prevus | AQ55: Femmes prevues | AR55: Enfants prevus | AS55: Jeunes prevus | AT55: Adultes prevus | AU55: Personnes vulnerables prevues | AV55: Nb participants reels | AW55: Hommes reels | AX55: Femmes reelles | AY55: Personnes vulnerables reelles | AZ55: Presence enregistree | BA55: Liste de presence disponible | BB55: Reference document presence | BC55: Budget prevu (FCFA) | BD55: Budget approuve (FCFA) | BE55: Depense reelle (FCFA) | BF55: Solde (FCFA) | BG55: Taux d'execution budgetaire | BH55: Source de financement | BI55: ID financement | BJ55: Montant prevu financement (FCFA) | BK55: Montant recu financement (FCFA) | BL55: Statut financement | BM55: Ressources necessaires | BN55: Prestataire / Fournisseur | BO55: Type de prestation | BP55: Reference contrat | BQ55: Montant prestation (FCFA) | BR55: Statut prestation | BS55: Resultat obtenu | BT55: Difficultes rencontrees | BU55: Solutions apportees | BV55: Ecart participants (reel-prevu) | BW55: Ecart budgetaire (FCFA) | BX55: Communication realisee | BY55: Photos disponibles | BZ55: Video disponible | CA55: Publication realisee | CB55: Support utilise | CC55: Lien support | CD55: Taux d'avancement (%) | CE55: Activite evaluee | CF55: Date evaluation | CG55: Evaluateur | CH55: Satisfaction (1-5) | CI55: Lecons apprises | CJ55: Recommandations | CK55: Nb documents justificatifs | CL55: Nb risques/incidents | CM55: Budget en depassement | CN55: Observations
A56: =IF(G56="","","ACT"&TEXT(ROW()-55,"00000")) -> ACT00001 | C56: PROJ0001 | D56: =IFERROR(INDEX(tbl_Projets[Titre complet du projet],MATCH(C56,tbl_Projets[ID Projet],0)),"") -> Projet d'appui a l'insertion professionnelle des jeunes | E56: =IFERROR(INDEX(tbl_Projets[Domaine d''intervention],MATCH(C56,tbl_Projets[ID Projet],0)),"") -> Education | F56: =IFERROR(INDEX(tbl_Projets[Nom du responsable],MATCH(C56,tbl_Projets[ID Projet],0)),"") -> Jean MABIALA | G56: VBG | L56: 46285 | O56: =IF(OR(M56="",N56=""),"",(N56-M56)*24) | Q56: =IF(L56="","",INDEX(PARAMETRES!$B$53:$B$65,MONTH(L56))) -> Septembre | R56: =IF(L56="","",INDEX(PARAMETRES!$C$53:$C$65,MONTH(L56))) -> T3 | S56: =IF(L56="","",YEAR(L56)) -> 2026 | T56: 46290 | U56: 7h00 | W56: =IF(OR(U56="",V56=""),"",(V56-U56)*24) | X56: Oui | Z56: En cours | AA56: =IF(AND(L56<>"",T56<>""),T56-L56,"") -> 5 | AB56: =IF(L56="","",IF(AND(TODAY()>L56,T56="",NOT(OR(Z56="Realisee",Z56="Annulee"))),"OUI","NON")) -> NON | AI56: =IFERROR(INDEX(PARAMETRES!$B$536:$B$586,MATCH(AH56,PARAMETRES!$J$536:$J$586,0)),"") | AJ56: =IFERROR(INDEX(PARAMETRES!$D$536:$D$586,MATCH(AH56,PARAMETRES!$J$536:$J$586,0)),"") | AK56: =IFERROR(INDEX(PARAMETRES!$F$536:$F$586,MATCH(AH56,PARAMETRES!$J$536:$J$586,0)),"") | AL56: =IFERROR(INDEX(PARAMETRES!$H$536:$H$586,MATCH(AH56,PARAMETRES!$J$536:$J$586,0)),"") | AV56: =IF(A56="",0,COUNTIFS(tbl_Beneficiaires_Activites[ID activite],A56)) -> 0 | BF56: =IF(BD56="",0,BD56)-IF(BE56="",0,BE56) -> 0 | BG56: =IF(OR(BD56="",BD56=0),0,BE56/BD56) -> 0 | BH56: Subvention | BV56: =IF(OR(AO56="",AV56=""),"",AV56-AO56) | BW56: =IF(OR(BE56="",BD56=""),"",BE56-BD56) | CE56: Oui | CK56: =IF(A56="",0,COUNTIF(tbl_Activites_Documents[ID Activite],A56)) -> 0 | CL56: =IF(A56="",0,COUNTIF(tbl_Activites_Risques[ID Activite],A56)) -> 0 | CM56: =IF(A56="","",IF(BE56>BD56,"OUI","NON")) -> NON
A57: =IF(G57="","","ACT"&TEXT(ROW()-55,"00000")) | D57: =IFERROR(INDEX(tbl_Projets[Titre complet du projet],MATCH(C57,tbl_Projets[ID Projet],0)),"") | E57: =IFERROR(INDEX(tbl_Projets[Domaine d''intervention],MATCH(C57,tbl_Projets[ID Projet],0)),"") | F57: =IFERROR(INDEX(tbl_Projets[Nom du responsable],MATCH(C57,tbl_Projets[ID Projet],0)),"") | O57: =IF(OR(M57="",N57=""),"",(N57-M57)*24) | Q57: =IF(L57="","",INDEX(PARAMETRES!$B$53:$B$65,MONTH(L57))) | R57: =IF(L57="","",INDEX(PARAMETRES!$C$53:$C$65,MONTH(L57))) | S57: =IF(L57="","",YEAR(L57)) | W57: =IF(OR(U57="",V57=""),"",(V57-U57)*24) | AA57: =IF(AND(L57<>"",T57<>""),T57-L57,"") | AB57: =IF(L57="","",IF(AND(TODAY()>L57,T57="",NOT(OR(Z57="Realisee",Z57="Annulee"))),"OUI","NON")) | AI57: =IFERROR(INDEX(PARAMETRES!$B$536:$B$586,MATCH(AH57,PARAMETRES!$J$536:$J$586,0)),"") | AJ57: =IFERROR(INDEX(PARAMETRES!$D$536:$D$586,MATCH(AH57,PARAMETRES!$J$536:$J$586,0)),"") | AK57: =IFERROR(INDEX(PARAMETRES!$F$536:$F$586,MATCH(AH57,PARAMETRES!$J$536:$J$586,0)),"") | AL57: =IFERROR(INDEX(PARAMETRES!$H$536:$H$586,MATCH(AH57,PARAMETRES!$J$536:$J$586,0)),"") | AV57: =IF(A57="",0,COUNTIFS(tbl_Beneficiaires_Activites[ID activite],A57)) -> 0 | BF57: =IF(BD57="",0,BD57)-IF(BE57="",0,BE57) -> 0 | BG57: =IF(OR(BD57="",BD57=0),0,BE57/BD57) -> 0 | BV57: =IF(OR(AO57="",AV57=""),"",AV57-AO57) | BW57: =IF(OR(BE57="",BD57=""),"",BE57-BD57) | CK57: =IF(A57="",0,COUNTIF(tbl_Activites_Documents[ID Activite],A57)) -> 0 | CL57: =IF(A57="",0,COUNTIF(tbl_Activites_Risques[ID Activite],A57)) -> 0 | CM57: =IF(A57="","",IF(BE57>BD57,"OUI","NON"))
A58: =IF(G58="","","ACT"&TEXT(ROW()-55,"00000")) | D58: =IFERROR(INDEX(tbl_Projets[Titre complet du projet],MATCH(C58,tbl_Projets[ID Projet],0)),"") | E58: =IFERROR(INDEX(tbl_Projets[Domaine d''intervention],MATCH(C58,tbl_Projets[ID Projet],0)),"") | F58: =IFERROR(INDEX(tbl_Projets[Nom du responsable],MATCH(C58,tbl_Projets[ID Projet],0)),"") | O58: =IF(OR(M58="",N58=""),"",(N58-M58)*24) | Q58: =IF(L58="","",INDEX(PARAMETRES!$B$53:$B$65,MONTH(L58))) | R58: =IF(L58="","",INDEX(PARAMETRES!$C$53:$C$65,MONTH(L58))) | S58: =IF(L58="","",YEAR(L58)) | W58: =IF(OR(U58="",V58=""),"",(V58-U58)*24) | AA58: =IF(AND(L58<>"",T58<>""),T58-L58,"") | AB58: =IF(L58="","",IF(AND(TODAY()>L58,T58="",NOT(OR(Z58="Realisee",Z58="Annulee"))),"OUI","NON")) | AI58: =IFERROR(INDEX(PARAMETRES!$B$536:$B$586,MATCH(AH58,PARAMETRES!$J$536:$J$586,0)),"") | AJ58: =IFERROR(INDEX(PARAMETRES!$D$536:$D$586,MATCH(AH58,PARAMETRES!$J$536:$J$586,0)),"") | AK58: =IFERROR(INDEX(PARAMETRES!$F$536:$F$586,MATCH(AH58,PARAMETRES!$J$536:$J$586,0)),"") | AL58: =IFERROR(INDEX(PARAMETRES!$H$536:$H$586,MATCH(AH58,PARAMETRES!$J$536:$J$586,0)),"") | AV58: =IF(A58="",0,COUNTIFS(tbl_Beneficiaires_Activites[ID activite],A58)) -> 0 | BF58: =IF(BD58="",0,BD58)-IF(BE58="",0,BE58) -> 0 | BG58: =IF(OR(BD58="",BD58=0),0,BE58/BD58) -> 0 | BV58: =IF(OR(AO58="",AV58=""),"",AV58-AO58) | BW58: =IF(OR(BE58="",BD58=""),"",BE58-BD58) | CK58: =IF(A58="",0,COUNTIF(tbl_Activites_Documents[ID Activite],A58)) -> 0 | CL58: =IF(A58="",0,COUNTIF(tbl_Activites_Risques[ID Activite],A58)) -> 0 | CM58: =IF(A58="","",IF(BE58>BD58,"OUI","NON"))
A59: =IF(G59="","","ACT"&TEXT(ROW()-55,"00000")) | D59: =IFERROR(INDEX(tbl_Projets[Titre complet du projet],MATCH(C59,tbl_Projets[ID Projet],0)),"") | E59: =IFERROR(INDEX(tbl_Projets[Domaine d''intervention],MATCH(C59,tbl_Projets[ID Projet],0)),"") | F59: =IFERROR(INDEX(tbl_Projets[Nom du responsable],MATCH(C59,tbl_Projets[ID Projet],0)),"") | O59: =IF(OR(M59="",N59=""),"",(N59-M59)*24) | Q59: =IF(L59="","",INDEX(PARAMETRES!$B$53:$B$65,MONTH(L59))) | R59: =IF(L59="","",INDEX(PARAMETRES!$C$53:$C$65,MONTH(L59))) | S59: =IF(L59="","",YEAR(L59)) | W59: =IF(OR(U59="",V59=""),"",(V59-U59)*24) | AA59: =IF(AND(L59<>"",T59<>""),T59-L59,"") | AB59: =IF(L59="","",IF(AND(TODAY()>L59,T59="",NOT(OR(Z59="Realisee",Z59="Annulee"))),"OUI","NON")) | AI59: =IFERROR(INDEX(PARAMETRES!$B$536:$B$586,MATCH(AH59,PARAMETRES!$J$536:$J$586,0)),"") | AJ59: =IFERROR(INDEX(PARAMETRES!$D$536:$D$586,MATCH(AH59,PARAMETRES!$J$536:$J$586,0)),"") | AK59: =IFERROR(INDEX(PARAMETRES!$F$536:$F$586,MATCH(AH59,PARAMETRES!$J$536:$J$586,0)),"") | AL59: =IFERROR(INDEX(PARAMETRES!$H$536:$H$586,MATCH(AH59,PARAMETRES!$J$536:$J$586,0)),"") | AV59: =IF(A59="",0,COUNTIFS(tbl_Beneficiaires_Activites[ID activite],A59)) -> 0 | BF59: =IF(BD59="",0,BD59)-IF(BE59="",0,BE59) -> 0 | BG59: =IF(OR(BD59="",BD59=0),0,BE59/BD59) -> 0 | BV59: =IF(OR(AO59="",AV59=""),"",AV59-AO59) | BW59: =IF(OR(BE59="",BD59=""),"",BE59-BD59) | CK59: =IF(A59="",0,COUNTIF(tbl_Activites_Documents[ID Activite],A59)) -> 0 | CL59: =IF(A59="",0,COUNTIF(tbl_Activites_Risques[ID Activite],A59)) -> 0 | CM59: =IF(A59="","",IF(BE59>BD59,"OUI","NON"))
A60: =IF(G60="","","ACT"&TEXT(ROW()-55,"00000")) | D60: =IFERROR(INDEX(tbl_Projets[Titre complet du projet],MATCH(C60,tbl_Projets[ID Projet],0)),"") | E60: =IFERROR(INDEX(tbl_Projets[Domaine d''intervention],MATCH(C60,tbl_Projets[ID Projet],0)),"") | F60: =IFERROR(INDEX(tbl_Projets[Nom du responsable],MATCH(C60,tbl_Projets[ID Projet],0)),"") | O60: =IF(OR(M60="",N60=""),"",(N60-M60)*24) | Q60: =IF(L60="","",INDEX(PARAMETRES!$B$53:$B$65,MONTH(L60))) | R60: =IF(L60="","",INDEX(PARAMETRES!$C$53:$C$65,MONTH(L60))) | S60: =IF(L60="","",YEAR(L60)) | W60: =IF(OR(U60="",V60=""),"",(V60-U60)*24) | AA60: =IF(AND(L60<>"",T60<>""),T60-L60,"") | AB60: =IF(L60="","",IF(AND(TODAY()>L60,T60="",NOT(OR(Z60="Realisee",Z60="Annulee"))),"OUI","NON")) | AI60: =IFERROR(INDEX(PARAMETRES!$B$536:$B$586,MATCH(AH60,PARAMETRES!$J$536:$J$586,0)),"") | AJ60: =IFERROR(INDEX(PARAMETRES!$D$536:$D$586,MATCH(AH60,PARAMETRES!$J$536:$J$586,0)),"") | AK60: =IFERROR(INDEX(PARAMETRES!$F$536:$F$586,MATCH(AH60,PARAMETRES!$J$536:$J$586,0)),"") | AL60: =IFERROR(INDEX(PARAMETRES!$H$536:$H$586,MATCH(AH60,PARAMETRES!$J$536:$J$586,0)),"") | AV60: =IF(A60="",0,COUNTIFS(tbl_Beneficiaires_Activites[ID activite],A60)) -> 0 | BF60: =IF(BD60="",0,BD60)-IF(BE60="",0,BE60) -> 0 | BG60: =IF(OR(BD60="",BD60=0),0,BE60/BD60) -> 0 | BV60: =IF(OR(AO60="",AV60=""),"",AV60-AO60) | BW60: =IF(OR(BE60="",BD60=""),"",BE60-BD60) | CK60: =IF(A60="",0,COUNTIF(tbl_Activites_Documents[ID Activite],A60)) -> 0 | CL60: =IF(A60="",0,COUNTIF(tbl_Activites_Risques[ID Activite],A60)) -> 0 | CM60: =IF(A60="","",IF(BE60>BD60,"OUI","NON"))
A61: =IF(G61="","","ACT"&TEXT(ROW()-55,"00000")) | D61: =IFERROR(INDEX(tbl_Projets[Titre complet du projet],MATCH(C61,tbl_Projets[ID Projet],0)),"") | E61: =IFERROR(INDEX(tbl_Projets[Domaine d''intervention],MATCH(C61,tbl_Projets[ID Projet],0)),"") | F61: =IFERROR(INDEX(tbl_Projets[Nom du responsable],MATCH(C61,tbl_Projets[ID Projet],0)),"") | O61: =IF(OR(M61="",N61=""),"",(N61-M61)*24) | Q61: =IF(L61="","",INDEX(PARAMETRES!$B$53:$B$65,MONTH(L61))) | R61: =IF(L61="","",INDEX(PARAMETRES!$C$53:$C$65,MONTH(L61))) | S61: =IF(L61="","",YEAR(L61)) | W61: =IF(OR(U61="",V61=""),"",(V61-U61)*24) | AA61: =IF(AND(L61<>"",T61<>""),T61-L61,"") | AB61: =IF(L61="","",IF(AND(TODAY()>L61,T61="",NOT(OR(Z61="Realisee",Z61="Annulee"))),"OUI","NON")) | AI61: =IFERROR(INDEX(PARAMETRES!$B$536:$B$586,MATCH(AH61,PARAMETRES!$J$536:$J$586,0)),"") | AJ61: =IFERROR(INDEX(PARAMETRES!$D$536:$D$586,MATCH(AH61,PARAMETRES!$J$536:$J$586,0)),"") | AK61: =IFERROR(INDEX(PARAMETRES!$F$536:$F$586,MATCH(AH61,PARAMETRES!$J$536:$J$586,0)),"") | AL61: =IFERROR(INDEX(PARAMETRES!$H$536:$H$586,MATCH(AH61,PARAMETRES!$J$536:$J$586,0)),"") | AV61: =IF(A61="",0,COUNTIFS(tbl_Beneficiaires_Activites[ID activite],A61)) -> 0 | BF61: =IF(BD61="",0,BD61)-IF(BE61="",0,BE61) -> 0 | BG61: =IF(OR(BD61="",BD61=0),0,BE61/BD61) -> 0 | BV61: =IF(OR(AO61="",AV61=""),"",AV61-AO61) | BW61: =IF(OR(BE61="",BD61=""),"",BE61-BD61) | CK61: =IF(A61="",0,COUNTIF(tbl_Activites_Documents[ID Activite],A61)) -> 0 | CL61: =IF(A61="",0,COUNTIF(tbl_Activites_Risques[ID Activite],A61)) -> 0 | CM61: =IF(A61="","",IF(BE61>BD61,"OUI","NON"))
A62: =IF(G62="","","ACT"&TEXT(ROW()-55,"00000")) | D62: =IFERROR(INDEX(tbl_Projets[Titre complet du projet],MATCH(C62,tbl_Projets[ID Projet],0)),"") | E62: =IFERROR(INDEX(tbl_Projets[Domaine d''intervention],MATCH(C62,tbl_Projets[ID Projet],0)),"") | F62: =IFERROR(INDEX(tbl_Projets[Nom du responsable],MATCH(C62,tbl_Projets[ID Projet],0)),"") | O62: =IF(OR(M62="",N62=""),"",(N62-M62)*24) | Q62: =IF(L62="","",INDEX(PARAMETRES!$B$53:$B$65,MONTH(L62))) | R62: =IF(L62="","",INDEX(PARAMETRES!$C$53:$C$65,MONTH(L62))) | S62: =IF(L62="","",YEAR(L62)) | W62: =IF(OR(U62="",V62=""),"",(V62-U62)*24) | AA62: =IF(AND(L62<>"",T62<>""),T62-L62,"") | AB62: =IF(L62="","",IF(AND(TODAY()>L62,T62="",NOT(OR(Z62="Realisee",Z62="Annulee"))),"OUI","NON")) | AI62: =IFERROR(INDEX(PARAMETRES!$B$536:$B$586,MATCH(AH62,PARAMETRES!$J$536:$J$586,0)),"") | AJ62: =IFERROR(INDEX(PARAMETRES!$D$536:$D$586,MATCH(AH62,PARAMETRES!$J$536:$J$586,0)),"") | AK62: =IFERROR(INDEX(PARAMETRES!$F$536:$F$586,MATCH(AH62,PARAMETRES!$J$536:$J$586,0)),"") | AL62: =IFERROR(INDEX(PARAMETRES!$H$536:$H$586,MATCH(AH62,PARAMETRES!$J$536:$J$586,0)),"") | AV62: =IF(A62="",0,COUNTIFS(tbl_Beneficiaires_Activites[ID activite],A62)) -> 0 | BF62: =IF(BD62="",0,BD62)-IF(BE62="",0,BE62) -> 0 | BG62: =IF(OR(BD62="",BD62=0),0,BE62/BD62) -> 0 | BV62: =IF(OR(AO62="",AV62=""),"",AV62-AO62) | BW62: =IF(OR(BE62="",BD62=""),"",BE62-BD62) | CK62: =IF(A62="",0,COUNTIF(tbl_Activites_Documents[ID Activite],A62)) -> 0 | CL62: =IF(A62="",0,COUNTIF(tbl_Activites_Risques[ID Activite],A62)) -> 0 | CM62: =IF(A62="","",IF(BE62>BD62,"OUI","NON"))
A63: =IF(G63="","","ACT"&TEXT(ROW()-55,"00000")) | D63: =IFERROR(INDEX(tbl_Projets[Titre complet du projet],MATCH(C63,tbl_Projets[ID Projet],0)),"") | E63: =IFERROR(INDEX(tbl_Projets[Domaine d''intervention],MATCH(C63,tbl_Projets[ID Projet],0)),"") | F63: =IFERROR(INDEX(tbl_Projets[Nom du responsable],MATCH(C63,tbl_Projets[ID Projet],0)),"") | O63: =IF(OR(M63="",N63=""),"",(N63-M63)*24) | Q63: =IF(L63="","",INDEX(PARAMETRES!$B$53:$B$65,MONTH(L63))) | R63: =IF(L63="","",INDEX(PARAMETRES!$C$53:$C$65,MONTH(L63))) | S63: =IF(L63="","",YEAR(L63)) | W63: =IF(OR(U63="",V63=""),"",(V63-U63)*24) | AA63: =IF(AND(L63<>"",T63<>""),T63-L63,"") | AB63: =IF(L63="","",IF(AND(TODAY()>L63,T63="",NOT(OR(Z63="Realisee",Z63="Annulee"))),"OUI","NON")) | AI63: =IFERROR(INDEX(PARAMETRES!$B$536:$B$586,MATCH(AH63,PARAMETRES!$J$536:$J$586,0)),"") | AJ63: =IFERROR(INDEX(PARAMETRES!$D$536:$D$586,MATCH(AH63,PARAMETRES!$J$536:$J$586,0)),"") | AK63: =IFERROR(INDEX(PARAMETRES!$F$536:$F$586,MATCH(AH63,PARAMETRES!$J$536:$J$586,0)),"") | AL63: =IFERROR(INDEX(PARAMETRES!$H$536:$H$586,MATCH(AH63,PARAMETRES!$J$536:$J$586,0)),"") | AV63: =IF(A63="",0,COUNTIFS(tbl_Beneficiaires_Activites[ID activite],A63)) -> 0 | BF63: =IF(BD63="",0,BD63)-IF(BE63="",0,BE63) -> 0 | BG63: =IF(OR(BD63="",BD63=0),0,BE63/BD63) -> 0 | BV63: =IF(OR(AO63="",AV63=""),"",AV63-AO63) | BW63: =IF(OR(BE63="",BD63=""),"",BE63-BD63) | CK63: =IF(A63="",0,COUNTIF(tbl_Activites_Documents[ID Activite],A63)) -> 0 | CL63: =IF(A63="",0,COUNTIF(tbl_Activites_Risques[ID Activite],A63)) -> 0 | CM63: =IF(A63="","",IF(BE63>BD63,"OUI","NON"))
A64: =IF(G64="","","ACT"&TEXT(ROW()-55,"00000")) | D64: =IFERROR(INDEX(tbl_Projets[Titre complet du projet],MATCH(C64,tbl_Projets[ID Projet],0)),"") | E64: =IFERROR(INDEX(tbl_Projets[Domaine d''intervention],MATCH(C64,tbl_Projets[ID Projet],0)),"") | F64: =IFERROR(INDEX(tbl_Projets[Nom du responsable],MATCH(C64,tbl_Projets[ID Projet],0)),"") | O64: =IF(OR(M64="",N64=""),"",(N64-M64)*24) | Q64: =IF(L64="","",INDEX(PARAMETRES!$B$53:$B$65,MONTH(L64))) | R64: =IF(L64="","",INDEX(PARAMETRES!$C$53:$C$65,MONTH(L64))) | S64: =IF(L64="","",YEAR(L64)) | W64: =IF(OR(U64="",V64=""),"",(V64-U64)*24) | AA64: =IF(AND(L64<>"",T64<>""),T64-L64,"") | AB64: =IF(L64="","",IF(AND(TODAY()>L64,T64="",NOT(OR(Z64="Realisee",Z64="Annulee"))),"OUI","NON")) | AI64: =IFERROR(INDEX(PARAMETRES!$B$536:$B$586,MATCH(AH64,PARAMETRES!$J$536:$J$586,0)),"") | AJ64: =IFERROR(INDEX(PARAMETRES!$D$536:$D$586,MATCH(AH64,PARAMETRES!$J$536:$J$586,0)),"") | AK64: =IFERROR(INDEX(PARAMETRES!$F$536:$F$586,MATCH(AH64,PARAMETRES!$J$536:$J$586,0)),"") | AL64: =IFERROR(INDEX(PARAMETRES!$H$536:$H$586,MATCH(AH64,PARAMETRES!$J$536:$J$586,0)),"") | AV64: =IF(A64="",0,COUNTIFS(tbl_Beneficiaires_Activites[ID activite],A64)) -> 0 | BF64: =IF(BD64="",0,BD64)-IF(BE64="",0,BE64) -> 0 | BG64: =IF(OR(BD64="",BD64=0),0,BE64/BD64) -> 0 | BV64: =IF(OR(AO64="",AV64=""),"",AV64-AO64) | BW64: =IF(OR(BE64="",BD64=""),"",BE64-BD64) | CK64: =IF(A64="",0,COUNTIF(tbl_Activites_Documents[ID Activite],A64)) -> 0 | CL64: =IF(A64="",0,COUNTIF(tbl_Activites_Risques[ID Activite],A64)) -> 0 | CM64: =IF(A64="","",IF(BE64>BD64,"OUI","NON"))
A65: =IF(G65="","","ACT"&TEXT(ROW()-55,"00000")) | D65: =IFERROR(INDEX(tbl_Projets[Titre complet du projet],MATCH(C65,tbl_Projets[ID Projet],0)),"") | E65: =IFERROR(INDEX(tbl_Projets[Domaine d''intervention],MATCH(C65,tbl_Projets[ID Projet],0)),"") | F65: =IFERROR(INDEX(tbl_Projets[Nom du responsable],MATCH(C65,tbl_Projets[ID Projet],0)),"") | O65: =IF(OR(M65="",N65=""),"",(N65-M65)*24) | Q65: =IF(L65="","",INDEX(PARAMETRES!$B$53:$B$65,MONTH(L65))) | R65: =IF(L65="","",INDEX(PARAMETRES!$C$53:$C$65,MONTH(L65))) | S65: =IF(L65="","",YEAR(L65)) | W65: =IF(OR(U65="",V65=""),"",(V65-U65)*24) | AA65: =IF(AND(L65<>"",T65<>""),T65-L65,"") | AB65: =IF(L65="","",IF(AND(TODAY()>L65,T65="",NOT(OR(Z65="Realisee",Z65="Annulee"))),"OUI","NON")) | AI65: =IFERROR(INDEX(PARAMETRES!$B$536:$B$586,MATCH(AH65,PARAMETRES!$J$536:$J$586,0)),"") | AJ65: =IFERROR(INDEX(PARAMETRES!$D$536:$D$586,MATCH(AH65,PARAMETRES!$J$536:$J$586,0)),"") | AK65: =IFERROR(INDEX(PARAMETRES!$F$536:$F$586,MATCH(AH65,PARAMETRES!$J$536:$J$586,0)),"") | AL65: =IFERROR(INDEX(PARAMETRES!$H$536:$H$586,MATCH(AH65,PARAMETRES!$J$536:$J$586,0)),"") | AV65: =IF(A65="",0,COUNTIFS(tbl_Beneficiaires_Activites[ID activite],A65)) -> 0 | BF65: =IF(BD65="",0,BD65)-IF(BE65="",0,BE65) -> 0 | BG65: =IF(OR(BD65="",BD65=0),0,BE65/BD65) -> 0 | BV65: =IF(OR(AO65="",AV65=""),"",AV65-AO65) | BW65: =IF(OR(BE65="",BD65=""),"",BE65-BD65) | CK65: =IF(A65="",0,COUNTIF(tbl_Activites_Documents[ID Activite],A65)) -> 0 | CL65: =IF(A65="",0,COUNTIF(tbl_Activites_Risques[ID Activite],A65)) -> 0 | CM65: =IF(A65="","",IF(BE65>BD65,"OUI","NON"))
A66: =IF(G66="","","ACT"&TEXT(ROW()-55,"00000")) | D66: =IFERROR(INDEX(tbl_Projets[Titre complet du projet],MATCH(C66,tbl_Projets[ID Projet],0)),"") | E66: =IFERROR(INDEX(tbl_Projets[Domaine d''intervention],MATCH(C66,tbl_Projets[ID Projet],0)),"") | F66: =IFERROR(INDEX(tbl_Projets[Nom du responsable],MATCH(C66,tbl_Projets[ID Projet],0)),"") | O66: =IF(OR(M66="",N66=""),"",(N66-M66)*24) | Q66: =IF(L66="","",INDEX(PARAMETRES!$B$53:$B$65,MONTH(L66))) | R66: =IF(L66="","",INDEX(PARAMETRES!$C$53:$C$65,MONTH(L66))) | S66: =IF(L66="","",YEAR(L66)) | W66: =IF(OR(U66="",V66=""),"",(V66-U66)*24) | AA66: =IF(AND(L66<>"",T66<>""),T66-L66,"") | AB66: =IF(L66="","",IF(AND(TODAY()>L66,T66="",NOT(OR(Z66="Realisee",Z66="Annulee"))),"OUI","NON")) | AI66: =IFERROR(INDEX(PARAMETRES!$B$536:$B$586,MATCH(AH66,PARAMETRES!$J$536:$J$586,0)),"") | AJ66: =IFERROR(INDEX(PARAMETRES!$D$536:$D$586,MATCH(AH66,PARAMETRES!$J$536:$J$586,0)),"") | AK66: =IFERROR(INDEX(PARAMETRES!$F$536:$F$586,MATCH(AH66,PARAMETRES!$J$536:$J$586,0)),"") | AL66: =IFERROR(INDEX(PARAMETRES!$H$536:$H$586,MATCH(AH66,PARAMETRES!$J$536:$J$586,0)),"") | AV66: =IF(A66="",0,COUNTIFS(tbl_Beneficiaires_Activites[ID activite],A66)) -> 0 | BF66: =IF(BD66="",0,BD66)-IF(BE66="",0,BE66) -> 0 | BG66: =IF(OR(BD66="",BD66=0),0,BE66/BD66) -> 0 | BV66: =IF(OR(AO66="",AV66=""),"",AV66-AO66) | BW66: =IF(OR(BE66="",BD66=""),"",BE66-BD66) | CK66: =IF(A66="",0,COUNTIF(tbl_Activites_Documents[ID Activite],A66)) -> 0 | CL66: =IF(A66="",0,COUNTIF(tbl_Activites_Risques[ID Activite],A66)) -> 0 | CM66: =IF(A66="","",IF(BE66>BD66,"OUI","NON"))
A67: =IF(G67="","","ACT"&TEXT(ROW()-55,"00000")) | D67: =IFERROR(INDEX(tbl_Projets[Titre complet du projet],MATCH(C67,tbl_Projets[ID Projet],0)),"") | E67: =IFERROR(INDEX(tbl_Projets[Domaine d''intervention],MATCH(C67,tbl_Projets[ID Projet],0)),"") | F67: =IFERROR(INDEX(tbl_Projets[Nom du responsable],MATCH(C67,tbl_Projets[ID Projet],0)),"") | O67: =IF(OR(M67="",N67=""),"",(N67-M67)*24) | Q67: =IF(L67="","",INDEX(PARAMETRES!$B$53:$B$65,MONTH(L67))) | R67: =IF(L67="","",INDEX(PARAMETRES!$C$53:$C$65,MONTH(L67))) | S67: =IF(L67="","",YEAR(L67)) | W67: =IF(OR(U67="",V67=""),"",(V67-U67)*24) | AA67: =IF(AND(L67<>"",T67<>""),T67-L67,"") | AB67: =IF(L67="","",IF(AND(TODAY()>L67,T67="",NOT(OR(Z67="Realisee",Z67="Annulee"))),"OUI","NON")) | AI67: =IFERROR(INDEX(PARAMETRES!$B$536:$B$586,MATCH(AH67,PARAMETRES!$J$536:$J$586,0)),"") | AJ67: =IFERROR(INDEX(PARAMETRES!$D$536:$D$586,MATCH(AH67,PARAMETRES!$J$536:$J$586,0)),"") | AK67: =IFERROR(INDEX(PARAMETRES!$F$536:$F$586,MATCH(AH67,PARAMETRES!$J$536:$J$586,0)),"") | AL67: =IFERROR(INDEX(PARAMETRES!$H$536:$H$586,MATCH(AH67,PARAMETRES!$J$536:$J$586,0)),"") | AV67: =IF(A67="",0,COUNTIFS(tbl_Beneficiaires_Activites[ID activite],A67)) -> 0 | BF67: =IF(BD67="",0,BD67)-IF(BE67="",0,BE67) -> 0 | BG67: =IF(OR(BD67="",BD67=0),0,BE67/BD67) -> 0 | BV67: =IF(OR(AO67="",AV67=""),"",AV67-AO67) | BW67: =IF(OR(BE67="",BD67=""),"",BE67-BD67) | CK67: =IF(A67="",0,COUNTIF(tbl_Activites_Documents[ID Activite],A67)) -> 0 | CL67: =IF(A67="",0,COUNTIF(tbl_Activites_Risques[ID Activite],A67)) -> 0 | CM67: =IF(A67="","",IF(BE67>BD67,"OUI","NON"))
A68: =IF(G68="","","ACT"&TEXT(ROW()-55,"00000")) | D68: =IFERROR(INDEX(tbl_Projets[Titre complet du projet],MATCH(C68,tbl_Projets[ID Projet],0)),"") | E68: =IFERROR(INDEX(tbl_Projets[Domaine d''intervention],MATCH(C68,tbl_Projets[ID Projet],0)),"") | F68: =IFERROR(INDEX(tbl_Projets[Nom du responsable],MATCH(C68,tbl_Projets[ID Projet],0)),"") | O68: =IF(OR(M68="",N68=""),"",(N68-M68)*24) | Q68: =IF(L68="","",INDEX(PARAMETRES!$B$53:$B$65,MONTH(L68))) | R68: =IF(L68="","",INDEX(PARAMETRES!$C$53:$C$65,MONTH(L68))) | S68: =IF(L68="","",YEAR(L68)) | W68: =IF(OR(U68="",V68=""),"",(V68-U68)*24) | AA68: =IF(AND(L68<>"",T68<>""),T68-L68,"") | AB68: =IF(L68="","",IF(AND(TODAY()>L68,T68="",NOT(OR(Z68="Realisee",Z68="Annulee"))),"OUI","NON")) | AI68: =IFERROR(INDEX(PARAMETRES!$B$536:$B$586,MATCH(AH68,PARAMETRES!$J$536:$J$586,0)),"") | AJ68: =IFERROR(INDEX(PARAMETRES!$D$536:$D$586,MATCH(AH68,PARAMETRES!$J$536:$J$586,0)),"") | AK68: =IFERROR(INDEX(PARAMETRES!$F$536:$F$586,MATCH(AH68,PARAMETRES!$J$536:$J$586,0)),"") | AL68: =IFERROR(INDEX(PARAMETRES!$H$536:$H$586,MATCH(AH68,PARAMETRES!$J$536:$J$586,0)),"") | AV68: =IF(A68="",0,COUNTIFS(tbl_Beneficiaires_Activites[ID activite],A68)) -> 0 | BF68: =IF(BD68="",0,BD68)-IF(BE68="",0,BE68) -> 0 | BG68: =IF(OR(BD68="",BD68=0),0,BE68/BD68) -> 0 | BV68: =IF(OR(AO68="",AV68=""),"",AV68-AO68) | BW68: =IF(OR(BE68="",BD68=""),"",BE68-BD68) | CK68: =IF(A68="",0,COUNTIF(tbl_Activites_Documents[ID Activite],A68)) -> 0 | CL68: =IF(A68="",0,COUNTIF(tbl_Activites_Risques[ID Activite],A68)) -> 0 | CM68: =IF(A68="","",IF(BE68>BD68,"OUI","NON"))
... A105: =IF(G105="","","ACT"&TEXT(ROW()-55,"00000")) | D105: =IFERROR(INDEX(tbl_Projets[Titre complet du projet],MATCH(C105,tbl_Projets[ID Projet],0)),"") | E105: =IFERROR(INDEX(tbl_Projets[Domaine d''intervention],MATCH(C105,tbl_Projets[ID Projet],0)),"") | F105: =IFERROR(INDEX(tbl_Projets[Nom du responsable],MATCH(C105,tbl_Projets[ID Projet],0)),"") | O105: =IF(OR(M105="",N105=""),"",(N105-M105)*24) | Q105: =IF(L105="","",INDEX(PARAMETRES!$B$53:$B$65,MONTH(L105))) | R105: =IF(L105="","",INDEX(PARAMETRES!$C$53:$C$65,MONTH(L105))) | S105: =IF(L105="","",YEAR(L105)) | W105: =IF(OR(U105="",V105=""),"",(V105-U105)*24) | AA105: =IF(AND(L105<>"",T105<>""),T105-L105,"") | AB105: =IF(L105="","",IF(AND(TODAY()>L105,T105="",NOT(OR(Z105="Realisee",Z105="Annulee"))),"OUI","NON")) | AI105: =IFERROR(INDEX(PARAMETRES!$B$536:$B$586,MATCH(AH105,PARAMETRES!$J$536:$J$586,0)),"") | AJ105: =IFERROR(INDEX(PARAMETRES!$D$536:$D$586,MATCH(AH105,PARAMETRES!$J$536:$J$586,0)),"") | AK105: =IFERROR(INDEX(PARAMETRES!$F$536:$F$586,MATCH(AH105,PARAMETRES!$J$536:$J$586,0)),"") | AL105: =IFERROR(INDEX(PARAMETRES!$H$536:$H$586,MATCH(AH105,PARAMETRES!$J$536:$J$586,0)),"") | AV105: =IF(A105="",0,COUNTIFS(tbl_Beneficiaires_Activites[ID activite],A105)) -> 0 | BF105: =IF(BD105="",0,BD105)-IF(BE105="",0,BE105) -> 0 | BG105: =IF(OR(BD105="",BD105=0),0,BE105/BD105) -> 0 | BV105: =IF(OR(AO105="",AV105=""),"",AV105-AO105) | BW105: =IF(OR(BE105="",BD105=""),"",BE105-BD105) | CK105: =IF(A105="",0,COUNTIF(tbl_Activites_Documents[ID Activite],A105)) -> 0 | CL105: =IF(A105="",0,COUNTIF(tbl_Activites_Risques[ID Activite],A105)) -> 0 | CM105: =IF(A105="","",IF(BE105>BD105,"OUI","NON"))
A108: EQUIPE MOBILISEE PAR ACTIVITE
A109: ID Activite | B109: ID employe | C109: Nom | D109: Fonction | E109: Role dans l'activite | F109: Presence
A142: INDICATEURS DE L'ACTIVITE
A143: ID Activite | B143: Code indicateur | C143: Indicateur | D143: Unite | E143: Cible | F143: Realisation | G143: % atteinte
G144: =IF(OR(E144="",E144=0,F144=""),"",F144/E144)
G145: =IF(OR(E145="",E145=0,F145=""),"",F145/E145)
G146: =IF(OR(E146="",E146=0,F146=""),"",F146/E146)
G147: =IF(OR(E147="",E147=0,F147=""),"",F147/E147)
G148: =IF(OR(E148="",E148=0,F148=""),"",F148/E148)
G149: =IF(OR(E149="",E149=0,F149=""),"",F149/E149)
G150: =IF(OR(E150="",E150=0,F150=""),"",F150/E150)
G151: =IF(OR(E151="",E151=0,F151=""),"",F151/E151)
G152: =IF(OR(E152="",E152=0,F152=""),"",F152/E152)
G153: =IF(OR(E153="",E153=0,F153=""),"",F153/E153)
G154: =IF(OR(E154="",E154=0,F154=""),"",F154/E154)
G155: =IF(OR(E155="",E155=0,F155=""),"",F155/E155)
... G173: =IF(OR(E173="",E173=0,F173=""),"",F173/E173)
A176: RISQUES ET INCIDENTS DE L'ACTIVITE
A177: ID Activite | B177: ID risque | C177: Risque/incident | D177: Date | E177: Niveau | F177: Impact | G177: Mesure prise | H177: Responsable | I177: Statut
B178: =IF(A178="","","RSA"&TEXT(ROW()-177,"0000"))
B179: =IF(A179="","","RSA"&TEXT(ROW()-177,"0000"))
B180: =IF(A180="","","RSA"&TEXT(ROW()-177,"0000"))
B181: =IF(A181="","","RSA"&TEXT(ROW()-177,"0000"))
B182: =IF(A182="","","RSA"&TEXT(ROW()-177,"0000"))
B183: =IF(A183="","","RSA"&TEXT(ROW()-177,"0000"))
B184: =IF(A184="","","RSA"&TEXT(ROW()-177,"0000"))
B185: =IF(A185="","","RSA"&TEXT(ROW()-177,"0000"))
B186: =IF(A186="","","RSA"&TEXT(ROW()-177,"0000"))
B187: =IF(A187="","","RSA"&TEXT(ROW()-177,"0000"))
B188: =IF(A188="","","RSA"&TEXT(ROW()-177,"0000"))
B189: =IF(A189="","","RSA"&TEXT(ROW()-177,"0000"))
... B207: =IF(A207="","","RSA"&TEXT(ROW()-177,"0000"))
A210: DOCUMENTS JUSTIFICATIFS DE L'ACTIVITE
A211: ID Activite | B211: Type de document | C211: Reference | D211: Date | E211: Statut | F211: Emplacement / lien
A244: ANALYSE DES ACTIVITES PAR PROJET
A245: Projet | B245: Activites prevues | C245: Realisees | D245: Taux de realisation
A246: =IFERROR(INDEX(tbl_Projets[Titre complet du projet],1),"") -> Projet d'appui a l'insertion professionnelle des jeunes | B246: =IF(A246="","",COUNTIFS(tbl_Activites[ID Projet],INDEX(tbl_Projets[ID Projet],1))) -> 1 | C246: =IF(A246="","",COUNTIFS(tbl_Activites[ID Projet],INDEX(tbl_Projets[ID Projet],1),tbl_Activites[Statut de l''activite],"Realisee")) -> 0 | D246: =IF(OR(B246="",B246=0),"",C246/B246) -> 0
A247: =IFERROR(INDEX(tbl_Projets[Titre complet du projet],2),"") -> 0 | B247: =IF(A247="","",COUNTIFS(tbl_Activites[ID Projet],INDEX(tbl_Projets[ID Projet],2))) -> 49 | C247: =IF(A247="","",COUNTIFS(tbl_Activites[ID Projet],INDEX(tbl_Projets[ID Projet],2),tbl_Activites[Statut de l''activite],"Realisee")) -> 0 | D247: =IF(OR(B247="",B247=0),"",C247/B247) -> 0
A248: =IFERROR(INDEX(tbl_Projets[Titre complet du projet],3),"") -> 0 | B248: =IF(A248="","",COUNTIFS(tbl_Activites[ID Projet],INDEX(tbl_Projets[ID Projet],3))) -> 49 | C248: =IF(A248="","",COUNTIFS(tbl_Activites[ID Projet],INDEX(tbl_Projets[ID Projet],3),tbl_Activites[Statut de l''activite],"Realisee")) -> 0 | D248: =IF(OR(B248="",B248=0),"",C248/B248) -> 0
A249: =IFERROR(INDEX(tbl_Projets[Titre complet du projet],4),"") -> 0 | B249: =IF(A249="","",COUNTIFS(tbl_Activites[ID Projet],INDEX(tbl_Projets[ID Projet],4))) -> 49 | C249: =IF(A249="","",COUNTIFS(tbl_Activites[ID Projet],INDEX(tbl_Projets[ID Projet],4),tbl_Activites[Statut de l''activite],"Realisee")) -> 0 | D249: =IF(OR(B249="",B249=0),"",C249/B249) -> 0
A250: =IFERROR(INDEX(tbl_Projets[Titre complet du projet],5),"") -> 0 | B250: =IF(A250="","",COUNTIFS(tbl_Activites[ID Projet],INDEX(tbl_Projets[ID Projet],5))) -> 49 | C250: =IF(A250="","",COUNTIFS(tbl_Activites[ID Projet],INDEX(tbl_Projets[ID Projet],5),tbl_Activites[Statut de l''activite],"Realisee")) -> 0 | D250: =IF(OR(B250="",B250=0),"",C250/B250) -> 0
A251: =IFERROR(INDEX(tbl_Projets[Titre complet du projet],6),"") -> 0 | B251: =IF(A251="","",COUNTIFS(tbl_Activites[ID Projet],INDEX(tbl_Projets[ID Projet],6))) -> 49 | C251: =IF(A251="","",COUNTIFS(tbl_Activites[ID Projet],INDEX(tbl_Projets[ID Projet],6),tbl_Activites[Statut de l''activite],"Realisee")) -> 0 | D251: =IF(OR(B251="",B251=0),"",C251/B251) -> 0
A252: =IFERROR(INDEX(tbl_Projets[Titre complet du projet],7),"") -> 0 | B252: =IF(A252="","",COUNTIFS(tbl_Activites[ID Projet],INDEX(tbl_Projets[ID Projet],7))) -> 49 | C252: =IF(A252="","",COUNTIFS(tbl_Activites[ID Projet],INDEX(tbl_Projets[ID Projet],7),tbl_Activites[Statut de l''activite],"Realisee")) -> 0 | D252: =IF(OR(B252="",B252=0),"",C252/B252) -> 0
A253: =IFERROR(INDEX(tbl_Projets[Titre complet du projet],8),"") -> 0 | B253: =IF(A253="","",COUNTIFS(tbl_Activites[ID Projet],INDEX(tbl_Projets[ID Projet],8))) -> 49 | C253: =IF(A253="","",COUNTIFS(tbl_Activites[ID Projet],INDEX(tbl_Projets[ID Projet],8),tbl_Activites[Statut de l''activite],"Realisee")) -> 0 | D253: =IF(OR(B253="",B253=0),"",C253/B253) -> 0
...

Sheet PARTENAIRES
A1: O.N.G BK — GESTION DES PARTENAIRES | Q1: -> PROJETS | R1: -> ACTIVITES | S1: -> PARAMETRES
A2: Derniere mise a jour : voir cellule ci-dessous — Cette feuille alimente PROJETS, ACTIVITES, DONATEURS, RECETTES/FINANCEMENTS, DEPENSES, RESSOURCES HUMAINES, SUIVI-EVALUATION, RAPPORTS et TABLEAU DE BORD.
A4: LEGENDE : texte bleu = champ a completer manuellement | texte vert italique = donnee calculee automatiquement | ne pas modifier les colonnes calculees | cellule grisee = calcul automatique.
A6: SYNTHESE GENERALE DES PARTENAIRES (calcul automatique)
A7: Total partenaires | B7: Actifs | C7: Prospects | D7: Inactifs | E7: Techniques | F7: Financiers | G7: Institutionnels | H7: Conventions actives | I7: Conventions a renouveler (<=60j)
A8: =COUNTIF(C56:C115,"<>") -> 0 | B8: =COUNTIF(AN56:AN115,"Actif")+COUNTIF(AN56:AN115,"En partenariat") -> 0 | C8: =COUNTIF(AN56:AN115,"Prospect") -> 0 | D8: =COUNTIF(AN56:AN115,"Inactif") -> 0 | E8: =COUNTIF(F56:F115,"Partenaire technique") -> 0 | F8: =COUNTIF(F56:F115,"Partenaire financier") -> 0 | G8: =COUNTIF(F56:F115,"Partenaire institutionnel") -> 0 | H8: =COUNTIF(tbl_Partenaires_Conventions[Statut],"Active") -> 0 | I8: =COUNTIFS(tbl_Partenaires_Conventions[Statut],"Active",tbl_Partenaires_Conventions[Date fin],"<="&(TODAY()+60)) -> 0
A10: ANALYSES AUTOMATIQUES
A11: Statut du partenaire | B11: Nb partenaires | D11: Type de partenaire | E11: Nb partenaires | G11: Domaine de collaboration | H11: Nb partenaires
A12: Prospect | B12: =COUNTIF(tbl_Partenaires[Statut du partenaire],A12) -> 0 | D12: Partenaire financier | E12: =COUNTIF(tbl_Partenaires[Type de partenaire],D12) -> 0 | G12: Education | H12: =COUNTIF(tbl_Partenaires[Domaine de collaboration principal],G12) -> 0
A13: En discussion | B13: =COUNTIF(tbl_Partenaires[Statut du partenaire],A13) -> 0 | D13: Partenaire technique | E13: =COUNTIF(tbl_Partenaires[Type de partenaire],D13) -> 0 | G13: Formation professionnelle | H13: =COUNTIF(tbl_Partenaires[Domaine de collaboration principal],G13) -> 0
A14: Actif | B14: =COUNTIF(tbl_Partenaires[Statut du partenaire],A14) -> 0 | D14: Partenaire institutionnel | E14: =COUNTIF(tbl_Partenaires[Type de partenaire],D14) -> 0 | G14: Entrepreneuriat | H14: =COUNTIF(tbl_Partenaires[Domaine de collaboration principal],G14) -> 0
A15: En partenariat | B15: =COUNTIF(tbl_Partenaires[Statut du partenaire],A15) -> 0 | D15: Partenaire gouvernemental | E15: =COUNTIF(tbl_Partenaires[Type de partenaire],D15) -> 0 | G15: Culture | H15: =COUNTIF(tbl_Partenaires[Domaine de collaboration principal],G15) -> 0
A16: Suspendu | B16: =COUNTIF(tbl_Partenaires[Statut du partenaire],A16) -> 0 | D16: Collectivite locale | E16: =COUNTIF(tbl_Partenaires[Type de partenaire],D16) -> 0 | G16: Environnement | H16: =COUNTIF(tbl_Partenaires[Domaine de collaboration principal],G16) -> 0
A17: Inactif | B17: =COUNTIF(tbl_Partenaires[Statut du partenaire],A17) -> 0 | D17: Organisation internationale | E17: =COUNTIF(tbl_Partenaires[Type de partenaire],D17) -> 0 | G17: Sante | H17: =COUNTIF(tbl_Partenaires[Domaine de collaboration principal],G17) -> 0
A18: Termine | B18: =COUNTIF(tbl_Partenaires[Statut du partenaire],A18) -> 0 | D18: ONG nationale | E18: =COUNTIF(tbl_Partenaires[Type de partenaire],D18) -> 0 | G18: Genre | H18: =COUNTIF(tbl_Partenaires[Domaine de collaboration principal],G18) -> 0
A19: A renouveler | B19: =COUNTIF(tbl_Partenaires[Statut du partenaire],A19) -> 0 | D19: ONG internationale | E19: =COUNTIF(tbl_Partenaires[Type de partenaire],D19) -> 0 | G19: Tourisme | H19: =COUNTIF(tbl_Partenaires[Domaine de collaboration principal],G19) -> 0
A20: Autre | B20: =COUNTIF(tbl_Partenaires[Statut du partenaire],A20) -> 0 | D20: Association | E20: =COUNTIF(tbl_Partenaires[Type de partenaire],D20) -> 0 | G20: Sport | H20: =COUNTIF(tbl_Partenaires[Domaine de collaboration principal],G20) -> 0
D21: Entreprise privee | E21: =COUNTIF(tbl_Partenaires[Type de partenaire],D21) -> 0 | G21: Agriculture et developpement rural | H21: =COUNTIF(tbl_Partenaires[Domaine de collaboration principal],G21) -> 0
D22: Fondation | E22: =COUNTIF(tbl_Partenaires[Type de partenaire],D22) -> 0 | G22: Elevage | H22: =COUNTIF(tbl_Partenaires[Domaine de collaboration principal],G22) -> 0
D23: Universite | E23: =COUNTIF(tbl_Partenaires[Type de partenaire],D23) -> 0 | G23: Peche et aquaculture | H23: =COUNTIF(tbl_Partenaires[Domaine de collaboration principal],G23) -> 0
D24: Etablissement scolaire | E24: =COUNTIF(tbl_Partenaires[Type de partenaire],D24) -> 0 | G24: Securite alimentaire et nutrition | H24: =COUNTIF(tbl_Partenaires[Domaine de collaboration principal],G24) -> 0
D25: Centre de recherche | E25: =COUNTIF(tbl_Partenaires[Type de partenaire],D25) -> 0 | G25: Eau, hygiene et assainissement | H25: =COUNTIF(tbl_Partenaires[Domaine de collaboration principal],G25) -> 0
D26: Organisation communautaire | E26: =COUNTIF(tbl_Partenaires[Type de partenaire],D26) -> 0 | G26: Protection sociale | H26: =COUNTIF(tbl_Partenaires[Domaine de collaboration principal],G26) -> 0
D27: Organisation professionnelle | E27: =COUNTIF(tbl_Partenaires[Type de partenaire],D27) -> 0 | G27: Protection de l'enfance | H27: =COUNTIF(tbl_Partenaires[Domaine de collaboration principal],G27) -> 0
D28: Media | E28: =COUNTIF(tbl_Partenaires[Type de partenaire],D28) -> 0 | G28: Jeunesse | H28: =COUNTIF(tbl_Partenaires[Domaine de collaboration principal],G28) -> 0
D29: Institution financiere | E29: =COUNTIF(tbl_Partenaires[Type de partenaire],D29) -> 0 | G29: Autonomisation des femmes | H29: =COUNTIF(tbl_Partenaires[Domaine de collaboration principal],G29) -> 0
D30: Autre | E30: =COUNTIF(tbl_Partenaires[Type de partenaire],D30) -> 0 | G30: Developpement communautaire | H30: =COUNTIF(tbl_Partenaires[Domaine de collaboration principal],G30) -> 0
G31: Inclusion sociale | H31: =COUNTIF(tbl_Partenaires[Domaine de collaboration principal],G31) -> 0
G32: Handicap et inclusion des personnes vulnerables | H32: =COUNTIF(tbl_Partenaires[Domaine de collaboration principal],G32) -> 0
G33: Emploi et insertion professionnelle | H33: =COUNTIF(tbl_Partenaires[Domaine de collaboration principal],G33) -> 0
G34: Developpement economique local | H34: =COUNTIF(tbl_Partenaires[Domaine de collaboration principal],G34) -> 0
G35: Artisanat | H35: =COUNTIF(tbl_Partenaires[Domaine de collaboration principal],G35) -> 0
G36: Numerique et transformation digitale | H36: =COUNTIF(tbl_Partenaires[Domaine de collaboration principal],G36) -> 0
G37: Technologies et innovation | H37: =COUNTIF(tbl_Partenaires[Domaine de collaboration principal],G37) -> 0
G38: Recherche et developpement | H38: =COUNTIF(tbl_Partenaires[Domaine de collaboration principal],G38) -> 0
G39: Gouvernance et citoyennete | H39: =COUNTIF(tbl_Partenaires[Domaine de collaboration principal],G39) -> 0
G40: Droits humains | H40: =COUNTIF(tbl_Partenaires[Domaine de collaboration principal],G40) -> 0
G41: Paix, cohesion sociale et prevention des conflits | H41: =COUNTIF(tbl_Partenaires[Domaine de collaboration principal],G41) -> 0
G42: Action humanitaire et gestion des urgences | H42: =COUNTIF(tbl_Partenaires[Domaine de collaboration principal],G42) -> 0
... G51: Autre domaine | H51: =COUNTIF(tbl_Partenaires[Domaine de collaboration principal],G51) -> 0
A54: TABLEAU PRINCIPAL — LISTE DES PARTENAIRES
A55: ID Partenaire | B55: Code interne | C55: Nom officiel | D55: Nom court | E55: Sigle | F55: Type de partenaire | G55: Categorie de partenariat | H55: Forme juridique | I55: Pays d'origine | J55: Annee de creation | K55: Site web | L55: Description | M55: Localite (siege) | N55: Pays (siege) | O55: Departement (siege) | P55: Commune/District (siege) | Q55: Arrondissement (siege) | R55: Adresse / site exact (siege) | S55: Telephone principal | T55: Telephone secondaire | U55: Email general | V55: Adresse postale | W55: Nom contact principal | X55: Prenom contact principal | Y55: Fonction contact principal | Z55: Telephone contact principal | AA55: Email contact principal | AB55: WhatsApp contact principal | AC55: Date debut fonction contact | AD55: Statut contact principal | AE55: Domaine de collaboration principal | AF55: Domaine de collaboration secondaire | AG55: Localite d'intervention | AH55: Pays d'intervention | AI55: Departement d'intervention | AJ55: Commune d'intervention | AK55: Arrondissement d'intervention | AL55: Date debut collaboration | AM55: Date fin collaboration | AN55: Statut du partenaire | AO55: Niveau de partenariat | AP55: Contribution financiere prevue (FCFA) | AQ55: Contribution financiere recue (FCFA) | AR55: Ecart contribution (FCFA) | AS55: Type de contribution principale | AT55: Nb projets associes | AU55: Nb conventions | AV55: Conventions actives | AW55: Alerte convention a renouveler (<=60j) | AX55: Nb documents | AY55: Note globale evaluation (/5) | AZ55: Date derniere evaluation | BA55: Nb risques identifies | BB55: Risque eleve/critique present | BC55: Nb contacts secondaires | BD55: Nb opportunites en cours | BE55: Nb actions de prospection | BF55: ID responsable interne | BG55: Nom responsable interne | BH55: Fonction responsable interne | BI55: Telephone responsable interne | BJ55: Email responsable interne | BK55: Facebook | BL55: LinkedIn | BM55: X / Twitter | BN55: YouTube | BO55: Autre reseau | BP55: Newsletter (Oui/Non) | BQ55: Contact presse | BR55: Doublon potentiel | BS55: Observations
A56: =IF(C56="","","PART"&TEXT(ROW()-55,"00000")) | N56: =IFERROR(INDEX(PARAMETRES!$B$536:$B$586,MATCH(M56,PARAMETRES!$J$536:$J$586,0)),"") | O56: =IFERROR(INDEX(PARAMETRES!$D$536:$D$586,MATCH(M56,PARAMETRES!$J$536:$J$586,0)),"") | P56: =IFERROR(INDEX(PARAMETRES!$F$536:$F$586,MATCH(M56,PARAMETRES!$J$536:$J$586,0)),"") | Q56: =IFERROR(INDEX(PARAMETRES!$H$536:$H$586,MATCH(M56,PARAMETRES!$J$536:$J$586,0)),"") | AH56: =IFERROR(INDEX(PARAMETRES!$B$536:$B$586,MATCH(AG56,PARAMETRES!$J$536:$J$586,0)),"") | AI56: =IFERROR(INDEX(PARAMETRES!$D$536:$D$586,MATCH(AG56,PARAMETRES!$J$536:$J$586,0)),"") | AJ56: =IFERROR(INDEX(PARAMETRES!$F$536:$F$586,MATCH(AG56,PARAMETRES!$J$536:$J$586,0)),"") | AK56: =IFERROR(INDEX(PARAMETRES!$H$536:$H$586,MATCH(AG56,PARAMETRES!$J$536:$J$586,0)),"") | AR56: =IF(OR(AP56="",AQ56=""),"",AP56-AQ56) | AT56: =IF(A56="",0,COUNTIF(tbl_Partenaires_Projets[ID Partenaire],A56)) -> 0 | AU56: =IF(A56="",0,COUNTIF(tbl_Partenaires_Conventions[ID Partenaire],A56)) -> 0 | AV56: =IF(A56="",0,COUNTIFS(tbl_Partenaires_Conventions[ID Partenaire],A56,tbl_Partenaires_Conventions[Statut],"Active")) -> 0 | AW56: =IF(A56="","",IF(COUNTIFS(tbl_Partenaires_Conventions[ID Partenaire],A56,tbl_Partenaires_Conventions[Statut],"Active")=0,"NON",IF(_xlfn.MINIFS(tbl_Partenaires_Conventions[Date fin],tbl_Partenaires_Conventions[ID Partenaire],A56,tbl_Partenaires_Conventions[Statut],"Active")-TODAY()<=60,"OUI","NON"))) | AX56: =IF(A56="",0,COUNTIF(tbl_Partenaires_Documents[ID Partenaire],A56)) -> 0 | AY56: =IFERROR(AVERAGEIFS(tbl_Partenaires_Evaluations[Note globale],tbl_Partenaires_Evaluations[ID Partenaire],A56),"") | AZ56: =IFERROR(_xlfn.MAXIFS(tbl_Partenaires_Evaluations[Date evaluation],tbl_Partenaires_Evaluations[ID Partenaire],A56),"") | BA56: =IF(A56="",0,COUNTIF(tbl_Partenaires_Risques[ID Partenaire],A56)) -> 0 | BB56: =IF(A56="","",IF(COUNTIFS(tbl_Partenaires_Risques[ID Partenaire],A56,tbl_Partenaires_Risques[Niveau],"Eleve")+COUNTIFS(tbl_Partenaires_Risques[ID Partenaire],A56,tbl_Partenaires_Risques[Niveau],"Critique")>0,"OUI","NON")) | BC56: =IF(A56="",0,COUNTIF(tbl_Partenaires_Contacts[ID Partenaire],A56)) -> 0 | BD56: =IF(A56="",0,COUNTIFS(tbl_Partenaires_Opportunites[ID Partenaire],A56,tbl_Partenaires_Opportunites[Statut],"<>Cloturee")) -> 0 | BE56: =IF(A56="",0,COUNTIF(tbl_Partenaires_Prospection[ID Partenaire],A56)) -> 0 | BR56: =IF(C56="","",IF(OR(COUNTIF(C56:C115,C56)>1,AND(E56<>"",COUNTIF(E56:E115,E56)>1),AND(S56<>"",COUNTIF(S56:S115,S56)>1),AND(U56<>"",COUNTIF(U56:U115,U56)>1)),"OUI","NON"))
A57: =IF(C57="","","PART"&TEXT(ROW()-55,"00000")) | N57: =IFERROR(INDEX(PARAMETRES!$B$536:$B$586,MATCH(M57,PARAMETRES!$J$536:$J$586,0)),"") | O57: =IFERROR(INDEX(PARAMETRES!$D$536:$D$586,MATCH(M57,PARAMETRES!$J$536:$J$586,0)),"") | P57: =IFERROR(INDEX(PARAMETRES!$F$536:$F$586,MATCH(M57,PARAMETRES!$J$536:$J$586,0)),"") | Q57: =IFERROR(INDEX(PARAMETRES!$H$536:$H$586,MATCH(M57,PARAMETRES!$J$536:$J$586,0)),"") | AH57: =IFERROR(INDEX(PARAMETRES!$B$536:$B$586,MATCH(AG57,PARAMETRES!$J$536:$J$586,0)),"") | AI57: =IFERROR(INDEX(PARAMETRES!$D$536:$D$586,MATCH(AG57,PARAMETRES!$J$536:$J$586,0)),"") | AJ57: =IFERROR(INDEX(PARAMETRES!$F$536:$F$586,MATCH(AG57,PARAMETRES!$J$536:$J$586,0)),"") | AK57: =IFERROR(INDEX(PARAMETRES!$H$536:$H$586,MATCH(AG57,PARAMETRES!$J$536:$J$586,0)),"") | AR57: =IF(OR(AP57="",AQ57=""),"",AP57-AQ57) | AT57: =IF(A57="",0,COUNTIF(tbl_Partenaires_Projets[ID Partenaire],A57)) -> 0 | AU57: =IF(A57="",0,COUNTIF(tbl_Partenaires_Conventions[ID Partenaire],A57)) -> 0 | AV57: =IF(A57="",0,COUNTIFS(tbl_Partenaires_Conventions[ID Partenaire],A57,tbl_Partenaires_Conventions[Statut],"Active")) -> 0 | AW57: =IF(A57="","",IF(COUNTIFS(tbl_Partenaires_Conventions[ID Partenaire],A57,tbl_Partenaires_Conventions[Statut],"Active")=0,"NON",IF(_xlfn.MINIFS(tbl_Partenaires_Conventions[Date fin],tbl_Partenaires_Conventions[ID Partenaire],A57,tbl_Partenaires_Conventions[Statut],"Active")-TODAY()<=60,"OUI","NON"))) | AX57: =IF(A57="",0,COUNTIF(tbl_Partenaires_Documents[ID Partenaire],A57)) -> 0 | AY57: =IFERROR(AVERAGEIFS(tbl_Partenaires_Evaluations[Note globale],tbl_Partenaires_Evaluations[ID Partenaire],A57),"") | AZ57: =IFERROR(_xlfn.MAXIFS(tbl_Partenaires_Evaluations[Date evaluation],tbl_Partenaires_Evaluations[ID Partenaire],A57),"") | BA57: =IF(A57="",0,COUNTIF(tbl_Partenaires_Risques[ID Partenaire],A57)) -> 0 | BB57: =IF(A57="","",IF(COUNTIFS(tbl_Partenaires_Risques[ID Partenaire],A57,tbl_Partenaires_Risques[Niveau],"Eleve")+COUNTIFS(tbl_Partenaires_Risques[ID Partenaire],A57,tbl_Partenaires_Risques[Niveau],"Critique")>0,"OUI","NON")) | BC57: =IF(A57="",0,COUNTIF(tbl_Partenaires_Contacts[ID Partenaire],A57)) -> 0 | BD57: =IF(A57="",0,COUNTIFS(tbl_Partenaires_Opportunites[ID Partenaire],A57,tbl_Partenaires_Opportunites[Statut],"<>Cloturee")) -> 0 | BE57: =IF(A57="",0,COUNTIF(tbl_Partenaires_Prospection[ID Partenaire],A57)) -> 0 | BR57: =IF(C57="","",IF(OR(COUNTIF(C56:C115,C57)>1,AND(E57<>"",COUNTIF(E56:E115,E57)>1),AND(S57<>"",COUNTIF(S56:S115,S57)>1),AND(U57<>"",COUNTIF(U56:U115,U57)>1)),"OUI","NON"))
A58: =IF(C58="","","PART"&TEXT(ROW()-55,"00000")) | N58: =IFERROR(INDEX(PARAMETRES!$B$536:$B$586,MATCH(M58,PARAMETRES!$J$536:$J$586,0)),"") | O58: =IFERROR(INDEX(PARAMETRES!$D$536:$D$586,MATCH(M58,PARAMETRES!$J$536:$J$586,0)),"") | P58: =IFERROR(INDEX(PARAMETRES!$F$536:$F$586,MATCH(M58,PARAMETRES!$J$536:$J$586,0)),"") | Q58: =IFERROR(INDEX(PARAMETRES!$H$536:$H$586,MATCH(M58,PARAMETRES!$J$536:$J$586,0)),"") | AH58: =IFERROR(INDEX(PARAMETRES!$B$536:$B$586,MATCH(AG58,PARAMETRES!$J$536:$J$586,0)),"") | AI58: =IFERROR(INDEX(PARAMETRES!$D$536:$D$586,MATCH(AG58,PARAMETRES!$J$536:$J$586,0)),"") | AJ58: =IFERROR(INDEX(PARAMETRES!$F$536:$F$586,MATCH(AG58,PARAMETRES!$J$536:$J$586,0)),"") | AK58: =IFERROR(INDEX(PARAMETRES!$H$536:$H$586,MATCH(AG58,PARAMETRES!$J$536:$J$586,0)),"") | AR58: =IF(OR(AP58="",AQ58=""),"",AP58-AQ58) | AT58: =IF(A58="",0,COUNTIF(tbl_Partenaires_Projets[ID Partenaire],A58)) -> 0 | AU58: =IF(A58="",0,COUNTIF(tbl_Partenaires_Conventions[ID Partenaire],A58)) -> 0 | AV58: =IF(A58="",0,COUNTIFS(tbl_Partenaires_Conventions[ID Partenaire],A58,tbl_Partenaires_Conventions[Statut],"Active")) -> 0 | AW58: =IF(A58="","",IF(COUNTIFS(tbl_Partenaires_Conventions[ID Partenaire],A58,tbl_Partenaires_Conventions[Statut],"Active")=0,"NON",IF(_xlfn.MINIFS(tbl_Partenaires_Conventions[Date fin],tbl_Partenaires_Conventions[ID Partenaire],A58,tbl_Partenaires_Conventions[Statut],"Active")-TODAY()<=60,"OUI","NON"))) | AX58: =IF(A58="",0,COUNTIF(tbl_Partenaires_Documents[ID Partenaire],A58)) -> 0 | AY58: =IFERROR(AVERAGEIFS(tbl_Partenaires_Evaluations[Note globale],tbl_Partenaires_Evaluations[ID Partenaire],A58),"") | AZ58: =IFERROR(_xlfn.MAXIFS(tbl_Partenaires_Evaluations[Date evaluation],tbl_Partenaires_Evaluations[ID Partenaire],A58),"") | BA58: =IF(A58="",0,COUNTIF(tbl_Partenaires_Risques[ID Partenaire],A58)) -> 0 | BB58: =IF(A58="","",IF(COUNTIFS(tbl_Partenaires_Risques[ID Partenaire],A58,tbl_Partenaires_Risques[Niveau],"Eleve")+COUNTIFS(tbl_Partenaires_Risques[ID Partenaire],A58,tbl_Partenaires_Risques[Niveau],"Critique")>0,"OUI","NON")) | BC58: =IF(A58="",0,COUNTIF(tbl_Partenaires_Contacts[ID Partenaire],A58)) -> 0 | BD58: =IF(A58="",0,COUNTIFS(tbl_Partenaires_Opportunites[ID Partenaire],A58,tbl_Partenaires_Opportunites[Statut],"<>Cloturee")) -> 0 | BE58: =IF(A58="",0,COUNTIF(tbl_Partenaires_Prospection[ID Partenaire],A58)) -> 0 | BR58: =IF(C58="","",IF(OR(COUNTIF(C56:C115,C58)>1,AND(E58<>"",COUNTIF(E56:E115,E58)>1),AND(S58<>"",COUNTIF(S56:S115,S58)>1),AND(U58<>"",COUNTIF(U56:U115,U58)>1)),"OUI","NON"))
A59: =IF(C59="","","PART"&TEXT(ROW()-55,"00000")) | N59: =IFERROR(INDEX(PARAMETRES!$B$536:$B$586,MATCH(M59,PARAMETRES!$J$536:$J$586,0)),"") | O59: =IFERROR(INDEX(PARAMETRES!$D$536:$D$586,MATCH(M59,PARAMETRES!$J$536:$J$586,0)),"") | P59: =IFERROR(INDEX(PARAMETRES!$F$536:$F$586,MATCH(M59,PARAMETRES!$J$536:$J$586,0)),"") | Q59: =IFERROR(INDEX(PARAMETRES!$H$536:$H$586,MATCH(M59,PARAMETRES!$J$536:$J$586,0)),"") | AH59: =IFERROR(INDEX(PARAMETRES!$B$536:$B$586,MATCH(AG59,PARAMETRES!$J$536:$J$586,0)),"") | AI59: =IFERROR(INDEX(PARAMETRES!$D$536:$D$586,MATCH(AG59,PARAMETRES!$J$536:$J$586,0)),"") | AJ59: =IFERROR(INDEX(PARAMETRES!$F$536:$F$586,MATCH(AG59,PARAMETRES!$J$536:$J$586,0)),"") | AK59: =IFERROR(INDEX(PARAMETRES!$H$536:$H$586,MATCH(AG59,PARAMETRES!$J$536:$J$586,0)),"") | AR59: =IF(OR(AP59="",AQ59=""),"",AP59-AQ59) | AT59: =IF(A59="",0,COUNTIF(tbl_Partenaires_Projets[ID Partenaire],A59)) -> 0 | AU59: =IF(A59="",0,COUNTIF(tbl_Partenaires_Conventions[ID Partenaire],A59)) -> 0 | AV59: =IF(A59="",0,COUNTIFS(tbl_Partenaires_Conventions[ID Partenaire],A59,tbl_Partenaires_Conventions[Statut],"Active")) -> 0 | AW59: =IF(A59="","",IF(COUNTIFS(tbl_Partenaires_Conventions[ID Partenaire],A59,tbl_Partenaires_Conventions[Statut],"Active")=0,"NON",IF(_xlfn.MINIFS(tbl_Partenaires_Conventions[Date fin],tbl_Partenaires_Conventions[ID Partenaire],A59,tbl_Partenaires_Conventions[Statut],"Active")-TODAY()<=60,"OUI","NON"))) | AX59: =IF(A59="",0,COUNTIF(tbl_Partenaires_Documents[ID Partenaire],A59)) -> 0 | AY59: =IFERROR(AVERAGEIFS(tbl_Partenaires_Evaluations[Note globale],tbl_Partenaires_Evaluations[ID Partenaire],A59),"") | AZ59: =IFERROR(_xlfn.MAXIFS(tbl_Partenaires_Evaluations[Date evaluation],tbl_Partenaires_Evaluations[ID Partenaire],A59),"") | BA59: =IF(A59="",0,COUNTIF(tbl_Partenaires_Risques[ID Partenaire],A59)) -> 0 | BB59: =IF(A59="","",IF(COUNTIFS(tbl_Partenaires_Risques[ID Partenaire],A59,tbl_Partenaires_Risques[Niveau],"Eleve")+COUNTIFS(tbl_Partenaires_Risques[ID Partenaire],A59,tbl_Partenaires_Risques[Niveau],"Critique")>0,"OUI","NON")) | BC59: =IF(A59="",0,COUNTIF(tbl_Partenaires_Contacts[ID Partenaire],A59)) -> 0 | BD59: =IF(A59="",0,COUNTIFS(tbl_Partenaires_Opportunites[ID Partenaire],A59,tbl_Partenaires_Opportunites[Statut],"<>Cloturee")) -> 0 | BE59: =IF(A59="",0,COUNTIF(tbl_Partenaires_Prospection[ID Partenaire],A59)) -> 0 | BR59: =IF(C59="","",IF(OR(COUNTIF(C56:C115,C59)>1,AND(E59<>"",COUNTIF(E56:E115,E59)>1),AND(S59<>"",COUNTIF(S56:S115,S59)>1),AND(U59<>"",COUNTIF(U56:U115,U59)>1)),"OUI","NON"))
A60: =IF(C60="","","PART"&TEXT(ROW()-55,"00000")) | N60: =IFERROR(INDEX(PARAMETRES!$B$536:$B$586,MATCH(M60,PARAMETRES!$J$536:$J$586,0)),"") | O60: =IFERROR(INDEX(PARAMETRES!$D$536:$D$586,MATCH(M60,PARAMETRES!$J$536:$J$586,0)),"") | P60: =IFERROR(INDEX(PARAMETRES!$F$536:$F$586,MATCH(M60,PARAMETRES!$J$536:$J$586,0)),"") | Q60: =IFERROR(INDEX(PARAMETRES!$H$536:$H$586,MATCH(M60,PARAMETRES!$J$536:$J$586,0)),"") | AH60: =IFERROR(INDEX(PARAMETRES!$B$536:$B$586,MATCH(AG60,PARAMETRES!$J$536:$J$586,0)),"") | AI60: =IFERROR(INDEX(PARAMETRES!$D$536:$D$586,MATCH(AG60,PARAMETRES!$J$536:$J$586,0)),"") | AJ60: =IFERROR(INDEX(PARAMETRES!$F$536:$F$586,MATCH(AG60,PARAMETRES!$J$536:$J$586,0)),"") | AK60: =IFERROR(INDEX(PARAMETRES!$H$536:$H$586,MATCH(AG60,PARAMETRES!$J$536:$J$586,0)),"") | AR60: =IF(OR(AP60="",AQ60=""),"",AP60-AQ60) | AT60: =IF(A60="",0,COUNTIF(tbl_Partenaires_Projets[ID Partenaire],A60)) -> 0 | AU60: =IF(A60="",0,COUNTIF(tbl_Partenaires_Conventions[ID Partenaire],A60)) -> 0 | AV60: =IF(A60="",0,COUNTIFS(tbl_Partenaires_Conventions[ID Partenaire],A60,tbl_Partenaires_Conventions[Statut],"Active")) -> 0 | AW60: =IF(A60="","",IF(COUNTIFS(tbl_Partenaires_Conventions[ID Partenaire],A60,tbl_Partenaires_Conventions[Statut],"Active")=0,"NON",IF(_xlfn.MINIFS(tbl_Partenaires_Conventions[Date fin],tbl_Partenaires_Conventions[ID Partenaire],A60,tbl_Partenaires_Conventions[Statut],"Active")-TODAY()<=60,"OUI","NON"))) | AX60: =IF(A60="",0,COUNTIF(tbl_Partenaires_Documents[ID Partenaire],A60)) -> 0 | AY60: =IFERROR(AVERAGEIFS(tbl_Partenaires_Evaluations[Note globale],tbl_Partenaires_Evaluations[ID Partenaire],A60),"") | AZ60: =IFERROR(_xlfn.MAXIFS(tbl_Partenaires_Evaluations[Date evaluation],tbl_Partenaires_Evaluations[ID Partenaire],A60),"") | BA60: =IF(A60="",0,COUNTIF(tbl_Partenaires_Risques[ID Partenaire],A60)) -> 0 | BB60: =IF(A60="","",IF(COUNTIFS(tbl_Partenaires_Risques[ID Partenaire],A60,tbl_Partenaires_Risques[Niveau],"Eleve")+COUNTIFS(tbl_Partenaires_Risques[ID Partenaire],A60,tbl_Partenaires_Risques[Niveau],"Critique")>0,"OUI","NON")) | BC60: =IF(A60="",0,COUNTIF(tbl_Partenaires_Contacts[ID Partenaire],A60)) -> 0 | BD60: =IF(A60="",0,COUNTIFS(tbl_Partenaires_Opportunites[ID Partenaire],A60,tbl_Partenaires_Opportunites[Statut],"<>Cloturee")) -> 0 | BE60: =IF(A60="",0,COUNTIF(tbl_Partenaires_Prospection[ID Partenaire],A60)) -> 0 | BR60: =IF(C60="","",IF(OR(COUNTIF(C56:C115,C60)>1,AND(E60<>"",COUNTIF(E56:E115,E60)>1),AND(S60<>"",COUNTIF(S56:S115,S60)>1),AND(U60<>"",COUNTIF(U56:U115,U60)>1)),"OUI","NON"))
A61: =IF(C61="","","PART"&TEXT(ROW()-55,"00000")) | N61: =IFERROR(INDEX(PARAMETRES!$B$536:$B$586,MATCH(M61,PARAMETRES!$J$536:$J$586,0)),"") | O61: =IFERROR(INDEX(PARAMETRES!$D$536:$D$586,MATCH(M61,PARAMETRES!$J$536:$J$586,0)),"") | P61: =IFERROR(INDEX(PARAMETRES!$F$536:$F$586,MATCH(M61,PARAMETRES!$J$536:$J$586,0)),"") | Q61: =IFERROR(INDEX(PARAMETRES!$H$536:$H$586,MATCH(M61,PARAMETRES!$J$536:$J$586,0)),"") | AH61: =IFERROR(INDEX(PARAMETRES!$B$536:$B$586,MATCH(AG61,PARAMETRES!$J$536:$J$586,0)),"") | AI61: =IFERROR(INDEX(PARAMETRES!$D$536:$D$586,MATCH(AG61,PARAMETRES!$J$536:$J$586,0)),"") | AJ61: =IFERROR(INDEX(PARAMETRES!$F$536:$F$586,MATCH(AG61,PARAMETRES!$J$536:$J$586,0)),"") | AK61: =IFERROR(INDEX(PARAMETRES!$H$536:$H$586,MATCH(AG61,PARAMETRES!$J$536:$J$586,0)),"") | AR61: =IF(OR(AP61="",AQ61=""),"",AP61-AQ61) | AT61: =IF(A61="",0,COUNTIF(tbl_Partenaires_Projets[ID Partenaire],A61)) -> 0 | AU61: =IF(A61="",0,COUNTIF(tbl_Partenaires_Conventions[ID Partenaire],A61)) -> 0 | AV61: =IF(A61="",0,COUNTIFS(tbl_Partenaires_Conventions[ID Partenaire],A61,tbl_Partenaires_Conventions[Statut],"Active")) -> 0 | AW61: =IF(A61="","",IF(COUNTIFS(tbl_Partenaires_Conventions[ID Partenaire],A61,tbl_Partenaires_Conventions[Statut],"Active")=0,"NON",IF(_xlfn.MINIFS(tbl_Partenaires_Conventions[Date fin],tbl_Partenaires_Conventions[ID Partenaire],A61,tbl_Partenaires_Conventions[Statut],"Active")-TODAY()<=60,"OUI","NON"))) | AX61: =IF(A61="",0,COUNTIF(tbl_Partenaires_Documents[ID Partenaire],A61)) -> 0 | AY61: =IFERROR(AVERAGEIFS(tbl_Partenaires_Evaluations[Note globale],tbl_Partenaires_Evaluations[ID Partenaire],A61),"") | AZ61: =IFERROR(_xlfn.MAXIFS(tbl_Partenaires_Evaluations[Date evaluation],tbl_Partenaires_Evaluations[ID Partenaire],A61),"") | BA61: =IF(A61="",0,COUNTIF(tbl_Partenaires_Risques[ID Partenaire],A61)) -> 0 | BB61: =IF(A61="","",IF(COUNTIFS(tbl_Partenaires_Risques[ID Partenaire],A61,tbl_Partenaires_Risques[Niveau],"Eleve")+COUNTIFS(tbl_Partenaires_Risques[ID Partenaire],A61,tbl_Partenaires_Risques[Niveau],"Critique")>0,"OUI","NON")) | BC61: =IF(A61="",0,COUNTIF(tbl_Partenaires_Contacts[ID Partenaire],A61)) -> 0 | BD61: =IF(A61="",0,COUNTIFS(tbl_Partenaires_Opportunites[ID Partenaire],A61,tbl_Partenaires_Opportunites[Statut],"<>Cloturee")) -> 0 | BE61: =IF(A61="",0,COUNTIF(tbl_Partenaires_Prospection[ID Partenaire],A61)) -> 0 | BR61: =IF(C61="","",IF(OR(COUNTIF(C56:C115,C61)>1,AND(E61<>"",COUNTIF(E56:E115,E61)>1),AND(S61<>"",COUNTIF(S56:S115,S61)>1),AND(U61<>"",COUNTIF(U56:U115,U61)>1)),"OUI","NON"))
A62: =IF(C62="","","PART"&TEXT(ROW()-55,"00000")) | N62: =IFERROR(INDEX(PARAMETRES!$B$536:$B$586,MATCH(M62,PARAMETRES!$J$536:$J$586,0)),"") | O62: =IFERROR(INDEX(PARAMETRES!$D$536:$D$586,MATCH(M62,PARAMETRES!$J$536:$J$586,0)),"") | P62: =IFERROR(INDEX(PARAMETRES!$F$536:$F$586,MATCH(M62,PARAMETRES!$J$536:$J$586,0)),"") | Q62: =IFERROR(INDEX(PARAMETRES!$H$536:$H$586,MATCH(M62,PARAMETRES!$J$536:$J$586,0)),"") | AH62: =IFERROR(INDEX(PARAMETRES!$B$536:$B$586,MATCH(AG62,PARAMETRES!$J$536:$J$586,0)),"") | AI62: =IFERROR(INDEX(PARAMETRES!$D$536:$D$586,MATCH(AG62,PARAMETRES!$J$536:$J$586,0)),"") | AJ62: =IFERROR(INDEX(PARAMETRES!$F$536:$F$586,MATCH(AG62,PARAMETRES!$J$536:$J$586,0)),"") | AK62: =IFERROR(INDEX(PARAMETRES!$H$536:$H$586,MATCH(AG62,PARAMETRES!$J$536:$J$586,0)),"") | AR62: =IF(OR(AP62="",AQ62=""),"",AP62-AQ62) | AT62: =IF(A62="",0,COUNTIF(tbl_Partenaires_Projets[ID Partenaire],A62)) -> 0 | AU62: =IF(A62="",0,COUNTIF(tbl_Partenaires_Conventions[ID Partenaire],A62)) -> 0 | AV62: =IF(A62="",0,COUNTIFS(tbl_Partenaires_Conventions[ID Partenaire],A62,tbl_Partenaires_Conventions[Statut],"Active")) -> 0 | AW62: =IF(A62="","",IF(COUNTIFS(tbl_Partenaires_Conventions[ID Partenaire],A62,tbl_Partenaires_Conventions[Statut],"Active")=0,"NON",IF(_xlfn.MINIFS(tbl_Partenaires_Conventions[Date fin],tbl_Partenaires_Conventions[ID Partenaire],A62,tbl_Partenaires_Conventions[Statut],"Active")-TODAY()<=60,"OUI","NON"))) | AX62: =IF(A62="",0,COUNTIF(tbl_Partenaires_Documents[ID Partenaire],A62)) -> 0 | AY62: =IFERROR(AVERAGEIFS(tbl_Partenaires_Evaluations[Note globale],tbl_Partenaires_Evaluations[ID Partenaire],A62),"") | AZ62: =IFERROR(_xlfn.MAXIFS(tbl_Partenaires_Evaluations[Date evaluation],tbl_Partenaires_Evaluations[ID Partenaire],A62),"") | BA62: =IF(A62="",0,COUNTIF(tbl_Partenaires_Risques[ID Partenaire],A62)) -> 0 | BB62: =IF(A62="","",IF(COUNTIFS(tbl_Partenaires_Risques[ID Partenaire],A62,tbl_Partenaires_Risques[Niveau],"Eleve")+COUNTIFS(tbl_Partenaires_Risques[ID Partenaire],A62,tbl_Partenaires_Risques[Niveau],"Critique")>0,"OUI","NON")) | BC62: =IF(A62="",0,COUNTIF(tbl_Partenaires_Contacts[ID Partenaire],A62)) -> 0 | BD62: =IF(A62="",0,COUNTIFS(tbl_Partenaires_Opportunites[ID Partenaire],A62,tbl_Partenaires_Opportunites[Statut],"<>Cloturee")) -> 0 | BE62: =IF(A62="",0,COUNTIF(tbl_Partenaires_Prospection[ID Partenaire],A62)) -> 0 | BR62: =IF(C62="","",IF(OR(COUNTIF(C56:C115,C62)>1,AND(E62<>"",COUNTIF(E56:E115,E62)>1),AND(S62<>"",COUNTIF(S56:S115,S62)>1),AND(U62<>"",COUNTIF(U56:U115,U62)>1)),"OUI","NON"))
A63: =IF(C63="","","PART"&TEXT(ROW()-55,"00000")) | N63: =IFERROR(INDEX(PARAMETRES!$B$536:$B$586,MATCH(M63,PARAMETRES!$J$536:$J$586,0)),"") | O63: =IFERROR(INDEX(PARAMETRES!$D$536:$D$586,MATCH(M63,PARAMETRES!$J$536:$J$586,0)),"") | P63: =IFERROR(INDEX(PARAMETRES!$F$536:$F$586,MATCH(M63,PARAMETRES!$J$536:$J$586,0)),"") | Q63: =IFERROR(INDEX(PARAMETRES!$H$536:$H$586,MATCH(M63,PARAMETRES!$J$536:$J$586,0)),"") | AH63: =IFERROR(INDEX(PARAMETRES!$B$536:$B$586,MATCH(AG63,PARAMETRES!$J$536:$J$586,0)),"") | AI63: =IFERROR(INDEX(PARAMETRES!$D$536:$D$586,MATCH(AG63,PARAMETRES!$J$536:$J$586,0)),"") | AJ63: =IFERROR(INDEX(PARAMETRES!$F$536:$F$586,MATCH(AG63,PARAMETRES!$J$536:$J$586,0)),"") | AK63: =IFERROR(INDEX(PARAMETRES!$H$536:$H$586,MATCH(AG63,PARAMETRES!$J$536:$J$586,0)),"") | AR63: =IF(OR(AP63="",AQ63=""),"",AP63-AQ63) | AT63: =IF(A63="",0,COUNTIF(tbl_Partenaires_Projets[ID Partenaire],A63)) -> 0 | AU63: =IF(A63="",0,COUNTIF(tbl_Partenaires_Conventions[ID Partenaire],A63)) -> 0 | AV63: =IF(A63="",0,COUNTIFS(tbl_Partenaires_Conventions[ID Partenaire],A63,tbl_Partenaires_Conventions[Statut],"Active")) -> 0 | AW63: =IF(A63="","",IF(COUNTIFS(tbl_Partenaires_Conventions[ID Partenaire],A63,tbl_Partenaires_Conventions[Statut],"Active")=0,"NON",IF(_xlfn.MINIFS(tbl_Partenaires_Conventions[Date fin],tbl_Partenaires_Conventions[ID Partenaire],A63,tbl_Partenaires_Conventions[Statut],"Active")-TODAY()<=60,"OUI","NON"))) | AX63: =IF(A63="",0,COUNTIF(tbl_Partenaires_Documents[ID Partenaire],A63)) -> 0 | AY63: =IFERROR(AVERAGEIFS(tbl_Partenaires_Evaluations[Note globale],tbl_Partenaires_Evaluations[ID Partenaire],A63),"") | AZ63: =IFERROR(_xlfn.MAXIFS(tbl_Partenaires_Evaluations[Date evaluation],tbl_Partenaires_Evaluations[ID Partenaire],A63),"") | BA63: =IF(A63="",0,COUNTIF(tbl_Partenaires_Risques[ID Partenaire],A63)) -> 0 | BB63: =IF(A63="","",IF(COUNTIFS(tbl_Partenaires_Risques[ID Partenaire],A63,tbl_Partenaires_Risques[Niveau],"Eleve")+COUNTIFS(tbl_Partenaires_Risques[ID Partenaire],A63,tbl_Partenaires_Risques[Niveau],"Critique")>0,"OUI","NON")) | BC63: =IF(A63="",0,COUNTIF(tbl_Partenaires_Contacts[ID Partenaire],A63)) -> 0 | BD63: =IF(A63="",0,COUNTIFS(tbl_Partenaires_Opportunites[ID Partenaire],A63,tbl_Partenaires_Opportunites[Statut],"<>Cloturee")) -> 0 | BE63: =IF(A63="",0,COUNTIF(tbl_Partenaires_Prospection[ID Partenaire],A63)) -> 0 | BR63: =IF(C63="","",IF(OR(COUNTIF(C56:C115,C63)>1,AND(E63<>"",COUNTIF(E56:E115,E63)>1),AND(S63<>"",COUNTIF(S56:S115,S63)>1),AND(U63<>"",COUNTIF(U56:U115,U63)>1)),"OUI","NON"))
A64: =IF(C64="","","PART"&TEXT(ROW()-55,"00000")) | N64: =IFERROR(INDEX(PARAMETRES!$B$536:$B$586,MATCH(M64,PARAMETRES!$J$536:$J$586,0)),"") | O64: =IFERROR(INDEX(PARAMETRES!$D$536:$D$586,MATCH(M64,PARAMETRES!$J$536:$J$586,0)),"") | P64: =IFERROR(INDEX(PARAMETRES!$F$536:$F$586,MATCH(M64,PARAMETRES!$J$536:$J$586,0)),"") | Q64: =IFERROR(INDEX(PARAMETRES!$H$536:$H$586,MATCH(M64,PARAMETRES!$J$536:$J$586,0)),"") | AH64: =IFERROR(INDEX(PARAMETRES!$B$536:$B$586,MATCH(AG64,PARAMETRES!$J$536:$J$586,0)),"") | AI64: =IFERROR(INDEX(PARAMETRES!$D$536:$D$586,MATCH(AG64,PARAMETRES!$J$536:$J$586,0)),"") | AJ64: =IFERROR(INDEX(PARAMETRES!$F$536:$F$586,MATCH(AG64,PARAMETRES!$J$536:$J$586,0)),"") | AK64: =IFERROR(INDEX(PARAMETRES!$H$536:$H$586,MATCH(AG64,PARAMETRES!$J$536:$J$586,0)),"") | AR64: =IF(OR(AP64="",AQ64=""),"",AP64-AQ64) | AT64: =IF(A64="",0,COUNTIF(tbl_Partenaires_Projets[ID Partenaire],A64)) -> 0 | AU64: =IF(A64="",0,COUNTIF(tbl_Partenaires_Conventions[ID Partenaire],A64)) -> 0 | AV64: =IF(A64="",0,COUNTIFS(tbl_Partenaires_Conventions[ID Partenaire],A64,tbl_Partenaires_Conventions[Statut],"Active")) -> 0 | AW64: =IF(A64="","",IF(COUNTIFS(tbl_Partenaires_Conventions[ID Partenaire],A64,tbl_Partenaires_Conventions[Statut],"Active")=0,"NON",IF(_xlfn.MINIFS(tbl_Partenaires_Conventions[Date fin],tbl_Partenaires_Conventions[ID Partenaire],A64,tbl_Partenaires_Conventions[Statut],"Active")-TODAY()<=60,"OUI","NON"))) | AX64: =IF(A64="",0,COUNTIF(tbl_Partenaires_Documents[ID Partenaire],A64)) -> 0 | AY64: =IFERROR(AVERAGEIFS(tbl_Partenaires_Evaluations[Note globale],tbl_Partenaires_Evaluations[ID Partenaire],A64),"") | AZ64: =IFERROR(_xlfn.MAXIFS(tbl_Partenaires_Evaluations[Date evaluation],tbl_Partenaires_Evaluations[ID Partenaire],A64),"") | BA64: =IF(A64="",0,COUNTIF(tbl_Partenaires_Risques[ID Partenaire],A64)) -> 0 | BB64: =IF(A64="","",IF(COUNTIFS(tbl_Partenaires_Risques[ID Partenaire],A64,tbl_Partenaires_Risques[Niveau],"Eleve")+COUNTIFS(tbl_Partenaires_Risques[ID Partenaire],A64,tbl_Partenaires_Risques[Niveau],"Critique")>0,"OUI","NON")) | BC64: =IF(A64="",0,COUNTIF(tbl_Partenaires_Contacts[ID Partenaire],A64)) -> 0 | BD64: =IF(A64="",0,COUNTIFS(tbl_Partenaires_Opportunites[ID Partenaire],A64,tbl_Partenaires_Opportunites[Statut],"<>Cloturee")) -> 0 | BE64: =IF(A64="",0,COUNTIF(tbl_Partenaires_Prospection[ID Partenaire],A64)) -> 0 | BR64: =IF(C64="","",IF(OR(COUNTIF(C56:C115,C64)>1,AND(E64<>"",COUNTIF(E56:E115,E64)>1),AND(S64<>"",COUNTIF(S56:S115,S64)>1),AND(U64<>"",COUNTIF(U56:U115,U64)>1)),"OUI","NON"))
A65: =IF(C65="","","PART"&TEXT(ROW()-55,"00000")) | N65: =IFERROR(INDEX(PARAMETRES!$B$536:$B$586,MATCH(M65,PARAMETRES!$J$536:$J$586,0)),"") | O65: =IFERROR(INDEX(PARAMETRES!$D$536:$D$586,MATCH(M65,PARAMETRES!$J$536:$J$586,0)),"") | P65: =IFERROR(INDEX(PARAMETRES!$F$536:$F$586,MATCH(M65,PARAMETRES!$J$536:$J$586,0)),"") | Q65: =IFERROR(INDEX(PARAMETRES!$H$536:$H$586,MATCH(M65,PARAMETRES!$J$536:$J$586,0)),"") | AH65: =IFERROR(INDEX(PARAMETRES!$B$536:$B$586,MATCH(AG65,PARAMETRES!$J$536:$J$586,0)),"") | AI65: =IFERROR(INDEX(PARAMETRES!$D$536:$D$586,MATCH(AG65,PARAMETRES!$J$536:$J$586,0)),"") | AJ65: =IFERROR(INDEX(PARAMETRES!$F$536:$F$586,MATCH(AG65,PARAMETRES!$J$536:$J$586,0)),"") | AK65: =IFERROR(INDEX(PARAMETRES!$H$536:$H$586,MATCH(AG65,PARAMETRES!$J$536:$J$586,0)),"") | AR65: =IF(OR(AP65="",AQ65=""),"",AP65-AQ65) | AT65: =IF(A65="",0,COUNTIF(tbl_Partenaires_Projets[ID Partenaire],A65)) -> 0 | AU65: =IF(A65="",0,COUNTIF(tbl_Partenaires_Conventions[ID Partenaire],A65)) -> 0 | AV65: =IF(A65="",0,COUNTIFS(tbl_Partenaires_Conventions[ID Partenaire],A65,tbl_Partenaires_Conventions[Statut],"Active")) -> 0 | AW65: =IF(A65="","",IF(COUNTIFS(tbl_Partenaires_Conventions[ID Partenaire],A65,tbl_Partenaires_Conventions[Statut],"Active")=0,"NON",IF(_xlfn.MINIFS(tbl_Partenaires_Conventions[Date fin],tbl_Partenaires_Conventions[ID Partenaire],A65,tbl_Partenaires_Conventions[Statut],"Active")-TODAY()<=60,"OUI","NON"))) | AX65: =IF(A65="",0,COUNTIF(tbl_Partenaires_Documents[ID Partenaire],A65)) -> 0 | AY65: =IFERROR(AVERAGEIFS(tbl_Partenaires_Evaluations[Note globale],tbl_Partenaires_Evaluations[ID Partenaire],A65),"") | AZ65: =IFERROR(_xlfn.MAXIFS(tbl_Partenaires_Evaluations[Date evaluation],tbl_Partenaires_Evaluations[ID Partenaire],A65),"") | BA65: =IF(A65="",0,COUNTIF(tbl_Partenaires_Risques[ID Partenaire],A65)) -> 0 | BB65: =IF(A65="","",IF(COUNTIFS(tbl_Partenaires_Risques[ID Partenaire],A65,tbl_Partenaires_Risques[Niveau],"Eleve")+COUNTIFS(tbl_Partenaires_Risques[ID Partenaire],A65,tbl_Partenaires_Risques[Niveau],"Critique")>0,"OUI","NON")) | BC65: =IF(A65="",0,COUNTIF(tbl_Partenaires_Contacts[ID Partenaire],A65)) -> 0 | BD65: =IF(A65="",0,COUNTIFS(tbl_Partenaires_Opportunites[ID Partenaire],A65,tbl_Partenaires_Opportunites[Statut],"<>Cloturee")) -> 0 | BE65: =IF(A65="",0,COUNTIF(tbl_Partenaires_Prospection[ID Partenaire],A65)) -> 0 | BR65: =IF(C65="","",IF(OR(COUNTIF(C56:C115,C65)>1,AND(E65<>"",COUNTIF(E56:E115,E65)>1),AND(S65<>"",COUNTIF(S56:S115,S65)>1),AND(U65<>"",COUNTIF(U56:U115,U65)>1)),"OUI","NON"))
A66: =IF(C66="","","PART"&TEXT(ROW()-55,"00000")) | N66: =IFERROR(INDEX(PARAMETRES!$B$536:$B$586,MATCH(M66,PARAMETRES!$J$536:$J$586,0)),"") | O66: =IFERROR(INDEX(PARAMETRES!$D$536:$D$586,MATCH(M66,PARAMETRES!$J$536:$J$586,0)),"") | P66: =IFERROR(INDEX(PARAMETRES!$F$536:$F$586,MATCH(M66,PARAMETRES!$J$536:$J$586,0)),"") | Q66: =IFERROR(INDEX(PARAMETRES!$H$536:$H$586,MATCH(M66,PARAMETRES!$J$536:$J$586,0)),"") | AH66: =IFERROR(INDEX(PARAMETRES!$B$536:$B$586,MATCH(AG66,PARAMETRES!$J$536:$J$586,0)),"") | AI66: =IFERROR(INDEX(PARAMETRES!$D$536:$D$586,MATCH(AG66,PARAMETRES!$J$536:$J$586,0)),"") | AJ66: =IFERROR(INDEX(PARAMETRES!$F$536:$F$586,MATCH(AG66,PARAMETRES!$J$536:$J$586,0)),"") | AK66: =IFERROR(INDEX(PARAMETRES!$H$536:$H$586,MATCH(AG66,PARAMETRES!$J$536:$J$586,0)),"") | AR66: =IF(OR(AP66="",AQ66=""),"",AP66-AQ66) | AT66: =IF(A66="",0,COUNTIF(tbl_Partenaires_Projets[ID Partenaire],A66)) -> 0 | AU66: =IF(A66="",0,COUNTIF(tbl_Partenaires_Conventions[ID Partenaire],A66)) -> 0 | AV66: =IF(A66="",0,COUNTIFS(tbl_Partenaires_Conventions[ID Partenaire],A66,tbl_Partenaires_Conventions[Statut],"Active")) -> 0 | AW66: =IF(A66="","",IF(COUNTIFS(tbl_Partenaires_Conventions[ID Partenaire],A66,tbl_Partenaires_Conventions[Statut],"Active")=0,"NON",IF(_xlfn.MINIFS(tbl_Partenaires_Conventions[Date fin],tbl_Partenaires_Conventions[ID Partenaire],A66,tbl_Partenaires_Conventions[Statut],"Active")-TODAY()<=60,"OUI","NON"))) | AX66: =IF(A66="",0,COUNTIF(tbl_Partenaires_Documents[ID Partenaire],A66)) -> 0 | AY66: =IFERROR(AVERAGEIFS(tbl_Partenaires_Evaluations[Note globale],tbl_Partenaires_Evaluations[ID Partenaire],A66),"") | AZ66: =IFERROR(_xlfn.MAXIFS(tbl_Partenaires_Evaluations[Date evaluation],tbl_Partenaires_Evaluations[ID Partenaire],A66),"") | BA66: =IF(A66="",0,COUNTIF(tbl_Partenaires_Risques[ID Partenaire],A66)) -> 0 | BB66: =IF(A66="","",IF(COUNTIFS(tbl_Partenaires_Risques[ID Partenaire],A66,tbl_Partenaires_Risques[Niveau],"Eleve")+COUNTIFS(tbl_Partenaires_Risques[ID Partenaire],A66,tbl_Partenaires_Risques[Niveau],"Critique")>0,"OUI","NON")) | BC66: =IF(A66="",0,COUNTIF(tbl_Partenaires_Contacts[ID Partenaire],A66)) -> 0 | BD66: =IF(A66="",0,COUNTIFS(tbl_Partenaires_Opportunites[ID Partenaire],A66,tbl_Partenaires_Opportunites[Statut],"<>Cloturee")) -> 0 | BE66: =IF(A66="",0,COUNTIF(tbl_Partenaires_Prospection[ID Partenaire],A66)) -> 0 | BR66: =IF(C66="","",IF(OR(COUNTIF(C56:C115,C66)>1,AND(E66<>"",COUNTIF(E56:E115,E66)>1),AND(S66<>"",COUNTIF(S56:S115,S66)>1),AND(U66<>"",COUNTIF(U56:U115,U66)>1)),"OUI","NON"))
A67: =IF(C67="","","PART"&TEXT(ROW()-55,"00000")) | N67: =IFERROR(INDEX(PARAMETRES!$B$536:$B$586,MATCH(M67,PARAMETRES!$J$536:$J$586,0)),"") | O67: =IFERROR(INDEX(PARAMETRES!$D$536:$D$586,MATCH(M67,PARAMETRES!$J$536:$J$586,0)),"") | P67: =IFERROR(INDEX(PARAMETRES!$F$536:$F$586,MATCH(M67,PARAMETRES!$J$536:$J$586,0)),"") | Q67: =IFERROR(INDEX(PARAMETRES!$H$536:$H$586,MATCH(M67,PARAMETRES!$J$536:$J$586,0)),"") | AH67: =IFERROR(INDEX(PARAMETRES!$B$536:$B$586,MATCH(AG67,PARAMETRES!$J$536:$J$586,0)),"") | AI67: =IFERROR(INDEX(PARAMETRES!$D$536:$D$586,MATCH(AG67,PARAMETRES!$J$536:$J$586,0)),"") | AJ67: =IFERROR(INDEX(PARAMETRES!$F$536:$F$586,MATCH(AG67,PARAMETRES!$J$536:$J$586,0)),"") | AK67: =IFERROR(INDEX(PARAMETRES!$H$536:$H$586,MATCH(AG67,PARAMETRES!$J$536:$J$586,0)),"") | AR67: =IF(OR(AP67="",AQ67=""),"",AP67-AQ67) | AT67: =IF(A67="",0,COUNTIF(tbl_Partenaires_Projets[ID Partenaire],A67)) -> 0 | AU67: =IF(A67="",0,COUNTIF(tbl_Partenaires_Conventions[ID Partenaire],A67)) -> 0 | AV67: =IF(A67="",0,COUNTIFS(tbl_Partenaires_Conventions[ID Partenaire],A67,tbl_Partenaires_Conventions[Statut],"Active")) -> 0 | AW67: =IF(A67="","",IF(COUNTIFS(tbl_Partenaires_Conventions[ID Partenaire],A67,tbl_Partenaires_Conventions[Statut],"Active")=0,"NON",IF(_xlfn.MINIFS(tbl_Partenaires_Conventions[Date fin],tbl_Partenaires_Conventions[ID Partenaire],A67,tbl_Partenaires_Conventions[Statut],"Active")-TODAY()<=60,"OUI","NON"))) | AX67: =IF(A67="",0,COUNTIF(tbl_Partenaires_Documents[ID Partenaire],A67)) -> 0 | AY67: =IFERROR(AVERAGEIFS(tbl_Partenaires_Evaluations[Note globale],tbl_Partenaires_Evaluations[ID Partenaire],A67),"") | AZ67: =IFERROR(_xlfn.MAXIFS(tbl_Partenaires_Evaluations[Date evaluation],tbl_Partenaires_Evaluations[ID Partenaire],A67),"") | BA67: =IF(A67="",0,COUNTIF(tbl_Partenaires_Risques[ID Partenaire],A67)) -> 0 | BB67: =IF(A67="","",IF(COUNTIFS(tbl_Partenaires_Risques[ID Partenaire],A67,tbl_Partenaires_Risques[Niveau],"Eleve")+COUNTIFS(tbl_Partenaires_Risques[ID Partenaire],A67,tbl_Partenaires_Risques[Niveau],"Critique")>0,"OUI","NON")) | BC67: =IF(A67="",0,COUNTIF(tbl_Partenaires_Contacts[ID Partenaire],A67)) -> 0 | BD67: =IF(A67="",0,COUNTIFS(tbl_Partenaires_Opportunites[ID Partenaire],A67,tbl_Partenaires_Opportunites[Statut],"<>Cloturee")) -> 0 | BE67: =IF(A67="",0,COUNTIF(tbl_Partenaires_Prospection[ID Partenaire],A67)) -> 0 | BR67: =IF(C67="","",IF(OR(COUNTIF(C56:C115,C67)>1,AND(E67<>"",COUNTIF(E56:E115,E67)>1),AND(S67<>"",COUNTIF(S56:S115,S67)>1),AND(U67<>"",COUNTIF(U56:U115,U67)>1)),"OUI","NON"))
A68: =IF(C68="","","PART"&TEXT(ROW()-55,"00000")) | N68: =IFERROR(INDEX(PARAMETRES!$B$536:$B$586,MATCH(M68,PARAMETRES!$J$536:$J$586,0)),"") | O68: =IFERROR(INDEX(PARAMETRES!$D$536:$D$586,MATCH(M68,PARAMETRES!$J$536:$J$586,0)),"") | P68: =IFERROR(INDEX(PARAMETRES!$F$536:$F$586,MATCH(M68,PARAMETRES!$J$536:$J$586,0)),"") | Q68: =IFERROR(INDEX(PARAMETRES!$H$536:$H$586,MATCH(M68,PARAMETRES!$J$536:$J$586,0)),"") | AH68: =IFERROR(INDEX(PARAMETRES!$B$536:$B$586,MATCH(AG68,PARAMETRES!$J$536:$J$586,0)),"") | AI68: =IFERROR(INDEX(PARAMETRES!$D$536:$D$586,MATCH(AG68,PARAMETRES!$J$536:$J$586,0)),"") | AJ68: =IFERROR(INDEX(PARAMETRES!$F$536:$F$586,MATCH(AG68,PARAMETRES!$J$536:$J$586,0)),"") | AK68: =IFERROR(INDEX(PARAMETRES!$H$536:$H$586,MATCH(AG68,PARAMETRES!$J$536:$J$586,0)),"") | AR68: =IF(OR(AP68="",AQ68=""),"",AP68-AQ68) | AT68: =IF(A68="",0,COUNTIF(tbl_Partenaires_Projets[ID Partenaire],A68)) -> 0 | AU68: =IF(A68="",0,COUNTIF(tbl_Partenaires_Conventions[ID Partenaire],A68)) -> 0 | AV68: =IF(A68="",0,COUNTIFS(tbl_Partenaires_Conventions[ID Partenaire],A68,tbl_Partenaires_Conventions[Statut],"Active")) -> 0 | AW68: =IF(A68="","",IF(COUNTIFS(tbl_Partenaires_Conventions[ID Partenaire],A68,tbl_Partenaires_Conventions[Statut],"Active")=0,"NON",IF(_xlfn.MINIFS(tbl_Partenaires_Conventions[Date fin],tbl_Partenaires_Conventions[ID Partenaire],A68,tbl_Partenaires_Conventions[Statut],"Active")-TODAY()<=60,"OUI","NON"))) | AX68: =IF(A68="",0,COUNTIF(tbl_Partenaires_Documents[ID Partenaire],A68)) -> 0 | AY68: =IFERROR(AVERAGEIFS(tbl_Partenaires_Evaluations[Note globale],tbl_Partenaires_Evaluations[ID Partenaire],A68),"") | AZ68: =IFERROR(_xlfn.MAXIFS(tbl_Partenaires_Evaluations[Date evaluation],tbl_Partenaires_Evaluations[ID Partenaire],A68),"") | BA68: =IF(A68="",0,COUNTIF(tbl_Partenaires_Risques[ID Partenaire],A68)) -> 0 | BB68: =IF(A68="","",IF(COUNTIFS(tbl_Partenaires_Risques[ID Partenaire],A68,tbl_Partenaires_Risques[Niveau],"Eleve")+COUNTIFS(tbl_Partenaires_Risques[ID Partenaire],A68,tbl_Partenaires_Risques[Niveau],"Critique")>0,"OUI","NON")) | BC68: =IF(A68="",0,COUNTIF(tbl_Partenaires_Contacts[ID Partenaire],A68)) -> 0 | BD68: =IF(A68="",0,COUNTIFS(tbl_Partenaires_Opportunites[ID Partenaire],A68,tbl_Partenaires_Opportunites[Statut],"<>Cloturee")) -> 0 | BE68: =IF(A68="",0,COUNTIF(tbl_Partenaires_Prospection[ID Partenaire],A68)) -> 0 | BR68: =IF(C68="","",IF(OR(COUNTIF(C56:C115,C68)>1,AND(E68<>"",COUNTIF(E56:E115,E68)>1),AND(S68<>"",COUNTIF(S56:S115,S68)>1),AND(U68<>"",COUNTIF(U56:U115,U68)>1)),"OUI","NON"))
A69: =IF(C69="","","PART"&TEXT(ROW()-55,"00000")) | N69: =IFERROR(INDEX(PARAMETRES!$B$536:$B$586,MATCH(M69,PARAMETRES!$J$536:$J$586,0)),"") | O69: =IFERROR(INDEX(PARAMETRES!$D$536:$D$586,MATCH(M69,PARAMETRES!$J$536:$J$586,0)),"") | P69: =IFERROR(INDEX(PARAMETRES!$F$536:$F$586,MATCH(M69,PARAMETRES!$J$536:$J$586,0)),"") | Q69: =IFERROR(INDEX(PARAMETRES!$H$536:$H$586,MATCH(M69,PARAMETRES!$J$536:$J$586,0)),"") | AH69: =IFERROR(INDEX(PARAMETRES!$B$536:$B$586,MATCH(AG69,PARAMETRES!$J$536:$J$586,0)),"") | AI69: =IFERROR(INDEX(PARAMETRES!$D$536:$D$586,MATCH(AG69,PARAMETRES!$J$536:$J$586,0)),"") | AJ69: =IFERROR(INDEX(PARAMETRES!$F$536:$F$586,MATCH(AG69,PARAMETRES!$J$536:$J$586,0)),"") | AK69: =IFERROR(INDEX(PARAMETRES!$H$536:$H$586,MATCH(AG69,PARAMETRES!$J$536:$J$586,0)),"") | AR69: =IF(OR(AP69="",AQ69=""),"",AP69-AQ69) | AT69: =IF(A69="",0,COUNTIF(tbl_Partenaires_Projets[ID Partenaire],A69)) -> 0 | AU69: =IF(A69="",0,COUNTIF(tbl_Partenaires_Conventions[ID Partenaire],A69)) -> 0 | AV69: =IF(A69="",0,COUNTIFS(tbl_Partenaires_Conventions[ID Partenaire],A69,tbl_Partenaires_Conventions[Statut],"Active")) -> 0 | AW69: =IF(A69="","",IF(COUNTIFS(tbl_Partenaires_Conventions[ID Partenaire],A69,tbl_Partenaires_Conventions[Statut],"Active")=0,"NON",IF(_xlfn.MINIFS(tbl_Partenaires_Conventions[Date fin],tbl_Partenaires_Conventions[ID Partenaire],A69,tbl_Partenaires_Conventions[Statut],"Active")-TODAY()<=60,"OUI","NON"))) | AX69: =IF(A69="",0,COUNTIF(tbl_Partenaires_Documents[ID Partenaire],A69)) -> 0 | AY69: =IFERROR(AVERAGEIFS(tbl_Partenaires_Evaluations[Note globale],tbl_Partenaires_Evaluations[ID Partenaire],A69),"") | AZ69: =IFERROR(_xlfn.MAXIFS(tbl_Partenaires_Evaluations[Date evaluation],tbl_Partenaires_Evaluations[ID Partenaire],A69),"") | BA69: =IF(A69="",0,COUNTIF(tbl_Partenaires_Risques[ID Partenaire],A69)) -> 0 | BB69: =IF(A69="","",IF(COUNTIFS(tbl_Partenaires_Risques[ID Partenaire],A69,tbl_Partenaires_Risques[Niveau],"Eleve")+COUNTIFS(tbl_Partenaires_Risques[ID Partenaire],A69,tbl_Partenaires_Risques[Niveau],"Critique")>0,"OUI","NON")) | BC69: =IF(A69="",0,COUNTIF(tbl_Partenaires_Contacts[ID Partenaire],A69)) -> 0 | BD69: =IF(A69="",0,COUNTIFS(tbl_Partenaires_Opportunites[ID Partenaire],A69,tbl_Partenaires_Opportunites[Statut],"<>Cloturee")) -> 0 | BE69: =IF(A69="",0,COUNTIF(tbl_Partenaires_Prospection[ID Partenaire],A69)) -> 0 | BR69: =IF(C69="","",IF(OR(COUNTIF(C56:C115,C69)>1,AND(E69<>"",COUNTIF(E56:E115,E69)>1),AND(S69<>"",COUNTIF(S56:S115,S69)>1),AND(U69<>"",COUNTIF(U56:U115,U69)>1)),"OUI","NON"))
A70: =IF(C70="","","PART"&TEXT(ROW()-55,"00000")) | N70: =IFERROR(INDEX(PARAMETRES!$B$536:$B$586,MATCH(M70,PARAMETRES!$J$536:$J$586,0)),"") | O70: =IFERROR(INDEX(PARAMETRES!$D$536:$D$586,MATCH(M70,PARAMETRES!$J$536:$J$586,0)),"") | P70: =IFERROR(INDEX(PARAMETRES!$F$536:$F$586,MATCH(M70,PARAMETRES!$J$536:$J$586,0)),"") | Q70: =IFERROR(INDEX(PARAMETRES!$H$536:$H$586,MATCH(M70,PARAMETRES!$J$536:$J$586,0)),"") | AH70: =IFERROR(INDEX(PARAMETRES!$B$536:$B$586,MATCH(AG70,PARAMETRES!$J$536:$J$586,0)),"") | AI70: =IFERROR(INDEX(PARAMETRES!$D$536:$D$586,MATCH(AG70,PARAMETRES!$J$536:$J$586,0)),"") | AJ70: =IFERROR(INDEX(PARAMETRES!$F$536:$F$586,MATCH(AG70,PARAMETRES!$J$536:$J$586,0)),"") | AK70: =IFERROR(INDEX(PARAMETRES!$H$536:$H$586,MATCH(AG70,PARAMETRES!$J$536:$J$586,0)),"") | AR70: =IF(OR(AP70="",AQ70=""),"",AP70-AQ70) | AT70: =IF(A70="",0,COUNTIF(tbl_Partenaires_Projets[ID Partenaire],A70)) -> 0 | AU70: =IF(A70="",0,COUNTIF(tbl_Partenaires_Conventions[ID Partenaire],A70)) -> 0 | AV70: =IF(A70="",0,COUNTIFS(tbl_Partenaires_Conventions[ID Partenaire],A70,tbl_Partenaires_Conventions[Statut],"Active")) -> 0 | AW70: =IF(A70="","",IF(COUNTIFS(tbl_Partenaires_Conventions[ID Partenaire],A70,tbl_Partenaires_Conventions[Statut],"Active")=0,"NON",IF(_xlfn.MINIFS(tbl_Partenaires_Conventions[Date fin],tbl_Partenaires_Conventions[ID Partenaire],A70,tbl_Partenaires_Conventions[Statut],"Active")-TODAY()<=60,"OUI","NON"))) | AX70: =IF(A70="",0,COUNTIF(tbl_Partenaires_Documents[ID Partenaire],A70)) -> 0 | AY70: =IFERROR(AVERAGEIFS(tbl_Partenaires_Evaluations[Note globale],tbl_Partenaires_Evaluations[ID Partenaire],A70),"") | AZ70: =IFERROR(_xlfn.MAXIFS(tbl_Partenaires_Evaluations[Date evaluation],tbl_Partenaires_Evaluations[ID Partenaire],A70),"") | BA70: =IF(A70="",0,COUNTIF(tbl_Partenaires_Risques[ID Partenaire],A70)) -> 0 | BB70: =IF(A70="","",IF(COUNTIFS(tbl_Partenaires_Risques[ID Partenaire],A70,tbl_Partenaires_Risques[Niveau],"Eleve")+COUNTIFS(tbl_Partenaires_Risques[ID Partenaire],A70,tbl_Partenaires_Risques[Niveau],"Critique")>0,"OUI","NON")) | BC70: =IF(A70="",0,COUNTIF(tbl_Partenaires_Contacts[ID Partenaire],A70)) -> 0 | BD70: =IF(A70="",0,COUNTIFS(tbl_Partenaires_Opportunites[ID Partenaire],A70,tbl_Partenaires_Opportunites[Statut],"<>Cloturee")) -> 0 | BE70: =IF(A70="",0,COUNTIF(tbl_Partenaires_Prospection[ID Partenaire],A70)) -> 0 | BR70: =IF(C70="","",IF(OR(COUNTIF(C56:C115,C70)>1,AND(E70<>"",COUNTIF(E56:E115,E70)>1),AND(S70<>"",COUNTIF(S56:S115,S70)>1),AND(U70<>"",COUNTIF(U56:U115,U70)>1)),"OUI","NON"))
A71: =IF(C71="","","PART"&TEXT(ROW()-55,"00000")) | N71: =IFERROR(INDEX(PARAMETRES!$B$536:$B$586,MATCH(M71,PARAMETRES!$J$536:$J$586,0)),"") | O71: =IFERROR(INDEX(PARAMETRES!$D$536:$D$586,MATCH(M71,PARAMETRES!$J$536:$J$586,0)),"") | P71: =IFERROR(INDEX(PARAMETRES!$F$536:$F$586,MATCH(M71,PARAMETRES!$J$536:$J$586,0)),"") | Q71: =IFERROR(INDEX(PARAMETRES!$H$536:$H$586,MATCH(M71,PARAMETRES!$J$536:$J$586,0)),"") | AH71: =IFERROR(INDEX(PARAMETRES!$B$536:$B$586,MATCH(AG71,PARAMETRES!$J$536:$J$586,0)),"") | AI71: =IFERROR(INDEX(PARAMETRES!$D$536:$D$586,MATCH(AG71,PARAMETRES!$J$536:$J$586,0)),"") | AJ71: =IFERROR(INDEX(PARAMETRES!$F$536:$F$586,MATCH(AG71,PARAMETRES!$J$536:$J$586,0)),"") | AK71: =IFERROR(INDEX(PARAMETRES!$H$536:$H$586,MATCH(AG71,PARAMETRES!$J$536:$J$586,0)),"") | AR71: =IF(OR(AP71="",AQ71=""),"",AP71-AQ71) | AT71: =IF(A71="",0,COUNTIF(tbl_Partenaires_Projets[ID Partenaire],A71)) -> 0 | AU71: =IF(A71="",0,COUNTIF(tbl_Partenaires_Conventions[ID Partenaire],A71)) -> 0 | AV71: =IF(A71="",0,COUNTIFS(tbl_Partenaires_Conventions[ID Partenaire],A71,tbl_Partenaires_Conventions[Statut],"Active")) -> 0 | AW71: =IF(A71="","",IF(COUNTIFS(tbl_Partenaires_Conventions[ID Partenaire],A71,tbl_Partenaires_Conventions[Statut],"Active")=0,"NON",IF(_xlfn.MINIFS(tbl_Partenaires_Conventions[Date fin],tbl_Partenaires_Conventions[ID Partenaire],A71,tbl_Partenaires_Conventions[Statut],"Active")-TODAY()<=60,"OUI","NON"))) | AX71: =IF(A71="",0,COUNTIF(tbl_Partenaires_Documents[ID Partenaire],A71)) -> 0 | AY71: =IFERROR(AVERAGEIFS(tbl_Partenaires_Evaluations[Note globale],tbl_Partenaires_Evaluations[ID Partenaire],A71),"") | AZ71: =IFERROR(_xlfn.MAXIFS(tbl_Partenaires_Evaluations[Date evaluation],tbl_Partenaires_Evaluations[ID Partenaire],A71),"") | BA71: =IF(A71="",0,COUNTIF(tbl_Partenaires_Risques[ID Partenaire],A71)) -> 0 | BB71: =IF(A71="","",IF(COUNTIFS(tbl_Partenaires_Risques[ID Partenaire],A71,tbl_Partenaires_Risques[Niveau],"Eleve")+COUNTIFS(tbl_Partenaires_Risques[ID Partenaire],A71,tbl_Partenaires_Risques[Niveau],"Critique")>0,"OUI","NON")) | BC71: =IF(A71="",0,COUNTIF(tbl_Partenaires_Contacts[ID Partenaire],A71)) -> 0 | BD71: =IF(A71="",0,COUNTIFS(tbl_Partenaires_Opportunites[ID Partenaire],A71,tbl_Partenaires_Opportunites[Statut],"<>Cloturee")) -> 0 | BE71: =IF(A71="",0,COUNTIF(tbl_Partenaires_Prospection[ID Partenaire],A71)) -> 0 | BR71: =IF(C71="","",IF(OR(COUNTIF(C56:C115,C71)>1,AND(E71<>"",COUNTIF(E56:E115,E71)>1),AND(S71<>"",COUNTIF(S56:S115,S71)>1),AND(U71<>"",COUNTIF(U56:U115,U71)>1)),"OUI","NON"))
A72: =IF(C72="","","PART"&TEXT(ROW()-55,"00000")) | N72: =IFERROR(INDEX(PARAMETRES!$B$536:$B$586,MATCH(M72,PARAMETRES!$J$536:$J$586,0)),"") | O72: =IFERROR(INDEX(PARAMETRES!$D$536:$D$586,MATCH(M72,PARAMETRES!$J$536:$J$586,0)),"") | P72: =IFERROR(INDEX(PARAMETRES!$F$536:$F$586,MATCH(M72,PARAMETRES!$J$536:$J$586,0)),"") | Q72: =IFERROR(INDEX(PARAMETRES!$H$536:$H$586,MATCH(M72,PARAMETRES!$J$536:$J$586,0)),"") | AH72: =IFERROR(INDEX(PARAMETRES!$B$536:$B$586,MATCH(AG72,PARAMETRES!$J$536:$J$586,0)),"") | AI72: =IFERROR(INDEX(PARAMETRES!$D$536:$D$586,MATCH(AG72,PARAMETRES!$J$536:$J$586,0)),"") | AJ72: =IFERROR(INDEX(PARAMETRES!$F$536:$F$586,MATCH(AG72,PARAMETRES!$J$536:$J$586,0)),"") | AK72: =IFERROR(INDEX(PARAMETRES!$H$536:$H$586,MATCH(AG72,PARAMETRES!$J$536:$J$586,0)),"") | AR72: =IF(OR(AP72="",AQ72=""),"",AP72-AQ72) | AT72: =IF(A72="",0,COUNTIF(tbl_Partenaires_Projets[ID Partenaire],A72)) -> 0 | AU72: =IF(A72="",0,COUNTIF(tbl_Partenaires_Conventions[ID Partenaire],A72)) -> 0 | AV72: =IF(A72="",0,COUNTIFS(tbl_Partenaires_Conventions[ID Partenaire],A72,tbl_Partenaires_Conventions[Statut],"Active")) -> 0 | AW72: =IF(A72="","",IF(COUNTIFS(tbl_Partenaires_Conventions[ID Partenaire],A72,tbl_Partenaires_Conventions[Statut],"Active")=0,"NON",IF(_xlfn.MINIFS(tbl_Partenaires_Conventions[Date fin],tbl_Partenaires_Conventions[ID Partenaire],A72,tbl_Partenaires_Conventions[Statut],"Active")-TODAY()<=60,"OUI","NON"))) | AX72: =IF(A72="",0,COUNTIF(tbl_Partenaires_Documents[ID Partenaire],A72)) -> 0 | AY72: =IFERROR(AVERAGEIFS(tbl_Partenaires_Evaluations[Note globale],tbl_Partenaires_Evaluations[ID Partenaire],A72),"") | AZ72: =IFERROR(_xlfn.MAXIFS(tbl_Partenaires_Evaluations[Date evaluation],tbl_Partenaires_Evaluations[ID Partenaire],A72),"") | BA72: =IF(A72="",0,COUNTIF(tbl_Partenaires_Risques[ID Partenaire],A72)) -> 0 | BB72: =IF(A72="","",IF(COUNTIFS(tbl_Partenaires_Risques[ID Partenaire],A72,tbl_Partenaires_Risques[Niveau],"Eleve")+COUNTIFS(tbl_Partenaires_Risques[ID Partenaire],A72,tbl_Partenaires_Risques[Niveau],"Critique")>0,"OUI","NON")) | BC72: =IF(A72="",0,COUNTIF(tbl_Partenaires_Contacts[ID Partenaire],A72)) -> 0 | BD72: =IF(A72="",0,COUNTIFS(tbl_Partenaires_Opportunites[ID Partenaire],A72,tbl_Partenaires_Opportunites[Statut],"<>Cloturee")) -> 0 | BE72: =IF(A72="",0,COUNTIF(tbl_Partenaires_Prospection[ID Partenaire],A72)) -> 0 | BR72: =IF(C72="","",IF(OR(COUNTIF(C56:C115,C72)>1,AND(E72<>"",COUNTIF(E56:E115,E72)>1),AND(S72<>"",COUNTIF(S56:S115,S72)>1),AND(U72<>"",COUNTIF(U56:U115,U72)>1)),"OUI","NON"))
